Workbook

Sheet Summary
A1: F&B price-source coverage - global sweep
A2: Built 2026-08-06 from 18 probe agents across all six regions (eap, eca, ssa, sar, menaap, lac). Denominator throughout: 279 deep COICOP F&B leaves (269 in division 01, 10 in division 02).
A4: The sweep
A5: Candidates in your list | B5: =COUNTA(All_Candidates_685!A2:A686) | C5: rows in price_scraping_global_sources_fnb.csv
A6: Probed and viable | B6: =COUNTIF(All_Candidates_685!G2:G686,"PROBED - VIABLE") | C6: list rows that verified (list has duplicate domains, so this exceeds distinct sources)
A7: Probed and rejected | B7: =COUNTIF(All_Candidates_685!G2:G686,"PROBED - SKIP") | C7: network trace on file showing they are not usable
A8: Not probed | B8: =COUNTIF(All_Candidates_685!G2:G686,"NOT PROBED*") | C8: duplicate domain, already onboarded, or time-boxed out
A9: Total viable sources found | B9: =COUNTA(All_Viable_340!A2:A341) | C9: includes net-new finds that were NOT in your list - see Discovered_NetNew
A11: Build plan
A12: Ready now (low effort) | B12: =COUNTA(Build_Plan_215!A2:A216) | C12: endpoint verified, real sample product captured
A13: Wave 1 - WFP/CKAN fetcher extension | B13: =COUNTIF(Build_Plan_215!G2:G216,"Wave 1") | C13: ONE line each in an existing _PANELS dict. Cheapest work in the plan. Date-check each panel - stale ones exist.
A14: Wave 2 - off-the-shelf platforms | B14: =COUNTIF(Build_Plan_215!G2:G216,"Wave 2") | C14: VTEX / Shopify / WooCommerce / Magento / PrestaShop / OpenCart / NCR Freshop -> 7 generic spiders cover all of them
A15: Wave 3 - bespoke | B15: =COUNTIF(Build_Plan_215!G2:G216,"Wave 3") | C15: one custom spider or fetcher each - this is the real cost
A16: Needs more work | B16: =COUNTA(Remaining_125!A2:A126)
A17: Wave 4 - endpoint known, harder parse | B17: =COUNTIF(Remaining_125!E2:E126,"TIER_1A")+COUNTIF(Remaining_125!E2:E126,"TIER_1B") | C17: pagination, auth or awkward parsing
A18: Wave 5 - needs a discovery pass | B18: =COUNTIF(Remaining_125!E2:E126,"TIER_2") | C18: Playwright to FIND the JSON endpoint, then scrape it over plain HTTP
A20: Of the ready set: spiders to write | B20: =COUNTIF(Build_Plan_215!H2:H216,"spider")
A21: Of the ready set: fetchers to write | B21: =COUNTIF(Build_Plan_215!H2:H216,"fetcher")
A22: Distinct build units | B22: =COUNTIF(Build_Plan_215!J2:J216,"Z_bespoke")+8 | C22: bespoke sources + 7 generic platform spiders + 1 fetcher edit. Far below the raw source count.
A24: Where we lack COUNTRY coverage
A25: Countries assessed | B25: =COUNTA(Country_Coverage!B2:B161)
A26: at 50% or more of the 279 leaves | B26: =COUNTIF(Country_Coverage!E2:E161,">=50")
A27: at 30-50% | B27: =COUNTIFS(Country_Coverage!E2:E161,">=30",Country_Coverage!E2:E161,"<50")
A28: under 30% - THE GAP LIST | B28: =COUNTIF(Country_Coverage!E2:E161,"<30") | C28: itemised on Country_Gaps
A29: at zero | B29: =COUNTIF(Country_Coverage!E2:E161,0) | C29: all six Gulf states are here - one WAF, six countries
A31: Where we lack LEAF coverage (division 01)
A32: Leaves already covered | B32: =COUNTIF(Leaf_Gaps_Div01!D2:D270,"ok")
A33: Absent from EAP retail - NEW SOURCES FIX THESE | B33: =COUNTIF(Leaf_Gaps_Div01!D2:D270,"out_of_region") | C33: teff, sorghum/millet flour, camel meat and milk, cowpeas, pigeon peas, bambara beans, cocoa beans, olives, yautia, quinoa - the direct payoff of this sweep
A34: Flagged sourcing_gap | B34: =COUNTIF(Leaf_Gaps_Div01!D2:D270,"sourcing_gap") | C34: TREAT AS HYPOTHESIS - most past ones turned out to be gold gaps, not source gaps
A35: Quantity / unit-value problem | B35: =COUNTIF(Leaf_Gaps_Div01!D2:D270,"trusted_tier") | C35: no new source fixes these
A36: Unreachable by design | B36: =COUNTIF(Leaf_Gaps_Div01!D2:D270,"catch_all")+COUNTIF(Leaf_Gaps_Div01!D2:D270,"out_of_scope")
A38: Read this before trusting the numbers
A39: Leaf counts per country are ESTIMATES, not leaf lists. | C39: Agents estimated HOW MANY of the 279 leaves each source reaches, from catalog categories they actually saw. They did not enumerate WHICH leaves. There is no country-by-leaf matrix here and there cannot be one until these sources are collected and classified.
A40: Leaf_Gaps_Div01 is measured on the CURRENT corpus, which is EAP-dominant. | C40: It is the authoritative answer to "which deep leaves lack coverage" today. Division 01 only (269 of the 279).
A41: Leaf_Gaps_Div01 is a SNAPSHOT of leaf_support_table.csv taken 2026-08-06 12:28. | C41: That table is regenerated by the classifier pipeline and it MOVES. During the build of this workbook a v20 classifier run rewrote it and shifted 14 leaves into "ok" (out_of_region 21 -> 16, sourcing_gap 29 -> 19). Re-run src/prices/build/leaf_support.py and rebuild this sheet before acting on the counts.
A42: EAP rows in Country_Coverage are scope-limited. | C42: The EAP agents only looked at Pacific Islands and official/wholesale feeds. A low or zero EAP number means "no such feed found", NOT "no coverage" - EAP already has 297 manifests that were not re-measured.
A43: Your list grades poorly. | C43: Verdict is a weak prior (ACCEPT 55% viable, SUSPECT 30%, REJECT 10%). Build tier is NOISE - tier B scored 14%, worse than rows with no tier at all (55%). Do not prioritise by it. Platform labels are also unreliable - several Bolivian rows labelled VTEX/Custom are actually Shopify.
A44: A manifest existing does not mean F&B coverage exists. | C44: Six confirmed cases where an onboarded source turned out to be electronics, cosmetics, craft or pharmacy.
A45: A zero country is usually not structurally empty. | C45: Most zeros are SPA-shelled, auth-gated or WAF-blocked storefronts that a Playwright discovery pass may still crack. Treat Country_Gaps as a work queue, not a verdict.

Sheet Build_Plan_215
A1: region | B1: slug | C1: source | D1: url | E1: tier | F1: effort | G1: build_wave | H1: scaffolding | I1: build_approach | J1: bucket | K1: platform | L1: analytical_role | M1: channel | N1: currency | O1: fnb_leaves_est | P1: endpoint | Q1: evidence | R1: in_csv | S1: notes | T1: gotcha
A2: ssa | B2: ethiopia | C2: WFP Food Prices (HDX) -- Ethiopia | D2: https://data.humdata.org/dataset/wfp-food-prices-for-ethiopia | E2: TIER_1B | F2: low | G2: Wave 1 | H2: fetcher | I2: Extend _PANELS in src/prices/fetchers/_shared/eap/wfp_food_prices.py - one line per country, no new code. DATE-CHECK each panel first. | J2: A_wfp_ckan | K2: WFP/HDX CKAN | L2: official_avg | M2: official_avg | N2: ETB | O2: 45 | P2: https://data.humdata.org/api/3/action/package_show?id=wfp-food-prices-for-ethiopia | Q2: CKAN resolved -> wfp_food_prices_eth.csv, 62,131 rows. 96 distinct commodities -- richest WFP panel in this shard: full cereal set (wheat/barley/maize/sorghum/teff, each in 2-5 sub-varieties), legumes (beans x6 varieties, chickpeas, lentils, peas x3), dairy (milk, camel milk, butter x2), live animals (bull/camel/cattle/donkey/goat/ox/sheep), produce (avocado/banana/beetroot/cabbage/carrots/garlic/guava/kale/lettuce/mango/onions/oranges/papaya/potatoes/swiss chard/sweet potatoes/tomatoes), coffee, honey, oils, pasta, salt, sesame, sugar. | R2: FALSE | S2: By far the biggest single lever for Ethiopia's F&B coverage -- reaches teff (all 4 sub-varieties), live animals, and multiple dairy/legume forms that no retail source in this shard touches.
A3: lac | B3: guatemala | C3: WFP Food Prices - Guatemala | D3: https://data.humdata.org/dataset/wfp-food-prices-for-guatemala | E3: TIER_1B | F3: low | G3: Wave 1 | H3: fetcher | I3: Extend _PANELS in src/prices/fetchers/_shared/eap/wfp_food_prices.py - one line per country, no new code. DATE-CHECK each panel first. | J3: A_wfp_ckan | K3: CKAN/WFP HDX | L3: official_avg | M3: wholesale/retail (mixed) | N3: GTQ | O3: 45 | P3: CKAN dataset wfp-food-prices-for-guatemala, resource wfp_food_prices_gtm.csv | Q3: GET CSV https://data.humdata.org/dataset/.../wfp_food_prices_gtm.csv -> HTTP 200, 2.29MB, 16,178 rows. Max date confirmed 2026-06-15 (live/recent). Sample: 'Maize (white)' 100 Pounds, Wholesale, La Terminal market, GTQ 67.75 (2026-06-15). Also carrots, onions, tomatoes, beans, coffee, bananas. | R3: FALSE | S3: Wholesale + some retail channel, La Terminal market Guatemala City + others; complements but barely overlaps supermarket SKUs (fresh produce/grains/pulses focus).
A4: menaap | B4: syria | C4: WFP Food Prices - Syria (HDX) | D4: https://data.humdata.org/dataset/aa40b3a8-2bc4-4826-9d82-82189bc5f392 | E4: TIER_1B | F4: low | G4: Wave 1 | H4: fetcher | I4: Extend _PANELS in src/prices/fetchers/_shared/eap/wfp_food_prices.py - one line per country, no new code. DATE-CHECK each panel first. | J4: A_wfp_ckan | K4: WFP/HDX CKAN | L4: official_avg | M4: official_avg | N4: SYP | O4: 44 | P4: CKAN package_show -> S3 CSV | Q4: CKAN package_show -> 200, resolves wfp_food_prices_syr.csv, 275,972 rows - by far the largest panel in the set. 77 distinct commodities across all 8 categories: fruit (apples, bananas), veg (cabbage, carrots, cucumbers x2, eggplant, garlic, parsley, pumpkin, spinach, tomatoes fresh+paste), dairy (cheese x2, labaneh, fresh milk, yogurt), meat (beef minced, chicken legs/plucked, sheep), cereals (bulgur, maize local, wheat, 3 bread variants, 2 pasta variants, rice), pulses (3 bean types, lentils, 2 pea types, chickpeas), oils/fats (oil, ghee), plus sugar/salt/tea/yeast/peanut. | R4: FALSE | S4: Syria's WFP panel is the deepest of the entire shard because of dedicated crisis-monitoring granularity (parallel-market fuel/bread variants tracked separately). One-line _PANELS addition: 'syr': ('Syria', 'wfp-food-prices-for-syrian-arab-republic').
A5: ssa | B5: rwanda | C5: WFP Rwanda (HDX) | D5: https://data.humdata.org/dataset/a4a84c1c-81d1-491b-9fbe-1955ae736508 | E5: TIER_1B | F5: low | G5: Wave 1 | H5: fetcher | I5: Extend _PANELS in src/prices/fetchers/_shared/eap/wfp_food_prices.py - one line per country, no new code. DATE-CHECK each panel first. | J5: A_wfp_ckan | K5: Custom (CKAN/HDX) | L5: official_avg | M5: official_avg | N5: RWF | O5: 42 | P5: https://data.humdata.org/api/3/action/package_show?id=wfp-food-prices-for-rwanda | Q5: CKAN-resolved CSV wfp_food_prices_rwa.csv (200, 19.9MB, richest+largest panel in this shard). 151,961 rows, 65 distinct commodities, max date 2026-06-15. Extremely granular: apples, avocados, guava, mangoes, passion fruit, papaya, oranges, cauliflower, greenhouse cucumbers, zucchini, soybeans, sorghum flour, 4+ rice-origin variants, 5 livestock species (live), 4 meat species. | R5: FALSE | S5: Best WFP panel discovered across the whole shard by both commodity count and row count -- essentially a near-retail-resolution market-price census. With every retail candidate in this shard unconfirmed, this feed alone is Rwanda's current F&B backbone.
A6: lac | B6: el_salvador | C6: WFP Food Prices - El Salvador | D6: https://data.humdata.org/dataset/wfp-food-prices-for-el-salvador | E6: TIER_1B | F6: low | G6: Wave 1 | H6: fetcher | I6: Extend _PANELS in src/prices/fetchers/_shared/eap/wfp_food_prices.py - one line per country, no new code. DATE-CHECK each panel first. | J6: A_wfp_ckan | K6: CKAN/WFP HDX | L6: official_avg | M6: wholesale/retail (mixed) | N6: USD | O6: 40 | P6: CKAN dataset wfp-food-prices-for-el-salvador, resource wfp_food_prices_slv.csv | Q6: GET CSV -> HTTP 200, 7,561 rows, max date confirmed 2026-06-15 (live). Sample: 'Maize (white)' 46 KG Wholesale San Salvador USD 26.49 (2026-06-15); also 'Maize (white)' Libra Retail USD 0.34. | R6: FALSE | S6: Both wholesale and retail channel rows present; national-average style market coverage.
A7: lac | B7: nicaragua | C7: WFP Food Prices - Nicaragua | D7: https://data.humdata.org/dataset/wfp-food-prices-for-nicaragua | E7: TIER_1B | F7: low | G7: Wave 1 | H7: fetcher | I7: Extend _PANELS in src/prices/fetchers/_shared/eap/wfp_food_prices.py - one line per country, no new code. DATE-CHECK each panel first. | J7: A_wfp_ckan | K7: CKAN/WFP HDX | L7: official_avg | M7: retail | N7: USD | O7: 35 | P7: CKAN dataset wfp-food-prices-for-nicaragua, resource wfp_food_prices_nic.csv | Q7: GET CSV -> HTTP 200, max date confirmed 2026-05-15 (live). Sample: 'Plantains' Pound, Retail, National Average, USD 0.44 (2026-05-15); also squashes, tomatoes. | R7: FALSE | S7: Retail national-average channel, fresh produce focus.
A8: menaap | B8: west_bank_and_gaza | C8: WFP Food Prices - State of Palestine (HDX) | D8: https://data.humdata.org/dataset/7d06b059-5831-4101-aa68-6d9123ad65b7 | E8: TIER_1B | F8: low | G8: Wave 1 | H8: fetcher | I8: Extend _PANELS in src/prices/fetchers/_shared/eap/wfp_food_prices.py - one line per country, no new code. DATE-CHECK each panel first. | J8: A_wfp_ckan | K8: WFP/HDX CKAN | L8: official_avg | M8: official_avg | N8: ILS | O8: 33 | P8: CKAN package_show -> S3 CSV | Q8: CKAN package_show?id=wfp-food-prices-for-state-of-palestine -> 200, resolves wfp_food_prices_pse.csv, 26,815 rows. 41 commodities: fruit (apples, bananas, oranges), veg (cauliflower, cucumbers, eggplant, onions, tomatoes greenhouse), dairy (goat cheese, labaneh, milk pasteurized + powder, yogurt), meat (beef, chicken, goat), 3 rice varieties, 2 oil types (maize + olive), semolina, bottled water. | R8: FALSE | S8: Repo slug is 'west_bank_and_gaza' (iso3 PSE per countries.yaml) - HDX dataset slug is 'wfp-food-prices-for-state-of-palestine'. One-line _PANELS addition: 'pse': ('State of Palestine', 'wfp-food-prices-for-state-of-palestine').
A9: ssa | B9: malawi | C9: WFP Food Prices (HDX) -- Malawi | D9: https://data.humdata.org/dataset/wfp-food-prices-for-malawi | E9: TIER_1B | F9: low | G9: Wave 1 | H9: fetcher | I9: Extend _PANELS in src/prices/fetchers/_shared/eap/wfp_food_prices.py - one line per country, no new code. DATE-CHECK each panel first. | J9: A_wfp_ckan | K9: WFP/HDX CKAN | L9: official_avg | M9: official_avg | N9: MWK | O9: 30 | P9: https://data.humdata.org/api/3/action/package_show?id=wfp-food-prices-for-malawi | Q9: CKAN resolved -> wfp_food_prices_mwi.csv, 82,819 rows. 63 distinct commodities -- notably rich in Malawi-specific leafy greens (Amaranthus, Blackjack leaves, Cowpea leaves, Mustard leaves, Pumpkin leaves, Rape leaves) and dried small fish (bonya, kapenta, matemba, usipa, utaka), plus cereals/legumes/tubers/oil/sugar. | R9: FALSE | S9: Second-richest WFP panel in the shard. The leafy-greens and dried-fish depth here is not replicated by any retailer in this pass -- structurally complementary, not overlapping.
A10: menaap | B10: jordan | C10: WFP Food Prices - Jordan (HDX) | D10: https://data.humdata.org/dataset/fba510fd-eccf-4b34-b5f6-cc531900270b | E10: TIER_1B | F10: low | G10: Wave 1 | H10: fetcher | I10: Extend _PANELS in src/prices/fetchers/_shared/eap/wfp_food_prices.py - one line per country, no new code. DATE-CHECK each panel first. | J10: A_wfp_ckan | K10: WFP/HDX CKAN | L10: official_avg | M10: official_avg | N10: JOD | O10: 29 | P10: CKAN package_show -> S3 CSV | Q10: CKAN package_show -> 200, resolves wfp_food_prices_jor.csv, 47,943 rows. 36 commodities across all 8 categories including both olive oil AND vegetable oil as separate lines, apples/bananas/oranges (fruit), cucumbers/garlic/onions/spinach/tomatoes (veg), beef/chicken/lamb (meat), two cheese types + two milk types (dairy) - the richest, most balanced panel of the whole shard. | R10: FALSE | S10: One-line _PANELS addition: 'jor': ('Jordan', 'wfp-food-prices-for-jordan').
A11: ssa | B11: kenya | C11: WFP Kenya (HDX) | D11: https://data.humdata.org/dataset/e0d3fba6-f9a2-45d7-b949-140c455197ff | E11: TIER_1B | F11: low | G11: Wave 1 | H11: fetcher | I11: Extend _PANELS in src/prices/fetchers/_shared/eap/wfp_food_prices.py - one line per country, no new code. DATE-CHECK each panel first. | J11: A_wfp_ckan | K11: Custom (CKAN/HDX, same pattern as existing src/prices/fetchers/_shared/eap/wfp_food_prices.py) | L11: official_avg | M11: official_avg | N11: KES | O11: 28 | P11: https://data.humdata.org/api/3/action/package_show?id=wfp-food-prices-for-kenya | Q11: CKAN package_show resolved CSV at wfp_food_prices_ken.csv (200, 3.6MB). 27,837 rows, 51 distinct commodities, max date 2026-07-15 (current). Retail+wholesale mixed pricetype. Sample: Maize (white) KES 1480/90kg wholesale Mombasa. | R11: FALSE | S11: Direct extension of the existing shared EAP WFP fetcher module -- just add ken to the _PANELS dict. 51 commodities incl. camel meat/milk (not covered by any retailer) is the standout addition.
A12: ssa | B12: central_african_republic | C12: WFP Central African Republic (HDX) | D12: https://data.humdata.org/dataset/e9f27b34-f511-498c-a7f8-fe8d2321f7ba | E12: TIER_1B | F12: low | G12: Wave 1 | H12: fetcher | I12: Extend _PANELS in src/prices/fetchers/_shared/eap/wfp_food_prices.py - one line per country, no new code. DATE-CHECK each panel first. | J12: A_wfp_ckan | K12: Custom (CKAN/HDX) | L12: official_avg | M12: official_avg | N12: XAF | O12: 28 | P12: https://data.humdata.org/api/3/action/package_show?id=wfp-food-prices-for-central-african-republic | Q12: CKAN-resolved CSV wfp_food_prices_caf.csv (200, 3.6MB). 30,356 rows, 39 distinct commodities (tied with Rwanda for richest panel in this shard), max date 2026-06-15. Commodities incl. Meat (antelope smoked, gazelle smoked -- bushmeat), Fish (catfish/frozen/sardine canned/smoked), Sesame, Groundnuts (shelled/unshelled), Charcoal. | R12: FALSE | S12: With no live retail candidate, this is effectively the ONLY viable F&B price source for CAR in this shard. The bushmeat commodities (antelope, gazelle) are a rare hit on the 'Other meat' leaf (01.1.2.2.9) that almost no supermarket source in the wider repo reaches.
A13: menaap | B13: iraq | C13: WFP Food Prices - Iraq (HDX) | D13: https://data.humdata.org/dataset/7d8955eb-37d2-4087-80e9-cae1aaa242f5 | E13: TIER_1B | F13: low | G13: Wave 1 | H13: fetcher | I13: Extend _PANELS in src/prices/fetchers/_shared/eap/wfp_food_prices.py - one line per country, no new code. DATE-CHECK each panel first. | J13: A_wfp_ckan | K13: WFP/HDX CKAN | L13: official_avg | M13: official_avg | N13: IQD | O13: 26 | P13: CKAN package_show -> S3 CSV | Q13: CKAN package_show -> 200, resolves wfp_food_prices_irq.csv, 56,712 rows. 49 commodities - largest non-Syria commodity list, includes dates, eggplant, cheese (local), yogurt, three rice varieties (regular/Indian/basmati), three wheat-flour sourcing variants (Turkey/local/generic). | R13: FALSE | S13: One-line _PANELS addition: 'irq': ('Iraq', 'wfp-food-prices-for-iraq').
... A118: menaap | B118: libya | C118: Al Mustawda (big.ly) | D118: https://big.ly/food | E118: TIER_1A | F118: low | G118: Wave 2 | H118: spider | I118: Generic OpenCart spider | J118: G_opencart | K118: OpenCart | L118: retailer_sku | M118: supermarket | N118: LYD | O118: 20 | P118: /food (OpenCart category route, SSR) | Q118: curl GET https://big.ly/food -> 200, 208KB HTML. OpenCart platform (theme 'renoxa'). Dedicated /food category (h2 title 'طعام'). Product cards parse cleanly: 'باذنجان' (Eggplant) 6.00 د.ل, 'بازلاء خضراء' (Green peas) 6.00 د.ل, 'بصل أحمر جاف' (Dry red onion) 3.50 د.ل. | R118: TRUE | S118: Sample was the fresh-produce subcategory only; '20,000+ completed orders' per CSV note suggests a larger catalog behind /food's 'subcategories' menu than what I paginated. Re-probe to enumerate all food subcategories before scaffolding.
A119: sar | B119: sri_lanka | C119: Carkeells | D119: https://carkeells.lk/en-gb/catalog/grocery | E119: TIER_1A | F119: low | G119: Wave 2 | H119: spider | I119: Generic OpenCart spider | J119: G_opencart | K119: OpenCart | L119: retailer_sku | M119: pharmacy | N119: LKR | O119: 15 | Q119: curl 200/21-64KB, plain OpenCart SSR HTML, `opencart` string present in body. GET /en-gb/catalog/grocery/food-products -> 200/64KB with real prices: Rs.525.00, Rs.375.00, Rs.595.00, Rs.160.00 etc (excluding a Rs.0.00 placeholder row). Confirmed as shard's own AI_NOTES suggested: a small grocery/beverages tail (2 subcategories) bolted onto a cosmetics/health/haircare-dominant OpenCart store. | R119: TRUE | S119: Real but tiny (~55 SKUs total across grocery+beverages per shard notes). Low priority -- everything it carries is already covered more deeply by Glomark/OnlineKade/SPAR2U.
A120: lac | B120: jamaica | C120: CoolMarket Groceries | D120: https://www.coolmarket.com/groceries.html | E120: TIER_1A | F120: low | G120: Wave 2 | H120: spider | I120: Generic Magento/GraphQL spider (incl. the mcprod.<domain> pattern) | J120: H_magento | K120: Magento | L120: retailer_sku | M120: supermarket | N120: JMD | O120: 170 | P120: SSR HTML Magento listing/PDP (data-price-amount attrs) | Q120: curl 200/4.04MB (Magento). data-price-amount attributes throughout: 'NESTLÉ Kit Kat 4 Bar Milk Chocolate 45g' JMD 204.00. 591 product-item-link matches on this single paginated listing page, consistent with CSV's '1,386 grocery items' claim. | R120: TRUE | S120: CSV called this the best Jamaica source; confirmed — deep grocery catalog with clean Magento price markup.
A121: menaap | B121: egypt | C121: Spinneys Egypt | D121: https://spinneys-egypt.com/ | E121: TIER_1B | F121: low | G121: Wave 2 | H121: spider | I121: Generic Magento/GraphQL spider (incl. the mcprod.<domain> pattern) | J121: H_magento | K121: Nuxt + Magento 2 (mcprod.<domain> backend pattern) | L121: retailer_sku | M121: supermarket | N121: EGP | O121: 165 | P121: https://mcprod.spinneys-egypt.com/graphql (Magento GraphQL, POST, no auth) | Q121: curl homepage -> 200, Nuxt fingerprint, config.apiURL 'https://spinneys-egypt.com/graphql' (direct proxy 400s on POST body, use mcprod subdomain instead). Direct curl POST to https://mcprod.spinneys-egypt.com/graphql (search:'rice') -> 200 clean JSON: 'El Shorouk Rice - 5 Kg' EGP 163.95, 'Dayma Rice - 1K' EGP 45.25. | R121: TRUE | S121: Upper-mid chain, third confirmed 'mcprod.<retailer-domain>/graphql' Magento site in Egypt (with Hyper One, Seoudi) -- strong signal of a shared storefront vendor to check for more Egyptian retailers on this stack. Categories incl. Fruits&Vegetables(916), Meat&Poultry(135), Seafood&Fish(137), Cheese/Dairy/Eggs(1844), Bakery&Bread(460), Frozen(998).
A122: menaap | B122: tunisia | C122: Carrefour Tunisia | D122: https://www.carrefour.tn/ | E122: TIER_1B | F122: low | G122: Wave 2 | H122: spider | I122: Generic Magento/GraphQL spider (incl. the mcprod.<domain> pattern) | J122: H_magento | K122: Magento 2 | L122: retailer_sku | M122: supermarket | N122: TND | O122: 165 | P122: /graphql (Magento GraphQL, POST, no auth) | Q122: curl homepage -> 200 but tiny 8.8KB SPA shell (data-media-backend=back.carrefour.tn). Playwright network trace found same-origin GraphQL traffic at /graphql. Direct curl POST to https://www.carrefour.tn/graphql (search:'riz') -> 200 clean JSON, NO Cloudflare/Akamai block: 'Riz Djerbien' TND 19.20, 'Riz Basmati' TND 8.49. categoryList query confirms full hypermarket taxonomy. | R122: FALSE | S122: Found via local operator search, not CSV. Distinct backend/operator from Carrefour Egypt's MAF/Akamai stack -- not WAF-hardened at all. Categories: Le marché(1082, likely fresh produce/meat/fish), Épicerie Salée(1292), Épicerie Sucrée(1654), Crèmerie et Produits Laitiers(671), Surgelés(312), Boissons(335). Strongest single Tunisia source found.
A123: menaap | B123: egypt | C123: Seoudi Market | D123: https://seoudisupermarket.com/ | E123: TIER_1B | F123: low | G123: Wave 2 | H123: spider | I123: Generic Magento/GraphQL spider (incl. the mcprod.<domain> pattern) | J123: H_magento | K123: Nuxt + Magento 2 (mcprod.<domain> backend pattern) | L123: retailer_sku | M123: supermarket | N123: EGP | O123: 160 | P123: https://mcprod.seoudisupermarket.com/graphql (Magento GraphQL, POST, no auth) | Q123: curl homepage -> 200, Magento+Nuxt fingerprint. Page source contains apiURL 'https://mcprod.seoudisupermarket.com/graphql'. Direct curl POST (search:'rice') -> 200 clean JSON: 'Al Doha Beyti Rice, Easy Rice Edition - 320g' EGP 25.75, 'Rehana Rice - 1kg' EGP 40.45. | R123: TRUE | S123: Established Cairo chain. Categories incl. Fruits&Vegetables(616), Meat/Poultry/Fishery(216), Dairy/Eggs/Cheese(1385), Cold Cuts&Deli(240), Bakery(471), Frozen(1146), Hot Drinks(1093). Same vendor pattern as Hyper One -- likely a shared Egyptian Magento/Nuxt storefront agency worth checking for other Egyptian retailers.
A124: menaap | B124: egypt | C124: Hyper One | D124: https://www.hyperone.com.eg/ | E124: TIER_1B | F124: low | G124: Wave 2 | H124: spider | I124: Generic Magento/GraphQL spider (incl. the mcprod.<domain> pattern) | J124: H_magento | K124: Nuxt + Magento 2 (mcprod.<domain> backend pattern) | L124: retailer_sku | M124: supermarket | N124: EGP | O124: 155 | P124: https://mcprod.hyperone.com.eg/graphql (Magento GraphQL, POST, no auth) | Q124: Bare domain hyperone.com.eg does not resolve; www. subdomain -> 200, Nuxt SPA. window.__NUXT__.config exposes apiUrl 'https://mcprod.hyperone.com.eg/graphql'. Direct curl POST to that endpoint (search:'rice') -> 200 clean JSON: 'Top Value Luxury Egyptian Rice - 1K' EGP 26.95, 'Meeza Egyptian Rice -1K' EGP 25.95. (The site's own www.hyperone.com.eg/graphql proxy path 400s on malformed body -- use the mcprod subdomain directly.) | R124: TRUE | S124: Large Egyptian-owned hypermarket, welfare-relevant per CSV. Categories incl. Fruits&Vegetables(172), Butchery&Poultry(59), Seafood(28), Dairy/Eggs/Cheese(521), Bakery(125), Herbs&Spices(291), Pickles(37).
A125: menaap | B125: egypt | C125: Gourmet Egypt | D125: https://gourmetegypt.com/ | E125: TIER_1B | F125: low | G125: Wave 2 | H125: spider | I125: Generic Magento/GraphQL spider (incl. the mcprod.<domain> pattern) | J125: H_magento | K125: Magento 2 | L125: retailer_sku | M125: supermarket | N125: EGP | O125: 150 | P125: /graphql (Magento GraphQL, POST, no auth) | Q125: curl homepage -> 200, Magento fingerprint. REST /rest/V1/products -> 401 (needs token, expected default). GraphQL POST /graphql (search:'rice') -> 200, clean JSON: 'Kohinoor Basmati Rice' EGP 195, 'Tilda Basmati Rice' EGP 180. categoryList query confirms full-line taxonomy. | R125: TRUE | S125: Premium/imported grocer. Categories: Meat/Poultry/Seafood(380), Bakery(317), Dairy&Eggs(637), Fruits&Vegetables(362), Frozen(568), Food Cupboard(1453), Beverages(871), Desserts(296), Chips&Snacks(469), Chocolate&Sweets(796).
A126: ssa | B126: kenya | C126: Chandarana Foodplus | D126: https://foodplus.co.ke/ | E126: TIER_1B | F126: low | G126: Wave 2 | H126: spider | I126: Generic Magento/GraphQL spider (incl. the mcprod.<domain> pattern) | J126: H_magento | K126: Magento | L126: retailer_sku | M126: supermarket | N126: KES | O126: 150 | P126: /rest/V1/products, /rest/V1/categories | Q126: The CSV's domain (chandaranafoodplus.com) is NXDOMAIN. Real domain foodplus.co.ke resolves and is Magento (not WooCommerce as CSV's platform column claims). GET /rest/V1/categories -> 200, no auth, full taxonomy incl. Fresh Fruits(146)/Fresh Vegetables(291)/Milk Butter Eggs(157)/Yoghurt(306)/Cheese(244)/Fresh Meat(102)/Deli(90), 18,205 products total. GET /rest/V1/products?searchCriteria[pageSize]=3 -> 200, 8KB JSON, sample 'C/CARE SCRUBBING BRUSH HANDLE A14' KES 165. | R126: TRUE | S126: Premium/expatriate chain per CSV; deepest single-source taxonomy verified in this shard. Domain correction is the key finding -- CSV's chandaranafoodplus.com does not resolve at all.
A127: lac | B127: panama | C127: Riba Smith | D127: https://www.ribasmith.com/ | E127: TIER_1B | F127: low | G127: Wave 2 | H127: spider | I127: Generic Magento/GraphQL spider (incl. the mcprod.<domain> pattern) | J127: H_magento | K127: Magento 2 | L127: retailer_sku | M127: supermarket | N127: USD | O127: 150 | P127: /graphql | Q127: POST /graphql {products(search:"arroz",pageSize:5){...}} -> HTTP 200 JSON. Sample: 'ARROZ PELIN ARROZ ESPECIAL 20 LBS' USD 16.48. | R127: FALSE | S127: Full-line premium PA chain; GraphQL open, no auth required for product search.
A128: lac | B128: dominican_republic | C128: Supermercados Nacional | D128: https://www.supermercadosnacional.com/ | E128: TIER_1B | F128: low | G128: Wave 2 | H128: spider | I128: Generic Magento/GraphQL spider (incl. the mcprod.<domain> pattern) | J128: H_magento | K128: Magento 2 | L128: retailer_sku | M128: supermarket | N128: DOP | O128: 150 | P128: /graphql | Q128: POST /graphql {products(search:"arroz",pageSize:5){...}} -> HTTP 200 JSON. Sample: 'Arroz Selecto Líder 10 Lb' DOP 327.95. | R128: FALSE | S128: Full-line DR chain, GraphQL open.
A129: lac | B129: curacao | C129: Van den Tweel Supermarket | D129: https://shopvdtcuracao.com/ | E129: TIER_1B | F129: low | G129: Wave 2 | H129: spider | I129: Generic Magento/GraphQL spider (incl. the mcprod.<domain> pattern) | J129: H_magento | K129: Magento 2 | L129: retailer_sku | M129: supermarket | N129: ANG | O129: 140 | P129: /graphql | Q129: POST /graphql {products(search:"melk",pageSize:5){...}} -> HTTP 200 JSON. Sample: 'AH Volle melk' ANG 3.29; also 'AH Magere melk' ANG 2.89, 'AH Halfvolle melk' ANG 2.89. | R129: FALSE | S129: Full-line CW chain (dairy confirmed), Albert Heijn-sourced private label suggests Dutch supply chain.
A130: lac | B130: british_virgin_islands | C130: RiteWay Food Markets | D130: https://www.riteway.vg/ | E130: TIER_1A | F130: low | G130: Wave 2 | H130: spider | I130: Generic Magento/GraphQL spider (incl. the mcprod.<domain> pattern) | J130: H_magento | K130: Magento 2 (custom 'Roadtown' theme) | L130: retailer_sku | M130: supermarket | N130: USD | O130: 130 | P130: /shop-groceries.html (SSR category listing) | Q130: GET /shop-groceries.html -> HTTP 200, 1.9MB SSR HTML with real Magento product-item cards. Sample product names: 'Fresh Ground Beef', 'Pork Tenderloin', 'Extra Sharp Cheddar Bar', 'Bakerly Brioche Hot Dog Buns'. Prices in same page: $4.99, $8.99, $39.99, $24.99, $7.99 (data-price-amount attrs). GraphQL endpoint (/graphql) returns HTTP 404 via the Varnish edge — GraphQL module likely disabled — but SSR category pages carry full name+price so Tier 1A applies instead. | R130: FALSE | S130: 60-year BVI chain, 9 stores, dedicated online-ordering platform ('RiteWay Online') with next-day delivery.
A131: lac | B131: jamaica | C131: Virtual Mart Jamaica | D131: https://www.virtualmartja.com/ | E131: TIER_1A | F131: low | G131: Wave 2 | H131: spider | I131: Generic Magento/GraphQL spider (incl. the mcprod.<domain> pattern) | J131: H_magento | K131: Magento | L131: retailer_sku | M131: supermarket | N131: JMD | O131: 100 | P131: SSR HTML Magento listing/PDP (data-price-amount attrs) | Q131: curl 200/225KB (Magento). data-price-amount price blocks confirmed, e.g. J$2,471.29 special-price product (id 106209). CSV notes groceries plus hardware/business-supplies categories. | R131: TRUE | S131: Mixed grocery + hardware/household catalog; F&B is a subset of a broader general-merchandise store.
... A136: eca | B136: italy | C136: Conad | D136: https://spesaonline.conad.it/ | E136: TIER_1A | F136: low | G136: Wave 3 | H136: spider | I136: One bespoke spider or fetcher per source | J136: Z_bespoke | K136: Custom (Sapo-family) | L136: retailer_sku | M136: supermarket | N136: EUR | O136: 170 | P136: /p/<slug>--<id> | Q136: GET / -> 200, 475KB, Sapo/Next hybrid. 15 unique real /p/<slug>--<id> product links on the homepage alone, spanning mozzarella, organic eggs, free-range eggs, water, chicken breast, carrots, toilet paper. EUR prices in SSR HTML (6,55 €, 2,49€, 5,24 €, 1,99€ ...). | R136: TRUE | S136: Largest Italian chain by share per CSV. Homepage alone already spans dairy, eggs, fresh meat, fresh produce, beverages, non-food -- strong full-line signal.
A137: eap | B137: malaysia | C137: KPDNHEP PriceCatcher (data.gov.my) | D137: https://storage.data.gov.my/pricecatcher/ | E137: TIER_1B | F137: low | G137: Wave 3 | H137: fetcher | I137: One bespoke spider or fetcher per source | J137: Z_bespoke | K137: Custom (static gov open-data bucket, no auth, no rate limit hit) | L137: official_avg | N137: MYR | O137: 160 | P137: /pricecatcher/pricecatcher_YYYY-MM.csv + /pricecatcher/lookup_item.csv (+ presumably lookup_premise.csv) | Q137: GET https://storage.data.gov.my/pricecatcher/pricecatcher_2026-08.csv -> 200, 8.9MB CSV, 345,029 rows (date,premise_code,item_code,price) for August 2026 alone; monthly files exist back to program start (pricecatcher_YYYY-MM.csv, also daily YYYY-MM-DD variants and a *_preview.parquet). Companion GET .../lookup_item.csv -> 200, 758-row item master (item_code,item,unit,item_group,item_category). Sample: item_code=1 'AYAM BERSIH - STANDARD' unit=1kg; premise_code=2, 2026-08-01, price=MYR 11.00. | R137: FALSE | S137: KPDNHEP's official daily price-monitoring program across 500+ registered premises nationwide (wet markets, supermarkets, minimarkets, hypermarkets), 758 SKUs total. Item-group breakdown: AYAM(10, chicken), DAGING(32, meat), BAHAN LAUT(38, fresh seafood), IKAN DARAT(4, freshwater fish), IKAN DALAM TIN(11, canned fish), HASIL LAUT KERING(4, dried seafood), SAYUR-SAYURAN(40, vegetables) + BAWANG(11, onions) + UBI KENTANG(3, potato), BUAH-BUAHAN(17, fruit), BERAS(19, rice), TEPUNG(8, flour), MEE/BIHUN/KUEY TEOW(28+3+2, noodles), MINYAK DAN LEMAK(39, oils/fats), TELUR(11, eggs), SUSU BAYI(20)+KRIMER DAN SUSU TEPUNG(23, dairy/milk powder), KACANG(7, nuts/pulses), REMPAH RATUS berbungkus+tidak(30+18, spices/condiments), KICAP DAN SOS(20, sauces), GULA(4, sugar), MINUMAN(47)+TERSEDIA MINUM(25, beverages) -- roughly 600 of the 758 items are food/beverage; the remainder (toiletries, stationery, diapers) rides the same monitoring program and is excluded downstream by the food gate. True whole-catalog walker: bulk monthly file, no pagination, no auth. Malaysia currently has zero official_avg/wholesale manifest in the repo -- this closes that gap outright and is the single strongest source found this session.
A138: eca | B138: malta | C138: PaviPama | D138: https://www.pavipama.com.mt/ | E138: TIER_1B | F138: low | G138: Wave 3 | H138: spider | I138: One bespoke spider or fetcher per source | J138: Z_bespoke | K138: Custom | L138: retailer_sku | M138: supermarket | N138: EUR | O138: 160 | P138: /api/cli/ecommerce/products/featured?p=0&store= (also /api/cli/categories) | Q138: curl 200 (after -L to /app/), Playwright network sniff found open API https://pavipama.com.mt/api/cli/ecommerce/products/featured?p=0&store= -> plain curl with Origin/Referer headers returns HTTP 200, 32.8KB JSON, 20 products/page. Sample: 'ACQUA FRIZZANTE 500ML' price 0.25 EUR, brand CONAD. /api/cli/categories returns 23 top-level categories: CONFECTIONERY, FRUIT & VEG, DELICATESSEN, FISH, BUTCHER, FROZEN, CHILLED, BABY, PERSONAL CARE, PASTA SHOP, FOODS, CELLAR, BAKERY, BEVERAGES, PETSHOP, CLEANING, HEALTH, etc. | R138: TRUE | S138: CSV URL (pavishopping.com) was DEAD (NXDOMAIN). Correct current domain found via WebSearch: pavipama.com.mt. Genuinely full-line: fruit&veg, fish, butcher, frozen, chilled, bakery, beverages, cellar, pasta shop confirmed as real top-level categories.
A139: eca | B139: armenia | C139: Parma | D139: https://parma.am/en/ | E139: TIER_1A | F139: low | G139: Wave 3 | H139: spider | I139: One bespoke spider or fetcher per source | J139: Z_bespoke | K139: Custom (Next.js) | L139: retailer_sku | M139: supermarket | N139: AMD | O139: 160 | P139: /en/product/shop?slug=<category>, /en/product/category?slug=<id> | Q139: GET /en/product/shop?slug=only-in-parma -> 200, 539KB HTML. Full category tree (baby-food, alcoholic-beverages, bakery, beef, basturma-sudjuk, battery...). Server-rendered dram prices in raw HTML: e.g. 233 է, 10387 է, 8514 է. | R139: TRUE | S139: Full grocery taxonomy incl. baby food, alcohol, bakery, fresh/cured meat (basturma). No login/geo wall hit.
A140: sar | B140: sri_lanka | C140: Glomark | D140: https://glomark.lk/ | E140: TIER_1A | F140: low | G140: Wave 3 | H140: spider | I140: One bespoke spider or fetcher per source | J140: Z_bespoke | K140: Custom PHP (ZENEDGE-fronted) | L140: retailer_sku | M140: supermarket | N140: LKR | O140: 160 | Q140: curl 200/1.14MB SSR HTML on /shop-now. 102 distinct subcategory URLs (/<path>/c/<id> and /<path>/<sub>/sc/<id>) spanning bakery(bread,buns,cake,cookies,savoury,sweet), beverages(coffee,tea,water,juices,malt,soft-drinks,sport/energy), chilled(cheese,cream,curd,desserts,pasteurized-milk,ready-to-cook,spreads,yogurt), fresh(fish: fresh-water+sea; fruits: imported+local; meat: beef,lamb,mutton,pork,poultry,ready-to-cook,value-added; vegetable: exotic,low-country,up-country), frozen(ready-to-cook,ready-to-eat,processed fish/meat/veg-fruit), grocery, household, pharmaceuticals. PDP confirmed: 'Banno Basmati Biriyani Rice 500G' Rs.250 (h1 + price both present, 767KB page). | R140: FALSE | S140: Best single find of this shard -- 'Sri Lanka's first global market', a genuine full-line supermarket (fresh meat by cut, two fish types, imported+local fruit, three vegetable tiers) served entirely over plain SSR HTML with no WAF encountered. Should be the first onboarding priority for Sri Lanka.
A141: lac | B141: bolivia | C141: Hipermaxi | D141: https://www.hipermaxi.com/ | E141: TIER_1A | F141: low | G141: Wave 3 | H141: spider | I141: One bespoke spider or fetcher per source | J141: Z_bespoke | K141: Next.js/Custom | L141: retailer_sku | M141: supermarket | N141: BOB | O141: 160 | P141: SSR HTML (no API needed) | Q141: curl 200/791KB, Next.js SSR. Prices server-rendered directly in HTML with schema-labelled blocks: 'Carne Molida de Segunda' (ground beef) Bs 40.50; 'Coca Cola Original 3 L' Bs 17.10. Full meat + beverage + grocery categories visible. | R141: TRUE | S141: Largest Bolivian supermarket chain per CSV; strongest Bolivia source, prices render server-side with no API needed.
A142: eca | B142: romania | C142: Freshful by eMAG | D142: https://www.freshful.ro/ | E142: TIER_1A | F142: low | G142: Wave 3 | H142: spider | I142: One bespoke spider or fetcher per source | J142: Z_bespoke | K142: Next.js | L142: retailer_sku | M142: supermarket | N142: RON | O142: 150 | P142: SSR HTML, no API needed | Q142: curl 200, 566KB SSR HTML (__NEXT_DATA__), real prices in raw HTML: '12,99 lei', '20,00 Lei', '56,99 Lei', '47,98 Lei', '23,03 Lei' | R142: TRUE | S142: Matches the brief's own worked example. Fresh produce with named local-producer attribution per CSV notes.
A143: eca | B143: kazakhstan | C143: Galmart | D143: https://galmart.kz/ | E143: TIER_1A | F143: low | G143: Wave 3 | H143: spider | I143: One bespoke spider or fetcher per source | J143: Z_bespoke | K143: Custom | L143: retailer_sku | M143: supermarket | N143: KZT | O143: 150 | P143: SSR HTML | Q143: curl 200, 142KB, real prices in raw HTML: '2 650₸', '2 850₸', '1 456₸', '1 835₸', '2 310₸', '2 100₸' | R143: TRUE | S143: Premium Astana chain with deep dairy taxonomy per CSV (mare/camel/goat milk as separate categories).
A144: eca | B144: slovenia | C144: Mercator Online | D144: https://mercatoronline.si/ | E144: TIER_1A | F144: low | G144: Wave 3 | H144: spider | I144: One bespoke spider or fetcher per source | J144: Z_bespoke | K144: Custom | L144: retailer_sku | M144: supermarket | N144: EUR | O144: 150 | P144: SSR HTML | Q144: curl 200, 767KB, real prices in raw HTML: '150,00 EUR', '60,00 EUR', '3,99€' | R144: TRUE | S144: 18,000+ products, delivery to 99% of Slovenian addresses per CSV; PC30 (30-day-lowest, omnibus) field noted but not verified in this pass.
A145: eca | B145: estonia | C145: Prisma Estonia | D145: https://www.prismamarket.ee/ | E145: TIER_1A | F145: low | G145: Wave 3 | H145: spider | I145: One bespoke spider or fetcher per source | J145: Z_bespoke | K145: Next.js | L145: retailer_sku | M145: supermarket | N145: EUR | O145: 150 | P145: SSR HTML / __NEXT_DATA__ JSON blob | Q145: curl 200, 367KB, Next.js SSR (__NEXT_DATA__ valid JSON with props.pageProps), real prices in raw HTML: '1,85 €', '12,33 €', '3,28 €' | R145: TRUE | S145: -
A146: eca | B146: armenia | C146: Supermarket.am | D146: https://supermarket.am/en/ | E146: TIER_1A | F146: low | G146: Wave 3 | H146: spider | I146: One bespoke spider or fetcher per source | J146: Z_bespoke | K146: Custom | L146: retailer_sku | M146: supermarket | N146: AMD | O146: 150 | P146: /en/products/_<id>/ | Q146: GET /en/products/_723530/ -> 200, 399KB. PDP h1 'Pasta Zara No. 50 500g', span.priceValue = '710 dr'. Category tree via /en/products/_<id>/ product links visible on homepage. | R146: TRUE | S146: Weight-based items sliced to order per CSV note; PDP price rendered server-side.
A147: eca | B147: bulgaria | C147: T Market Online | D147: https://tmarketonline.bg/ | E147: TIER_1A | F147: low | G147: Wave 3 | H147: spider | I147: One bespoke spider or fetcher per source | J147: Z_bespoke | K147: Custom | L147: retailer_sku | M147: supermarket | N147: BGN/EUR | O147: 150 | P147: SSR product pages | Q147: GET /product/avokado-izrael -> h1 'Avokado, br.' (avocado), price '1,39 lv' / '0,71 EUR'. Real /product/<slug> and /category/<slug> links throughout homepage. | R147: TRUE | S147: Maxima-group chain; CSV flags unusually good fresh + LOCAL Bulgarian lines (rose tomatoes, Madzharov cheese, banitsa sheets).
A148: eca | B148: finland | C148: Prisma | D148: https://www.prisma.fi/ | E148: TIER_1A | F148: low | G148: Wave 3 | H148: spider | I148: One bespoke spider or fetcher per source | J148: Z_bespoke | K148: Custom (Next.js) | L148: retailer_sku | M148: supermarket | N148: EUR | O148: 150 | P148: SSR + __NEXT_DATA__ | Q148: GET / -> 200, 1.04MB, __NEXT_DATA__ present, real EUR prices rendered server-side (e.g. '5 439,15 €' owner-price banner item). Same S-Group family as s-kaupat.fi. Grocery category page not separately fetched this round. | R148: TRUE | S148: Homepage sample was a big-ticket appliance, not F&B -- grocery category page needs a follow-up fetch to confirm F&B depth directly, but platform/SSR confirmed working.
A149: eca | B149: iceland | C149: Kronan | D149: https://www.kronan.is/ | E149: TIER_1B | F149: low | G149: Wave 3 | H149: spider | I149: One bespoke spider or fetcher per source | J149: Z_bespoke | K149: Custom | L149: retailer_sku | M149: supermarket | N149: ISK | O149: 150 | P149: SSR embedded JSON at /vara/<slug> | Q149: GET / -> 200, 479KB. Embedded product JSON in SSR HTML: {"slug":"100273243-isey-skyr-solmyrkvi",...,"categoryTag":"05-05-01-skyr",...,"discountedPrice":330,"priceInfo":"170 gr. - 1.941 kr. / kg"} (Isey skyr yoghurt, 330 kr). Also saw Red Bull, Floridana juice, /vara/<id-slug> product links throughout. | R149: TRUE | S149: Internal category codes (e.g. 05-05-01-skyr) look pre-classified -- useful mapping hint. ISK has no minor units so price values are literal kr.
A150: eca | B150: croatia | C150: Plodine | D150: https://www.plodine.hr/ | E150: TIER_1A | F150: low | G150: Wave 3 | H150: spider | I150: One bespoke spider or fetcher per source | J150: Z_bespoke | K150: Next.js | L150: retailer_sku | M150: supermarket | N150: EUR | O150: 150 | P150: SSR homepage/category HTML | Q150: GET -> 200, 86KB SSR (Next.js). Sample: h2 'Svježi black Angus steak' near 9,49€; also 4,49€, 12,99€ visible. | R150: TRUE | S150: National chain, carried by all 4 Croatian aggregators for cross-validation.
A151: eca | B151: croatia | C151: Kaufland Croatia | D151: https://www.kaufland.hr/ | E151: TIER_1A | F151: low | G151: Wave 3 | H151: spider | I151: One bespoke spider or fetcher per source | J151: Z_bespoke | K151: Vue/Next hybrid | L151: retailer_sku | M151: supermarket | N151: EUR | O151: 150 | P151: SSR homepage/category HTML | Q151: GET -> 200, 208KB SSR (Vue+Next). Direct price '1,44€' repeated in homepage HTML. Also found a published 'Popis maloprodajnih cijena' (retail price list) page at /akcije-novosti/popis-mpc.html (200, 114KB) but it is an explanatory HTML page, not a raw CSV/XML download. | R151: TRUE | S151: Overturns shard's D-tier 'SUSPECT' prediction -- plain curl works cleanly, no WAF encountered.
A152: eca | B152: moldova | C152: Linella.md | D152: https://linella.md/ | E152: TIER_1A | F152: low | G152: Wave 3 | H152: spider | I152: One bespoke spider or fetcher per source | J152: Z_bespoke | K152: Custom | L152: retailer_sku | M152: supermarket | N152: MDL | O152: 150 | P152: SSR category HTML (/ro/catalog) | Q152: GET -> 200, 864KB SSR. class='price-products-catalog-content__main 10.59 9.49' style list/discount pairs directly in listing HTML. | R152: TRUE | S152: 206 stores, 14,500+ products per shard; list+promo price pairs and per-0.5kg fresh pricing.
... A164: eca | B164: spain | C164: Ulabox | D164: https://www.ulabox.com/ | E164: TIER_1B | F164: low | G164: Wave 3 | H164: spider | I164: One bespoke spider or fetcher per source | J164: Z_bespoke | K164: Next.js | L164: retailer_sku | M164: supermarket | N164: EUR | O164: 140 | P164: page-embedded JSON (Next.js hydration) | Q164: GET -> 200, 347KB. Embedded JSON 'price':9.95 and 'price':12.45 in page source. | R164: TRUE | S164: Bespoke storefront, prices present in initial page payload.
A165: sar | B165: maldives | C165: WHIM | D165: https://whim.com.mv/ | E165: TIER_1A | F165: low | G165: Wave 3 | H165: spider | I165: One bespoke spider or fetcher per source | J165: Z_bespoke | K165: Custom (not yet fingerprinted beyond SSR HTML) | L165: retailer_sku | M165: supermarket | N165: MVR | O165: 140 | Q165: GET /shop -> 200, 192KB SSR HTML. ~55 category links found: dairy/eggs/milk (butter, cheese, milk, yogurt), drinks (chocolate-malted, coffee, cordials, juices, non-alcoholic, soft drinks, tea incl. flower/herbal, water), fresh-fruits-vegetables, frozen (food, meat, seafood, vegetables, ice-cream), chilled-ham-sausage, maldivian-smoked-dried-fish-related-products, pantry (baking, breads incl. flatbread/wraps, breakfast/cereals, canned foods/fruits, coconut products, condiments incl. Maldivian condiments and pickles/chutney, dried fruit, herbs/legumes/spices, jam/spreads/honey, noodles, oils/vinegar, pasta, rice/multigrains/quinoa, sauces, snacks, sugar/syrups), vegan, baby food. | R165: FALSE | S165: This is the already-onboarded 'whim_mv' spider (manifest lists it as channel: supermarket on Odoo, PDPs at /shop/<slug>-<id>) -- re-verified category breadth here since it anchors the whole Maldives estimate. Genuinely the closest thing to a full-line supermarket found for Maldives: strong pantry/dairy/drinks/frozen breadth including a Maldivian-specific dried/smoked fish line, but NO fresh meat and NO fresh fish category (only frozen meat/seafood + chilled ham/sausage) -- matches the island-import-dependent profile the brief predicted.
A166: ssa | B166: zimbabwe | C166: SPAR Zimbabwe | D166: https://www.spar.co.zw/products | E166: TIER_1A | F166: low | G166: Wave 3 | H166: spider | I166: One bespoke spider or fetcher per source | J166: Z_bespoke | K166: Custom (ASP.NET WebForms + AngularJS) | L166: retailer_sku | M166: supermarket | N166: USD | O166: 140 | P166: SSR HTML listing at /products (paginated/searchable via query string, not yet mapped) | Q166: GET /products -> 200, 134KB. Real ASP.NET+AngularJS-enhanced SSR product listing: 'MAZOE ORANGE CRUSH ORIGINAL 2L' -> USD$4.00, 'RAHA COOKING OIL 2L' visible with product-links markup, canonical /products/{id}/{slug} PDP URLs. | R166: TRUE | S166: USD staples (maize meal, cooking oil, sugar) confirmed live and dollarised per prior research; full SPAR chain.
A167: eca | B167: romania | C167: MegaMarket.ro | D167: https://www.megamarket.ro/ | E167: TIER_1A | F167: low | G167: Wave 3 | H167: spider | I167: One bespoke spider or fetcher per source | J167: Z_bespoke | K167: Custom | L167: retailer_sku | M167: supermarket | N167: RON | O167: 130 | P167: SSR HTML | Q167: curl 200, 148KB, real prices in raw HTML: '8,09 lei', '0,81 lei', '13,49 lei', '33,94 lei', '3,57 lei' | R167: TRUE | S167: CSV notes per-category item counts (conserve 278, paste 53) as a completeness check.
A168: eca | B168: austria | C168: MPreis | D168: https://www.mpreis.at/ | E168: TIER_1A | F168: low | G168: Wave 3 | H168: spider | I168: One bespoke spider or fetcher per source | J168: Z_bespoke | K168: Custom + Algolia | L168: retailer_sku | M168: supermarket | N168: EUR | O168: 130 | P168: SSR HTML (Algolia search key not yet extracted) | Q168: curl 200, 640KB, Algolia detected, real prices in raw HTML: '0,78 €', '1,57 €', '1,56 €', '3,99 €', '5,99 €', '12,09 €' | R168: FALSE | S168: Net-new discovery (not in CSV shard) - Austria's 3 CSV rows all failed probing, this fills the gap. Tyrol-based regional chain, ~150 stores nationwide-adjacent.
A169: eca | B169: iceland | C169: Heimkaup | D169: https://www.heimkaup.is/ | E169: TIER_1B | F169: low | G169: Wave 3 | H169: spider | I169: One bespoke spider or fetcher per source | J169: Z_bespoke | K169: Custom | L169: retailer_sku | M169: supermarket | N169: ISK | O169: 130 | P169: SSR embedded JSON at /p/<slug>-<id> | Q169: GET / -> 200, 379KB. 49 unique /p/<slug>-<id> product links (beer, soft drinks, wine, ice cream). Embedded JSON for Pepsi Max 12x330ml: "price":129900,"commodityGroup":{"name":"GROCERY"}. | R169: TRUE | S169: MINOR-UNIT TRAP: price field is in hundredths (129900 -> 1,299.00 kr for a 12-pack), not literal ISK like Kronan. Verify against rendered page before trusting raw field.
A170: eca | B170: kosovo | C170: Maxi E-Shop | D170: https://maxiks.shop/ | E170: TIER_1A | F170: low | G170: Wave 3 | H170: spider | I170: One bespoke spider or fetcher per source | J170: Z_bespoke | K170: Custom | L170: retailer_sku | M170: supermarket | N170: EUR | O170: 130 | P170: /product/<slug> | Q170: GET / -> 200, 390KB. Real product card: h3.product-title 'Faculet e lagur Fresh x 52cope' (wet wipes), h4.product-price '1.79€'. Full supermarket taxonomy visible in nav (Ushqimore=grocery, Bulmet=dairy, Pije=drinks, Fruta & Perime=fruit&veg, Pjekurina=bakery). | R170: TRUE | S170: 18 Prishtina outlets per CSV; EUR is Kosovo's domestic currency so this passes the currency-authenticity check cleanly.
A171: eca | B171: latvia | C171: Elvi.lv | D171: https://www.elvi.lv/ | E171: TIER_1A | F171: low | G171: Wave 3 | H171: spider | I171: One bespoke spider or fetcher per source | J171: Z_bespoke | K171: Custom | L171: retailer_sku | M171: supermarket | N171: EUR | O171: 130 | P171: SSR homepage/category HTML | Q171: GET -> 200, 73KB SSR. Direct prices 0.89€ / 2.58€ / 2.86€ in homepage HTML. | R171: TRUE | S171: National chain, bespoke storefront, prices render server-side.
A172: eca | B172: latvia | C172: Top! Veikali (toppartika.lv) | D172: https://www.toppartika.lv/ | E172: TIER_1A | F172: low | G172: Wave 3 | H172: spider | I172: One bespoke spider or fetcher per source | J172: Z_bespoke | K172: Custom | L172: retailer_sku | M172: supermarket | N172: EUR | O172: 130 | P172: SSR homepage/category HTML | Q172: GET -> 200, 4.08MB SSR. Direct prices 1.47€ / 1.59€ / 1.98€ in homepage HTML. | R172: TRUE | S172: Very large homepage payload (4MB) -- likely already lists most/all categories server-side.
A173: eca | B173: moldova | C173: Mega Alina | D173: https://www.megaalina.md/ | E173: TIER_1A | F173: low | G173: Wave 3 | H173: spider | I173: One bespoke spider or fetcher per source | J173: Z_bespoke | K173: Custom | L173: retailer_sku | M173: supermarket | N173: MDL | O173: 130 | P173: SSR category HTML (/ro/catalog/...) | Q173: GET -> 200, 673KB SSR. Direct catalog prices '5.99 MDL' / '4.99 MDL' repeated in listing HTML. | R173: TRUE | S173: Strike-through discount pairs across food, dairy, juice, household.
A174: eca | B174: spain | C174: Cartio | D174: https://cartio.es/landing/ | E174: TIER_1A | F174: low | G174: Wave 3 | H174: spider | I174: One bespoke spider or fetcher per source | J174: Z_bespoke | K174: Custom | L174: retailer_sku | M174: aggregator | N174: EUR | O174: 130 | P174: SSR landing HTML | Q174: GET -> 200, 120KB SSR. Direct prices '6,99€' / '0,31€' / '1,95€' in HTML. | R174: TRUE | S174: Basket-level comparison across Mercadona/Carrefour/Lidl/Alcampo; shard notes an account requirement but the landing page itself rendered prices without one.
A175: ssa | B175: benin | C175: NolMarket | D175: https://nolmarket.com/ | E175: TIER_1B | F175: low | G175: Wave 3 | H175: spider | I175: One bespoke spider or fetcher per source | J175: Z_bespoke | K175: Custom (Laravel + React) | L175: retailer_sku | M175: supermarket | N175: XOF | O175: 130 | P175: /api/products (paginate ?page=N) | Q175: React SPA (CRA, div#root) with a fully open Laravel JSON API. GET https://nolmarket.com/api/products -> 200, paginated (24/page, 121 total_pages, 2,887 total products), no auth needed. Sample: 'Patee au boeuf PRIX MINI' 700 FCFA (Animalerie). Sampled pages 1,5,10,20,40,60,80,100,120 -> categories span Animalerie, Boissons (Biere, Champagnes, Cidre, Jus de fruits, Spiritueux, Vins), Epicerie (Conserves-plats cuisines, Petit Dejeuner, Produits de base), Produits Frais (Fromages-Charcuterie-Beurre, Fruits secs et frais, Pains-Viennoiseries, Viandes-Poissons-Crustasses-Oeufs, Yaourt/Creme fraiche), Produits Locaux (Amuse gueule, Boissons locales, Epices/Huile locale, Graine/Legume sec, Poudre/Farine/Bouillie, Produits cosmetiques, The/Cafe/Miel/Confiture). | R175: TRUE | S175: Best single retail source found across all 8 countries this pass -- genuinely full-line (fresh + meat/fish/eggs + dairy + bakery + local staples) with a dedicated 'Produits Locaux' section that carries exactly the local-grain/flour/oil forms that block chain supermarkets do not.
A176: eca | B176: romania | C176: VivoMarket.ro | D176: https://www.vivomarket.ro/ | E176: TIER_1A | F176: low | G176: Wave 3 | H176: spider | I176: One bespoke spider or fetcher per source | J176: Z_bespoke | K176: Custom | L176: retailer_sku | M176: supermarket | N176: RON | O176: 120 | P176: SSR HTML | Q176: curl 200, 1.9MB, real prices in raw HTML: '51,82 Lei', '28,90 Lei', '21,60 Lei', '26,21 Lei', '13,18 Lei' | R176: TRUE | S176: Carries both retail and HoReCa lines per CSV; tag channel separately.
A177: eca | B177: kazakhstan | C177: GroceryKZ | D177: https://grocerykz.com/ | E177: TIER_1A | F177: low | G177: Wave 3 | H177: spider | I177: One bespoke spider or fetcher per source | J177: Z_bespoke | K177: Custom | L177: retailer_sku | M177: supermarket | N177: KZT | O177: 120 | P177: SSR HTML | Q177: curl 200, 164KB, real prices in raw HTML: '3 750 KZT', '4 650 KZT', '2 450 KZT', '2 250 KZT', '16 900 KZT' | R177: TRUE | S177: English interface per CSV, per-piece pricing with stock flags.
... A198: ssa | B198: sudan | C198: HyperSale | D198: https://www.hypersale.sd/ | E198: TIER_1A | F198: low | G198: Wave 3 | H198: spider | I198: One bespoke spider or fetcher per source | J198: Z_bespoke | K198: Custom (Laravel) | L198: retailer_sku | M198: supermarket | N198: SDG | O198: 45 | P198: /category/hypersale-super-market | Q198: GET /category/hypersale-super-market -> HTTP 200, 430KB SSR HTML with real product links + prices. Samples: 'Al Hamwi Coffee Classic Cardamom 180gm' 24.000 SDG, 'Frozina Pomme Frite Potatoes 25gm' 23.000 SDG, 'Karim Coconut Milk 400ml' 7.500 SDG, 'Lotus Biscoff Original 250gm' price present, 'Frozen Strawberry 1kg' present. | R198: TRUE | S198: GOTCHA: prices render as '24.000SDG' -- verify whether '.' is a thousands separator (SDG 24,000) or a decimal point before scaffolding; eyeball against a known SDG price level. Dedicated grocery vertical confirmed distinct from the general marketplace (electronics/fashion/beauty also on this domain).
A199: ssa | B199: guinea | C199: Beryz | D199: https://www.beryz.com/fr/alimentation | E199: TIER_1A | F199: low | G199: Wave 3 | H199: spider | I199: One bespoke spider or fetcher per source | J199: Z_bespoke | K199: Custom | L199: retailer_sku | M199: supermarket | N199: GNF | O199: 40 | Q199: curl -> HTTP 200, 104.5KB SSR HTML. Confirmed product card: 'Huile de palme rouge' -- 'Fatou Camara -- Conakry' -- '8 000 GNF/litre', tagged category 'Huiles'. | R199: TRUE | S199: Confirms CSV's 'STRONG' rating and dual retail/wholesale pricing claim structurally (though the sampled card shows only one price point). Per-vendor + per-region (Conakry/Labe/Kindia/Boke) tagging is unusually valuable for spatial analysis.
A200: sar | B200: nepal | C200: Kalimati Fruits and Vegetable Market Development Board (wholesale) | D200: https://kalimatimarket.gov.np/price | E200: TIER_1B | F200: low | G200: Wave 3 | H200: fetcher | I200: One bespoke spider or fetcher per source | J200: Z_bespoke | K200: Custom (Laravel, DataTables.js UI but server renders HTML rows on POST) | L200: wholesale reference | M200: official_avg | N200: NPR | O200: 35 | P200: /price (GET for token, POST with datePricing param) | Q200: GET /price (grab CSRF token '_token' + session cookie from hidden form field) then POST same URL with form fields _token, datePricing=YYYY-MM-DD (X-Requested-With: XMLHttpRequest header not even required) -> 200, 30821 bytes HTML fragment, 98 commodity rows/day. Sample: 'गोलभेडा ठूलो(नेपाली)' (Tomato, large, local) के.जी. रू ४०.००-५०.०० (avg रू ४५). No auth beyond the CSRF handshake. | R200: FALSE | S200: Whole-catalog walker: 98 commodities/day (many varieties per crop e.g. 3 tomato types, 4 potato types) covering nearly all fresh vegetables + fruits traded through Nepal's largest wholesale market. min/max/avg per unit. Walk daily by iterating datePricing for history. This is the single highest-value new find in the shard.
A201: ssa | B201: angola | C201: Kiwaba Online | D201: https://www.kiwaba.online/ | E201: TIER_1B | F201: low | G201: Wave 3 | H201: spider | I201: One bespoke spider or fetcher per source | J201: Z_bespoke | K201: Custom (React/Vite + Supabase) | L201: retailer_sku | M201: supermarket | N201: AOA | O201: 30 | P201: https://{project-ref}.supabase.co/rest/v1/products (apikey header required, key lives in the site's JS bundle) | Q201: React SPA (Vite, div#root) backed by open Supabase REST API. Anon JWT key found embedded in /assets/index-D4PaSevu.js. GET https://aljtwptkvhazymmtiqmx.supabase.co/rest/v1/products?select=id,name,price,unit,category_id&active=eq.true&limit=1500 -H 'apikey: <anon-jwt>' -> 200, 302 active products. Sample: 'LABIO DE VACA cax 15kg' (cow lip, wholesale case) Kz 48,500.00. Categories: Carnes, Peixe & Marisco, Hortícolas, Cereais & Grãos, Bebidas, Fubas e farinhas, Lacticínios (plus non-food: Saúde e beleza, Medicamentos, Detergentes, Roupa). | R201: TRUE | S201: Mid-size mixed grocery+pharmacy catalog (302 active items). Confirms CSV's 'STRONG' verdict. Food categories are real but not deep per-category (single digits to low tens of SKUs each).
A202: menaap | B202: djibouti | C202: AHADO EXPRESS | D202: https://ahadoexpress.net/ | E202: TIER_1B | F202: low | G202: Wave 3 | H202: spider | I202: One bespoke spider or fetcher per source | J202: Z_bespoke | K202: Custom (static site + public Google Sheet as backend, no auth) | L202: retailer_sku | M202: supermarket | N202: DJF | O202: 25 | P202: https://docs.google.com/spreadsheets/d/{sheetId}/gviz/tq?tqx=out:json&sheet=Produits | Q202: Catalog is client-rendered from a public Google Sheets gviz endpoint, not a normal REST API. Traced js/main.js -> js/data-loader.js -> js/config.js for sheetId, then hit https://docs.google.com/spreadsheets/d/1WnLMz5rtsKa0cCmbqNN_Fh3d_5nm99kJVmzrN4427-Y/gviz/tq?tqx=out:json&sheet=Produits directly -> HTTP 200, 44KB JSON-ish (gviz wrapper), 174 rows. Sample: 'Huile Bertini' and 'Bio' with variant tiers e.g. '1 paquet' 500 FDJ / 'Pack (x6)' 2900 FDJ. Categories: Nettoyage 33, Riz 21, Epices 20, Lait Poudre 18, Spaghetti 18, Lait Infantile 11, Hygiene 7, Conserves 6, Boissons 5, Huiles 5, Bebe 4, Petit Dej 4, Frais 1. | R202: TRUE | S202: Fragile source (a spreadsheet, not a database) but fully open, no auth, no WAF. Narrow assortment: mostly packaged/shelf-stable goods (rice, pasta, powdered milk, oils, canned goods, cleaning products mixed into same catalog). Almost no fresh produce (only 1 'Frais' row).
A203: sar | B203: nepal | C203: Vhandar | D203: https://www.vhandar.com/ | E203: TIER_1B | F203: low | G203: Wave 3 | H203: spider | I203: One bespoke spider or fetcher per source | J203: Z_bespoke | K203: Custom (Next.js + separate API host) | L203: retailer_sku | M203: supermarket | N203: NPR | O203: 25 | P203: GET api.vhandar.com/products, /categories | Q203: Next.js frontend, backend at GET https://api.vhandar.com/products?status=active&page=1&limit=50 -> 200, 143KB JSON, plain curl, no auth. pagination.total=1180. Sample: 'Sip & Seal Matcha Powder' unit=g unitValue=100 pricePerUnit=1600 (NPR implied). Categories via /categories endpoint: Dairy/Bread/Eggs, Packaged & Instant Food, Rice/Atta/Flour, Dals/Pulses, Oil/Ghee, Masala/Dry Fruits, Sauces/Spreads, Tea/Coffee, Sweet Tooth, Snacks, Cold Drinks/Juice, Bakery/Biscuits, Horeca, Beauty/Cleaning/Personal-care/Baby (non-food). | R203: TRUE | S203: No fresh-produce, meat, or fish category -- packaged/shelf-stable goods only, plus a HORECA wholesale vertical and MRP+savings fields (margin analysis). Heavy overlap with MeroKirana's packaged/dairy/beverage categories so counted incrementally, not standalone.
A204: sar | B204: pakistan | C204: Pakistan Bureau of Statistics -- Weekly Sensitive Price Indicator (SPI) | D204: https://www.pbs.gov.pk/spi and per-week bulletin pages e.g. https://www.pbs.gov.pk/weekly-sensitive-price-indicator-spi-for-the-week-ended-on-30-07-2026/ | E204: TIER_1A | F204: low | G204: Wave 3 | H204: fetcher | I204: One bespoke spider or fetcher per source | J204: Z_bespoke | K204: WordPress (static uploads) | L204: official_avg | M204: official_avg | N204: PKR | O204: 25 | P204: wp-content/uploads/2020/07/Annex_{DD.MM.YYYY}.xlsx (dated, predictable pattern) | Q204: www.pbs.gov.pk/spi 404s directly (stale vanity URL) but the per-week bulletin page (found via WebSearch) -> HTTP 200, links to a stable-pattern Annex XLSX (wp-content/uploads/2020/07/Annex_DD.MM.YYYY.xlsx). Downloaded and parsed with openpyxl: 'Appendix-A / CONSUMER PRICES OF ESSENTIAL ITEMS', MIN/AVG/MAX price per item across 17 cities (Islamabad, Rawalpindi, Gujranwala, Sialkot, Lahore, Faisalabad, Sargodha, ...). Sample rows: 'Wheat Flour Bag 20 Kg' avg PKR 3085 (Islamabad), 'Milk fresh (Un-boiled) 1 Ltr' avg PKR 250.66, 'Rice Basmati Broken 1 Kg' avg PKR 274.83, 'Eggs Hen (Farm) 1 Dozen' avg PKR 271.48. | R204: FALSE | S204: 51 essential items (food + non-food) across 50 markets in 17 cities, published weekly with a predictable filename pattern once the current-week bulletin URL is found (need a small WebSearch or an index-page crawl each week to get the live URL -- the /spi vanity page itself is stale). Food-relevant subset (flour, rice x2, bread, beef, mutton, chicken, milk, curd, powdered milk, eggs, 2 cooking oils, ghee, sugar, tea, pulses, onion, potato, ...) covers the classic SPI basket.
A205: ssa | B205: benin | C205: Yobou Market | D205: https://www.yoboumarket.com/ | E205: TIER_1B | F205: low | G205: Wave 3 | H205: spider | I205: One bespoke spider or fetcher per source | J205: Z_bespoke | K205: Custom (Next.js) | L205: retailer_sku | M205: supermarket | N205: XOF | O205: 25 | P205: /api/products?limit=all&includeInactive=true | Q205: Next.js app with open API. GET https://www.yoboumarket.com/api/products?limit=all&includeInactive=true -> 200, 578KB, 778 products, no auth. Sample: 'Chou' (cabbage) 500 FCFA. Category breakdown: Alimentation 48, Cuisine 44, Fruits et Legumes 37, Petit Dejeuner 36, Hygiene et Cosmetique 30, Nettoyages 12, Electromenagers 12, Pagnes/tissus 9, Grignoter 5, Epices 3, Savon 3, plus 539 uncategorized. | R205: TRUE | S205: Thinner and more general-merchandise than NolMarket; food is ~130-180 of 778 SKUs once the 539 uncategorized rows are triaged.
A206: sar | B206: bangladesh | C206: TCB (Trading Corporation of Bangladesh) daily essential-commodity prices | D206: https://tcb.gov.bd/pages/daily-rmps | E206: TIER_1A | F206: low | G206: Wave 3 | H206: fetcher | I206: One bespoke spider or fetcher per source | J206: Z_bespoke | K206: Custom CMS (V2Ministry) | L206: official_avg | M206: official_avg | N206: BDT | O206: 15 | P206: /pages/daily-rmps -> dated XLSX (Oracle object storage) | Q206: curl -> HTTP 200, 90.8KB HTML with a table of dated links directly to XLSX files, e.g. https://objectstorage.ap-dcc-gazipur-1.oraclecloud15.com/n/axvjbnqprylg/b/V2Ministry/o/office-tcb/2026/7/....xlsx. Not downloaded/parsed the XLSX schema in this pass, but the link pattern (one dated XLSX per day, Oracle Cloud object storage, no auth) is a clean published-static-doc fetcher shape. | R206: FALSE | S206: TCB's tracked list is narrow (rice, edible oil, sugar, lentils/pulses, onion -- the classic 'essential commodities' basket used for open-market-sale interventions), so leaf count is modest, but it is trivial to fetch (one XLSX per day, stable link).
A207: sar | B207: nepal | C207: Groceries Nepal | D207: https://groceriesnepal.com/ | E207: TIER_1B | F207: low | G207: Wave 3 | H207: spider | I207: One bespoke spider or fetcher per source | J207: Z_bespoke | K207: Custom (Vite/React) | L207: retailer_sku | M207: supermarket | N207: NPR | O207: 10 | P207: GET /api/products | Q207: React SPA, GET https://groceriesnepal.com/api/products -> 200, 26446 bytes JSON, plain curl, no auth. 97 products. categories = {Dairy, Dry Fruits, Fruits, Grocery, Leafy Vegetables, Vegetables}. Sample: 'Tomato (Goalbheda)' category=Vegetables price=100 prevPrice=90 unit=kg, also carries nameNp (Nepali name). | R207: TRUE | S207: Small catalog (97 SKUs) but genuinely carries fresh Vegetables/Leafy Vegetables/Fruits categories, complementing the packaged-only sources. Thin depth per leaf though.
A208: ssa | B208: ghana | C208: Tezeon Grocery | D208: https://tezeon.com/grocery | E208: TIER_1B | F208: low | G208: Wave 3 | H208: spider | I208: One bespoke spider or fetcher per source | J208: Z_bespoke | K208: Custom (Django REST + Next.js frontend) | L208: retailer_sku | M208: supermarket | N208: GHS | O208: 10 | P208: /api/products/ (category filter param not yet resolved), /api/products/categories/ | Q208: Playwright network trace on a category page surfaced a fully open Django-style REST API: GET https://api.tezeon.com/api/products/categories/ -> 200, 204KB, full category tree, no auth. Reproduced standalone with curl. GET https://api.tezeon.com/api/products/ -> 200, 42KB, paginated product list with real prices (e.g. 'Tecno True Wireless Stereo Earphone' GHS 600.00). A 'Groceries & Food' top-level category exists (slug groceries-food) alongside Rice & Pasta, Snacks, Spices, Drinks, Fruit & Vegetable Tools sub-categories, but attempts to filter the products endpoint by category=groceries-food and category=groceries both returned HTTP 400 within budget -- the correct filter param name was not found. | R208: TRUE | S208: General marketplace (electronics/fashion/home dominant per the 150+ category list) with a real but modest F&B slice. Endpoint is trivially open; only the query-param spelling needs one more probe cycle.
A209: sar | B209: nepal | C209: ShopIt Nepal | D209: https://www.shopitnepal.com/ | E209: TIER_1B | F209: low | G209: Wave 3 | H209: spider | I209: One bespoke spider or fetcher per source | J209: Z_bespoke | K209: Custom (Next.js) | L209: retailer_sku | M209: supermarket | N209: NPR | O209: 8 | P209: GET /api/mobile/products, /api/mobile/category | Q209: Next.js frontend, GET https://shopitnepal.com/api/mobile/products -> 200, 7253 bytes JSON, plain curl, no auth. Sample: 'NIVEA Shea Smooth 75ml' price=185 mrp=200. GET /api/mobile/category -> categories {Baby Products, Chocolates, Cloud Kitchen, Daily Groceries, Hajmola, Home & Kitchen, Ice Creams, Liquors, Mouth Freashner, Packaged Foods, Party Supplies, Personal Care, Sexual Wellness, Smokes, Soft Drinks}. | R209: TRUE | S209: Quick-commerce convenience-store catalog (cloud kitchen, liquor, smokes, sweets) with no visible fresh-produce category -- 'Daily Groceries' unconfirmed for fresh items. Endpoint only returned 1 page (default limit) in this probe; pagination params not confirmed.
A210: ssa | B210: malawi | C210: Tambala Market | D210: https://www.tambalamarket.store/categories/food-beverages | E210: TIER_1A | F210: low | G210: Wave 3 | H210: spider | I210: One bespoke spider or fetcher per source | J210: Z_bespoke | K210: Custom | L210: retailer_sku | M210: supermarket | N210: MWK | O210: 8 | P210: SSR HTML | Q210: GET /categories/food-beverages -> 200, 338KB, multiple 'MWK' matches in raw HTML. | R210: TRUE | S210: Multi-seller marketplace; per prior research the food category is small (~17 items) and wine-heavy -- low net-new value beyond Add2Cart/DoorShoppin.
A211: sar | B211: nepal | C211: MilanWholesale | D211: https://milanwholesale.com/ | E211: TIER_1A | F211: low | G211: Wave 3 | H211: fetcher | I211: One bespoke spider or fetcher per source | J211: Z_bespoke | K211: Custom (not WordPress -- wp-json/wc endpoints 404, csrf-token in page suggests bespoke PHP app) | L211: wholesale reference | M211: wholesale | N211: NPR | O211: 5 | P211: GET /product-category/<slug> | Q211: GET https://milanwholesale.com/product-category/rice -> 200, 104587 bytes SSR HTML, plain curl, no auth. Product cards extracted via h-tag anchors, e.g. 'Rajhans Royal Pulao Basmati Rice 20kg' Rs.4500, 'Aashiyana Usina Long Grain Rice 5kg'. Categories: biscuits, breakfast-dips-spreads, chips-biscuits-noodles, cooking-oil-ghee, daal, dry-fruits, flour-flour-products, hot-cold-beverages, lentils-pulses-beans, noodles, rice, spices-masala, sugar-salt. | R211: TRUE | S211: Wholesale bulk pricing on dry staples only (rice, dal/pulses, oil/ghee, spices, sugar/salt, dry fruits, noodles, biscuits) -- no fresh produce/dairy/meat. Prices are bulk-pack (20kg sacks etc.), pair with a retail source for wholesale-retail spread per shard notes. High category overlap with Vhandar/MeroKirana so counted mostly incremental (different channel/analytical_role, not new leaves).
... A216: menaap | B216: libya | C216: Matjar Libya | D216: https://www.matjar-libya.com/ | E216: TIER_1A | F216: low | G216: Wave 3 | H216: spider | I216: One bespoke spider or fetcher per source | J216: Z_bespoke | K216: Custom | L216: retailer_sku | M216: marketplace | N216: LYD | O216: 0 | P216: SSR HTML, /products | Q216: curl -> 200, 169KB. Real LYD prices ('179,00 د.ل', '531,00 د.ل'). Product URL slugs confirm catalogue: acm-depiwhite-advanced-creme-anti-taches (cream), aspirateur-pro-maison (vacuum cleaner), detecteur-cameras-cachees (hidden camera detector), extracteur-points-noirs (blackhead extractor) - anti-theft/cosmetics/gadget dropship, zero food SKUs. | R216: TRUE | S216: Confirms CSV pass-3 reclassification to non-food. Not counted toward F&B coverage.

Sheet Remaining_125
A1: region | B1: slug | C1: source | D1: url | E1: tier | F1: effort | G1: build_wave | H1: scaffolding | I1: build_approach | J1: bucket | K1: platform | L1: analytical_role | M1: channel | N1: currency | O1: fnb_leaves_est | P1: endpoint | Q1: evidence | R1: in_csv | S1: notes | T1: gotcha
A2: eca | B2: tajikistan | C2: Dado.tj | D2: https://dado.tj/ | E2: TIER_1B | F2: medium | G2: Wave 4 | H2: spider | I2: Bespoke spider/fetcher - endpoint already known; extra work is pagination, auth or parsing | J2: D_woocommerce | K2: WooCommerce | L2: retailer_sku | M2: supermarket | N2: TJS | O2: 90 | P2: /wp-json/wc/store/v1/products (price field currently unreliable) | Q2: WordPress+WooCommerce confirmed. GET /wp-json/wc/store/v1/products?per_page=20 -> HTTP 200, structured JSON, TJS currency, but price=0 for every one of 25 sampled products across 2 pages. Frontend PDP for a different product (h1 'Yabloko Sultanat' -- apple) shows a real non-zero price '4.89c.' rendered in the page. Product-category nav includes fresh produce (arbuz/watermelon, chesnok/garlic) alongside household chemicals. | R2: TRUE | S2: DATA QUALITY CAVEAT: the Store API endpoint works structurally but returns price=0 site-wide while the HTML frontend shows real prices -- looks like a price-sync bug on the store's own catalogue, not a scraping problem. Would need to scrape rendered PDP HTML instead of trusting the API price field until this is resolved.
A3: eca | B3: germany | C3: Liefershop.de | D3: https://www.liefershop.de/ | E3: TIER_1B | F3: medium | G3: Wave 4 | H3: spider | I3: Bespoke spider/fetcher - endpoint already known; extra work is pagination, auth or parsing | J3: D_woocommerce | K3: WooCommerce | L3: retailer_sku | M3: supermarket | N3: EUR | O3: 60 | P3: /wp-json/wc/store/v1/products?per_page=N&page=N | Q3: WooCommerce Store API /wp-json/wc/store/v1/products confirmed working (HTTP 200). Page 1 returned mostly Juice Plus+ MLM products, but page 5 (offset) returned genuine F&B SKUs: 'Lamotte & Cie Champagne Brut', 'Tavernello Vino Rosato d'Italia', 'Kosakenkaffee', 'Carpe Diem Kombucha Classic', 'Saupiquet Thunfisch-Salat Mexicana', 'Küstengold Spargelabschnitte', 'Cinema Popcorn süss', 'Heisse Tasse Tomaten-Creme-Suppe', 'Nestlé Cerealien Mini Packs', 'Corny Müsli-Riegel' | R3: TRUE | S3: CSV gotcha confirmed and worse than described: catalog is heavily contaminated with Juice Plus+ MLM shake/supplement products interleaved with real wine/beverage/pantry SKUs - needs an MLM-brand filter before use.
A4: lac | B4: chile | C4: Jumbo Chile | D4: https://www.jumbo.cl/ | E4: TIER_1B | F4: medium | G4: Wave 4 | H4: spider | I4: Bespoke spider/fetcher - endpoint already known; extra work is pagination, auth or parsing | J4: E_vtex | K4: VTEX | L4: retailer_sku | M4: supermarket | N4: CLP | O4: 155 | P4: /api/catalog_system/pub/products/search (via jumbocl.myvtex.com origin, not the WAF'd custom domain) | Q4: Custom domain jumbo.cl/api/... 404s (Next.js frontend not proxying legacy API). VTEX origin GET https://jumbocl.myvtex.com/api/catalog_system/pub/products/search?_from=0&_to=5 -> HTTP 206, 110476 bytes. Sample: 'Platano Extra Granel (1 a 2 un. Aprox)' CLP 1590.0, link resolves to jumbocl.myvtex.com/platano-granel/p | R4: FALSE | S4: Cencosud CL flagship hypermarket. Spider must target the myvtex.com origin, not jumbo.cl, mirroring the Shopify *.myshopify.com origin trick in platform_fingerprints.md.
A5: lac | B5: paraguay | C5: Arete Supermercados | D5: https://arete.com.py/ | E5: TIER_1A | F5: medium | G5: Wave 4 | H5: spider | I5: Bespoke spider/fetcher - endpoint already known; extra work is pagination, auth or parsing | J5: E_vtex | K5: Custom (same URL shape/vendor as Casa Rica; a 'GET /api/catalog_system/...' probe on this domain returned the platform's own JSON error 'La funcion solicitada no existe', confirming it is NOT VTEX) | L5: retailer_sku | M5: supermarket | N5: PYG | O5: 150 | P5: /catalogo/<category-slug>-c<id> | Q5: GET https://arete.com.py/catalogo/arroz-c347 -> HTTP 200, 200343 bytes SSR HTML. Sample: 'ARROZ ENOC INTEGRAL 1 KG' Gs. 14.000 (other rows on same page: Gs. 2.850 / 5.500 / 5.200 / 9.950). Homepage has 162 distinct /catalogo/*-c<id> categories incl. aceites, arroz, frutas, frutas-y-verduras, leche-condensada. | R5: FALSE | S5: Second full-line PY chain on the same platform family as Casa Rica -- high category overlap expected.
A6: lac | B6: chile | C6: Santa Isabel | D6: https://www.santaisabel.cl/ | E6: TIER_1B | F6: medium | G6: Wave 4 | H6: spider | I6: Bespoke spider/fetcher - endpoint already known; extra work is pagination, auth or parsing | J6: E_vtex | K6: VTEX | L6: retailer_sku | M6: supermarket | N6: CLP | O6: 140 | P6: /api/catalog_system/pub/products/search (via santaisabel.myvtex.com origin) | Q6: Custom domain santaisabel.cl/api/... 404s. VTEX origin GET https://santaisabel.myvtex.com/api/catalog_system/pub/products/search?_from=0&_to=5 -> HTTP 206, 97397 bytes. Sample: 'Trutro Entero de Pollo kg' CLP 3990.0 | R6: FALSE | S6: Cencosud CL supermarket banner, fresh meat confirmed. Same myvtex-origin caveat as Jumbo CL.
A7: lac | B7: ecuador | C7: Tia | D7: https://www.tia.com.ec/supermercado | E7: TIER_1A | F7: medium | G7: Wave 4 | H7: spider | I7: Bespoke spider/fetcher - endpoint already known; extra work is pagination, auth or parsing | J7: H_magento | K7: Magento 2 (SSR HTML) | L7: retailer_sku | M7: supermarket | N7: USD | O7: 165 | P7: /supermercado/<category>/<subcategory> (Magento 2 SSR category pages; /catalogsearch/result redirect confirms Magento) | Q7: GET https://www.tia.com.ec/supermercado/frutas-y-verduras/frutas -> HTTP 200, 319188 bytes SSR HTML. Product name + price directly in listing markup: 'ARANDANO BANDEJA 125 G' USD 1.59 (class=product-item-name / product-item-link). Full /supermercado nav tree includes aguas-y-bebidas, comestibles/{aceites-y-vinagres, arroz-y-fideos, cafe-y-chocolate-en-polvo, cereales-y-granolas, dulces-postres-y-untables, enlatados-y-conservas, granos-y-semillas, harinas-y-avenas, te-y-aromaticas}, desechables, frutas-y-verduras, lacteos/{crema-de-leche, huevos, leche-en-polvo, leches-blancas, leches-saborizadas, leches-vegetales, quesos, yogurt}, pastas, snacks-y-golosinas/{cakes-y-bocaditos, chocolates, galletas, papas-fritas, snacks-de-maiz}. | R7: FALSE | S7: Ecuador's largest variety/discount retailer, full grocery vertical confirmed via nav tree. Magento GraphQL (/graphql) 403s -- scrape via SSR category pagination instead.
A8: ssa | B8: senegal | C8: Kaynoo | D8: https://www.kaynoo.sn/epicerie.html | E8: TIER_1B | F8: medium | G8: Wave 4 | H8: spider | I8: Bespoke spider/fetcher - endpoint already known; extra work is pagination, auth or parsing | J8: H_magento | K8: Magento | L8: retailer_sku | M8: supermarket | N8: XOF | O8: 45 | P8: Magento GraphQL or /rest/V1/products | Q8: GET /epicerie.html -> 200, 361KB, Magento fingerprint confirmed (price-box price-final_price divs, data-price-amount='2500'/'4500'/'4000' on real product ids). Catalogue mixes food with cosmetics per prior research -- filter by category. | R8: TRUE | S8: Strong on local items (cafe Touba in 3 pack sizes, moringa/nebeday, baobab-adjacent) but heavy overlap with Sakanal/Yombouna's epicerie coverage -- most of its value is depth on a handful of leaves, not breadth.
A9: eca | B9: croatia | C9: Konzum | D9: https://www.konzum.hr/kreni-u-kupnju | E9: TIER_1A | F9: medium | G9: Wave 4 | H9: spider | I9: Bespoke spider/fetcher - endpoint already known; extra work is pagination, auth or parsing | J9: Z_bespoke | K9: Next.js | L9: retailer_sku | M9: supermarket | N9: EUR | O9: 170 | P9: SSR category HTML | Q9: GET -> 200, 291KB SSR (Next.js). Direct prices in HTML: 1,49€ / 2,99€ / 3,99€ / 180,00€. | R9: TRUE | S9: 12,000+ products; per shard, 5 price fields per SKU (current/unit-per-kg/30-day-low/reference-date/promo-end) -- capture all 5, not just current.
A10: lac | B10: paraguay | C10: Casa Rica | D10: https://www.casarica.com.py/ | E10: TIER_1A | F10: medium | G10: Wave 4 | H10: spider | I10: Bespoke spider/fetcher - endpoint already known; extra work is pagination, auth or parsing | J10: Z_bespoke | K10: Custom (shared by several PY grocery sites, same '/catalogo/*-c<id>' URL shape and identical API error string) | L10: retailer_sku | M10: supermarket | N10: PYG | O10: 165 | P10: /catalogo/<category-slug>-c<id> (custom PY grocery-platform vendor, SSR HTML, paginated) | Q10: GET https://www.casarica.com.py/catalogo/aceite-de-girasol-c2 -> HTTP 200, 286701 bytes SSR HTML. Products+prices directly in markup: 'ACEITE CANUELAS GIRASOL 1.5LT' Gs. 29.000, 'ACEITE COCINERO GIRASOL PET 900ML' Gs. 21.000. Homepage lists 261 distinct /catalogo/<slug>-c<id> category links spanning vacuno (beef), verduleria-fruteria, verduras, semiblandos/semiduros (cheese), yogurt-entero/dietetico, salames, rotiseria, sal, te, yerba, vinos by country, sidras. | R10: FALSE | S10: Full-line Asuncion-area supermarket chain incl. fresh meat/produce/deli.
A11: eca | B11: netherlands | C11: Jumbo | D11: https://www.jumbo.com/ | E11: TIER_1A | F11: medium | G11: Wave 4 | H11: spider | I11: Bespoke spider/fetcher - endpoint already known; extra work is pagination, auth or parsing | J11: Z_bespoke | K11: Vue | L11: retailer_sku | M11: supermarket | N11: EUR | O11: 160 | P11: SSR category HTML (/producten/) | Q11: GET /producten/ -> 200, 1.32MB SSR (Vue). Product cards found (data-testid='product-card-0', data-product-id='765935ZK') with 'Prijs: € 3,25' in the price DOM. | R11: TRUE | S11: Overturns shard's D-tier 'SUSPECT' prediction -- category page renders server-side with real product cards, no WAF. ~20-22k articles per shard; runs a lowest-price-guarantee mechanically tied to competitors.
A12: eca | B12: spain | C12: Precios del Super | D12: https://preciosdelsuper.es/ | E12: TIER_1A | F12: medium | G12: Wave 4 | H12: spider | I12: Bespoke spider/fetcher - endpoint already known; extra work is pagination, auth or parsing | J12: Z_bespoke | K12: Custom | L12: retailer_sku | M12: aggregator | N12: EUR | O12: 160 | P12: SSR listing HTML | Q12: GET -> 200, 124KB SSR. Direct prices '2,99€' / '16,95€' in HTML. | R12: TRUE | S12: 120,000+ products across 8 supermarkets per shard, with per-product price history and a daily changes feed.
A13: eca | B13: georgia | C13: Wolt Market Georgia | D13: https://wolt.com/en/geo/tbilisi/category/grocery | E13: TIER_1B | F13: medium | G13: Wave 4 | H13: spider | I13: Bespoke spider/fetcher - endpoint already known; extra work is pagination, auth or parsing | J13: Z_bespoke | K13: Custom (Wolt public API) | L13: retailer_sku | M13: aggregator | N13: GEL | O13: 150 | P13: restaurant-api.wolt.com/v1/pages/restaurants | Q13: GET https://restaurant-api.wolt.com/v1/pages/restaurants?lat=41.7151&lon=44.8271 -> HTTP 200, 2.77MB JSON, 1315 venues in the 'restaurants-delivering-venues' section for Tbilisi (includes named grocery chains: SPAR, IOLI, Rkoni, Europroduct, Smart, etc. per CSV). Public API, no auth required. | R13: TRUE | S13: Directory endpoint confirmed; per-venue menu endpoint (restaurant-api.wolt.com/v3/venues/slug/<slug>/menu/data) not individually tested this round but is a documented Wolt pattern. Aggregator margin caveat applies vs shelf price.
... A17: ssa | B17: mozambique | C17: RECHEIO Cash & Carry | D17: https://recheio.co.mz/ | E17: TIER_1A | F17: medium | G17: Wave 4 | H17: spider | I17: Bespoke spider/fetcher - endpoint already known; extra work is pagination, auth or parsing | J17: Z_bespoke | K17: Custom (ASP.NET-style) | L17: retailer_sku | M17: supermarket | N17: MZN | O17: 120 | P17: unresolved exact product endpoint -- category page confirmed live | Q17: GET / -> 200, 141KB. Attempted category page GET /loja/mercearia -> 200, 40KB, real title 'Mercearia ao Melhor Preco em Mocambique' confirming the category exists live, but no price-class markup surfaced in that page's raw HTML this pass (likely paginated/AJAX-loaded product grid). | R17: TRUE | S17: 1,456 products in mercearia alone + full aisle taxonomy (lacticinios, carne e peixe, bebidas, vegetais, loja asiatica) per prior research -- best Mozambique source, but I could not independently pull a live price this pass so the estimate is held below the presumed max.
A18: eap | B18: japan | C18: opengov.jp Retail Price Survey (re-publication of MIC Statistics Bureau retail price survey) | D18: https://opengov.jp/en/prices/retail-prices/ | E18: TIER_1A | F18: medium | G18: Wave 4 | H18: fetcher | I18: Bespoke spider/fetcher - endpoint already known; extra work is pagination, auth or parsing | J18: Z_bespoke | K18: Custom | L18: official_avg | N18: JPY | O18: 115 | P18: /en/prices/retail-prices/<code>/ (per-item static HTML page; codes prefixed 01xx = food, 02xx = alcohol) | Q18: GET /en/prices/retail-prices/ -> 200, 366KB HTML, 541 item-code links with English names, e.g. '01001 | Rice A', '01101 | Tuna', '01414 | Daikon radish', '01131 | Short-neck clam'. GET /en/prices/retail-prices/01001/ -> 200, title 'Rice A Retail Prices', year table: 2026 Jan national-average price JPY 5,317 (+27.0% YoY). Plain curl with a browser UA, no JS, no auth. | R18: FALSE | S18: 541 total item codes span the whole CPI basket by prefix: 01=207 items (food), 02=32 (alcohol), 03-09=302 (rent/clothing/health/education/personal care, out of scope). The 01+02 subset reaches deep, specific division-01 leaves current Japan sources miss entirely -- named fish species (tuna, horse mackerel, sardine, salmon, mackerel, sea bream, yellowtail, squid, octopus, shrimp, clam, oyster, scallop -> COICOP 01.1.3.x), named vegetables (cabbage, lettuce, daikon, broccoli, spinach, onion, ginger -> 01.1.7.x), noodles/rice/bread/flour, dairy, and Sake/Shochu/Chuhai for div-02. Japan's existing onboarded set (rakuten, yahoo_shopping, docomo, athome_jp, homes_jp, hotpepper_jp) is mostly non-grocery (real estate, mobile plans, restaurant bookings) -- this is likely Japan's primary deep-F&B channel, not a supplement. CAVEAT not fully resolved this session: the item page shown is a Year+Jan-value summary table; unclear whether opengov.jp exposes the full monthly series the underlying survey actually produces, or only this annual snapshot -- verify cadence before onboarding. 541 pages to walk (one HTTP call per item) makes this medium, not low, effort.
A19: eca | B19: azerbaijan | C19: Wolt Baku grocery (aggregator) | D19: https://wolt.com/en/aze/baku/category/grocery | E19: TIER_1B | F19: medium | G19: Wave 4 | H19: spider | I19: Bespoke spider/fetcher - endpoint already known; extra work is pagination, auth or parsing | J19: Z_bespoke | K19: Custom | L19: retailer_sku | M19: aggregator | N19: AZN | O19: 100 | P19: page-embedded JSON | Q19: GET -> 200, 2MB. Embedded JSON: store list w/ prices e.g. 'price':935 (9.35 AZN); store names include 'SPAR Ehmed Recebli','Bravo Supermarket Winter Park','Araz Statistics 2 Supermarket','Tamstore Express Fountain sq.','Oba Market Ahmadli'. | R19: TRUE | S19: Marketplace directory of ~7 Baku chains, several labelled 'same prices as in store'. Treat as directory first: consolation-prize catalog scrape only if per-store storefronts fail.
A20: lac | B20: st_vincent_and_the_grenadines | C20: C.K. Greaves & Company | D20: https://www.ckgreaves.com/ | E20: TIER_1A | F20: medium | G20: Wave 4 | H20: spider | I20: Bespoke spider/fetcher - endpoint already known; extra work is pagination, auth or parsing | J20: Z_bespoke | K20: WordPress + custom shop module | L20: retailer_sku | M20: supermarket | N20: XCD | O20: 100 | P20: /shop/browse/product/{id}_{slug}/ (SSR PDP) | Q20: GET /shop/browse/product/19751_b-bird-apple-juice-340ml/ -> HTTP 200, 102KB HTML with real embedded price markup ('<div class="price-now..."><span class="sym">$</span><strong class="dol">4</strong><em class="dec">35</em></div>' = $4.35) for product 'B Bird Apple Juice 340ml'. Product catalog browsable via /departments/ and /shop/browse/product/ paths (WordPress-hosted custom storefront, not WooCommerce core — /wp-json/wc/store/v1/products returned HTTP 404). | R20: FALSE | S20: Currency shown only as generic '$' symbol; XCD assumed from SVG's official currency per country-currency conventions (not confirmed by an explicit currency code in the page). Catalog skews packaged goods (juice, tea, cleaning, pet products) in the pages sampled — fresh produce/meat depth unconfirmed.
A21: sar | B21: nepal | C21: MeroKirana | D21: https://merokirana.com/ | E21: TIER_1B | F21: medium | G21: Wave 4 | H21: spider | I21: Bespoke spider/fetcher - endpoint already known; extra work is pagination, auth or parsing | J21: Z_bespoke | K21: Custom (Semantro) | L21: retailer_sku | M21: supermarket | N21: NPR | O21: 95 | P21: POST /semantro-web-interface/query | Q21: React SPA over a proprietary 'Semantro' backend at POST https://merokirana.com/semantro-web-interface/query (multipart form field 'data' = JSON action descriptor, plain curl, no auth/cookies). actionName=listBaseCategories -> 10 categories incl. Veg & Fruits, Eggs & Meat, Bakery & Dairy. actionName=listLatestProducts (pageLimit start/end) -> product id list. actionName=getProductData per product -> price+currency. Verified end-to-end: 'Kejjan's Snail Mucin & Rice Water Face Toner, 150ml' -> priceCurrency 'NRs.', price 555.0. | R21: TRUE | S21: Only category-scoped listing action name unconfirmed in the time budget (listLatestProducts has no categoryId param seen); listBaseCategories + getProductData are proven and category id is already known ('Veg & Fruits' id=35ae95a75bda48a3-ac60b32fab01d5db) so a category-listing action almost certainly exists next to listLatestProducts -- probe further before scaffolding. DDC (state dairy) lines per shard notes.
A22: lac | B22: haiti | C22: KITT National | D22: https://kittnational.com/ | E22: TIER_1B | F22: medium | G22: Wave 4 | H22: spider | I22: Bespoke spider/fetcher - endpoint already known; extra work is pagination, auth or parsing | J22: Z_bespoke | K22: Supabase/React SPA | L22: retailer_sku | M22: marketplace | N22: HTG | O22: 40 | P22: https://2kug72le92fjtj5suphu.helloreaddy.com/rest/v1/product_items (Supabase REST, publishable key required) | Q22: Playwright network trace found a Supabase PostgREST backend (helloreaddy.com) with a client-side publishable key (sb_publishable_...) captured from page requests. GET .../rest/v1/product_items?select=id,name,price,category_id&status=eq.active with apikey+Authorization headers -> 200. Sample: 'Nutella — Bokal Pate Chokola 26.5 oz' HTG 1427.15. Prefer:count=exact shows 1,341 total active products across categories including Manje (Food), Bwason (Beverages), Desè (Dessert), Maket (Market/general). | R22: TRUE | S22: General last-mile delivery/marketplace platform (electronics, auto, clothing, tools) with a food/beverage/dessert vertical, not a dedicated grocery store; F&B share of the 1,341-item catalog is a minority. Needed a Playwright pass to capture the anon API key before curl worked.
A23: lac | B23: trinidad_and_tobago | C23: TriniCart | D23: https://trinicart.pro/ | E23: TIER_1B | F23: medium | G23: Wave 4 | H23: spider | I23: Bespoke spider/fetcher - endpoint already known; extra work is pagination, auth or parsing | J23: Z_bespoke | K23: Supabase/React SPA | L23: retailer_sku | M23: supermarket | N23: TTD | O23: 40 | P23: https://lmrfzrshpwqxaeorfecv.supabase.co/rest/v1/admin_content?select=value&key=eq.maraval-products-v1 (Supabase REST, anon key required) | Q23: curl on root -> 1.9KB Vite/React SPA shell. Playwright network trace found a Supabase backend (lmrfzrshpwqxaeorfecv.supabase.co) with an anon JWT key captured from page requests. GET .../rest/v1/admin_content?select=value&key=eq.maraval-products-v1 with apikey+Authorization -> 200, 116KB JSON containing a 'custom' product array (173 items). Sample: 'Chief All Purpose Seasoning 40g' TTD 12.00. | R23: TRUE | S23: Smaller catalog per CSV notes (173 items). Product data is embedded as a JSON blob inside a generic 'admin_content' key/value row, not a normal paginated products table — parse accordingly. Needed a Playwright pass to capture the anon key before curl worked.
A24: sar | B24: nepal | C24: Daraz Nepal (catalog search AJAX) | D24: https://www.daraz.com.np/ | E24: TIER_1B | F24: medium | G24: Wave 4 | H24: spider | I24: Bespoke spider/fetcher - endpoint already known; extra work is pagination, auth or parsing | J24: Z_bespoke | K24: Custom/Enterprise (Lazada-derived, mtop stack for other endpoints but the catalog/search ajax itself is unsigned) | L24: retailer_sku | M24: marketplace | N24: NPR | O24: 20 | P24: GET /catalog/?ajax=true&isFirstRequest=true&page=N&q=<keyword> | Q24: GET https://www.daraz.com.np/catalog/?ajax=true&isFirstRequest=true&page=1&q=rice -> 200, 131488 bytes JSON, plain curl with browser UA, no auth/session needed. mods.listItems = 40 products/page with name, price, originalPrice, discount, sellerName, categories. Sample: 'Hilife Pulao Basmati Rice 1 Kg' price=264 originalPrice=270 discount='2% Off'. | R24: TRUE | S24: Reaching leaf breadth requires walking a keyword list (one query per leaf/commodity) rather than a category crawl -- higher scaffolding effort than a catalog endpoint. Confirms shard's was_price/discount capture need for flash-sale distortion. Third-party seller names carried per item (dMart pantry vertical mixed with generic marketplace sellers).
A25: lac | B25: peru | C25: Inkafarma | D25: https://inkafarma.pe/ | E25: TIER_1B | F25: medium | G25: Wave 4 | H25: spider | I25: Bespoke spider/fetcher - endpoint already known; extra work is pagination, auth or parsing | J25: Z_bespoke | K25: Custom (AWS API Gateway) | L25: retailer_sku | M25: pharmacy | N25: PEN | O25: 20 | P25: https://5doa19p9r7.execute-api.us-east-1.amazonaws.com/MMPROD/products/{skus}?companyCode=IKF&saleChannel=WEB&saleChannelType=DIGITAL | Q25: The CSV-listed VTEX endpoint (/api/catalog_system/pub/products/search) returns the SPA shell (text/html), not JSON — not actually VTEX. Playwright network trace found the real backend: AWS API Gateway https://5doa19p9r7.execute-api.us-east-1.amazonaws.com/MMPROD/products/{comma-sep-skus}?companyCode=IKF&saleChannel=WEB&saleChannelType=DIGITAL. Replayed with plain curl (no auth needed) -> 200, 21.3KB JSON for 2 SKUs. Sample: 'Gel Limpiador Bioderma Sébium Moussant Piel Mixta a Grasa' PEN 159.90. | R25: TRUE | S25: CSV wrongly listed this as VTEX. Endpoint is keyed by SKU code, not paginated by category — a search/listing endpoint to enumerate SKUs was not found in this probe pass; would need one more Playwright capture on a search query before scaffolding a full-catalog walker. Pharmacy chain, COICOP 6 focus.
A26: eap | B26: japan | C26: opengov.jp Wholesale Produce Market Prices (MAFF daily wholesale data, 30 central markets) | D26: https://opengov.jp/en/prices/vegetable-market/ | E26: TIER_1A | F26: medium | G26: Wave 4 | H26: fetcher | I26: Bespoke spider/fetcher - endpoint already known; extra work is pagination, auth or parsing | J26: Z_bespoke | K26: Custom | L26: official_avg | M26: wholesale | N26: JPY | O26: 15 | P26: /en/prices/vegetable-market/<commodity_code>/ | Q26: GET /en/prices/vegetable-market/ -> 200, 361KB HTML, 71 commodity-code links (e.g. 30100). GET /en/prices/vegetable-market/30100/ -> 200, title 'Daikon radish (だいこん) Wholesale Price Trends -- Grade-Specific Market Data', daily rows across 5 regional markets, e.g. '2026-04-02 Morioka (盛岡) JPY124 29.4t Slightly rising'. Plain curl, no auth. | R26: FALSE | S26: MAFF daily wholesale high/low + trading volume across 30 central markets, 71 fresh vegetable/fruit commodity codes, 16 years of history per site claim. Substantially overlaps the vegetable/fruit items already in the retail-prices source above (same crops, finer market-level granularity) -- scored as a smaller incremental add rather than fully additive, mainly for cultivar-level depth (e.g. distinct radish/cabbage varieties) the retail survey collapses to one line.
A27: sar | B27: nepal | C27: Thulo.com supermarket panel | D27: https://thulo.com.np/supermarket | E27: TIER_1B | F27: medium | G27: Wave 4 | H27: spider | I27: Bespoke spider/fetcher - endpoint already known; extra work is pagination, auth or parsing | J27: Z_bespoke | K27: Custom | L27: retailer_sku | M27: supermarket | N27: NPR | O27: 12 | P27: GET /thulo-product/shop?category=N&maxp=N | Q27: GET https://thulo.com.np/thulo-product/shop?category=394&maxp=35670 -> 200, 63201 bytes JSON with a single 'grid' key containing an HTML fragment (plain curl, no auth). Product titles extracted from 'global-card-contents-title' anchors, e.g. 'Maghe Special Combo Set 3'; PDP links point to named-vendor subdomains (pasal101.thulo.com.np/shop/...), confirming the multi-vendor panel structure the shard notes describe. | R27: TRUE | S27: category=394 sampled was a promo/combo bucket, not necessarily representative; full category id list (dairy-products-en link seen on the listing page) not enumerated in the time budget. Must dedupe on vendor+SKU (same product repeats across named vendors) per shard AI_NOTES. Price extraction needs a second regex pass -- offerPrice/productPrice classes present but not cleanly captured in this probe.
A28: sar | B28: nepal | C28: Goket Groceries | D28: https://www.goket.com.np/ | E28: TIER_1A | F28: medium | G28: Wave 4 | H28: spider | I28: Bespoke spider/fetcher - endpoint already known; extra work is pagination, auth or parsing | J28: Z_bespoke | K28: Custom (Next.js) | L28: retailer_sku | M28: supermarket | N28: NPR | O28: 3 | P28: GET /categories (category listing only; product/price endpoint unconfirmed) | Q28: GET https://www.goket.com.np/categories -> 200, 32671 bytes, plain curl, no auth. Real category names embedded in HTML: Baby Care, Beverages, Cleaning Supplies, Packaged Foods, Pantry Staples, Personal Care -- but zero price or product-slug tokens found on that page (products load one level deeper, not confirmed in time budget). Next.js app. | R28: TRUE | S28: Matches shard's SUSPECT verdict: app-led catalog (dedicated iOS app), thin 6-category set with no visible fresh produce/dairy/meat. Low priority relative to MeroKirana/Vhandar which are already deeper and confirmed end-to-end.
A29: menaap | B29: egypt | C29: Talabat Egypt | D29: https://www.talabat.com/egypt/groceries | E29: TIER_1A | F29: medium | G29: Wave 4 | H29: spider | I29: Bespoke spider/fetcher - endpoint already known; extra work is pagination, auth or parsing | J29: Z_bespoke | K29: Custom (Next.js) | L29: seller_directory | M29: marketplace | N29: EGP | O29: 0 | P29: /egypt/groceries/{areaId}/{slug} (SSR __NEXT_DATA__) + /nextLocationApi/location/country-areas/{countryId} for area enumeration | Q29: curl on /egypt/groceries/<areaId>/<slug> server-renders a __NEXT_DATA__ blob with props.pageProps.vendors[] -- 20 vendors per area, no auth. First attempt with a guessed area id (59) accidentally returned Kuwaiti vendors (Talabat area IDs are NOT country-namespaced in the URL). Fixed by first calling https://www.talabat.com/nextLocationApi/location/country-areas/9 (curl, 200, 466KB JSON) which lists real Egypt area ids/slugs (country id 9 = Egypt, areas keyed by Arabic city/area names e.g. القاهرة=Cairo). Re-probed /egypt/groceries/10032/faisal-el-taawon-2 -> 20 genuine Egyptian vendors: 'Souq El Aasr', 'Akher Sa'a Bakery', 'Elsuhagi For Poultry & Butchery', 'Kheir Zaman', 'Carrefour', 'Metro Market', 'talabat mart', 'tKiosk by tMart'. | R29: TRUE | S29: MAJOR discovery asset confirmed live: enumerates independent traditional retailers with no web presence (dairies, roasteries, butchers, fruit sellers) across every Egyptian area/city. Prices include platform margin per CSV -- use as a store/seller directory, not a price series, except where no alternative exists (traditional retail). Walking all areas from country-areas/9 would produce a full seller census. | T29: Area IDs are global across Talabat's whole footprint, not scoped per country segment in the URL -- always resolve area ids via nextLocationApi/location/country-areas/{countryId} first, never guess small integers.
A30: eca | B30: malta | C30: Greens Supermarket | D30: https://www.greens.com.mt/ | E30: TIER_2 | F30: medium | G30: Wave 5 | H30: spider | I30: Playwright DISCOVERY pass first - find the internal JSON endpoint, then scrape it over plain HTTP | J30: D_woocommerce | K30: Custom (not WooCommerce, despite CSV label) | L30: retailer_sku | M30: supermarket | N30: EUR | O30: 0 | P30: not WooCommerce - platform misidentified in CSV | Q30: curl 200 (after -L redirect to www.), but the WooCommerce Store API path returned the homepage HTML (bootstrap-based custom theme), not JSON - CSV's 'WordPress/WooCommerce' platform tag appears wrong for this site | R30: TRUE | S30: Needs a proper platform re-identification pass; not blocked, just not WooCommerce as labeled.
A31: eca | B31: slovenia | C31: Tus | D31: https://www.tus.si/ | E31: TIER_2 | F31: medium | G31: Wave 5 | H31: spider | I31: Playwright DISCOVERY pass first - find the internal JSON endpoint, then scrape it over plain HTTP | J31: D_woocommerce | K31: possibly WooCommerce | L31: retailer_sku | M31: supermarket | N31: EUR | O31: 0 | P31: not confirmed | Q31: curl 200, 181KB, woocommerce string found but no product prices confirmed on homepage | R31: TRUE | S31: Worth a follow-up WooCommerce Store API check given the platform hint.
A32: eca | B32: uzbekistan | C32: Korzinka | D32: https://www.korzinka.uz/en | E32: TIER_2 | F32: medium | G32: Wave 5 | H32: spider | I32: Playwright DISCOVERY pass first - find the internal JSON endpoint, then scrape it over plain HTTP | J32: Z_bespoke | K32: Nuxt/Vue | L32: retailer_sku | M32: supermarket | N32: UZS | O32: 140 | P32: api.korzinka.uz (exact route TBD) | Q32: curl -> 403 'Just a moment...' Cloudflare challenge. Playwright render (homepage and /en/catalog) -> HTTP 200, real content: 'product__price'/'product__price-current' DOM classes present, soum-denominated values visible after render (e.g. '300 000 soum'). Backend host api.korzinka.uz confirmed live (returns a structured JSON error for a wrong method rather than a block), but the correct catalog route was not found within the time budget. | R32: TRUE | S32: 250+ stores, 12 regions, own online supermarket since 2005 per shard. curl-blocked but Playwright bypasses cleanly -- needs a render-then-scrape approach or the right api.korzinka.uz route.
A33: eca | B33: moldova | C33: Casa Mega | D33: https://casamega.md/ | E33: TIER_2 | F33: medium | G33: Wave 5 | H33: spider | I33: Playwright DISCOVERY pass first - find the internal JSON endpoint, then scrape it over plain HTTP | J33: Z_bespoke | K33: CS-Cart | L33: retailer_sku | M33: supermarket | N33: MDL | O33: 130 | P33: SSR after JS challenge clears | Q33: curl -> 403 'DDOS protection page'. Playwright render -> 200, 2.57MB, CS-Cart platform confirmed ('ty-price-num' class), real prices visible after render: '2 399.00' / '599.00' / '1 699.00' MDL. | R33: TRUE | S33: curl-blocked but Playwright bypasses cleanly -- not a hard Cloudflare-strict block, needs a headless-render step in the spider or cookie replay.
A34: lac | B34: barbados | C34: PriceSmart Barbados | D34: https://www.pricesmart.com/en-BB/category/Groceries/G10D03 | E34: TIER_2 | F34: medium | G34: Wave 5 | H34: spider | I34: Playwright DISCOVERY pass first - find the internal JSON endpoint, then scrape it over plain HTTP | J34: Z_bespoke | K34: Custom/Nuxt | L34: retailer_sku | M34: warehouse_club | N34: USD (site header shows $, region en-BB; verify BBD vs USD display before scaffolding) | O34: 90 | P34: POST /api/ct/getCategory (session-gated, Playwright only) | Q34: curl: 200/383KB but Nuxt SPA shell, zero prices in raw HTML (only account/login form fields). Playwright render (8s wait): prices visible ($49.00-$399.99 range) and product names extracted via a[href*='/product/'] selector: 'Maeva Avocado Oil Spray 2 Units / 200 mL', 'Froot Loops Chocolate Flavored Cereal 878 g'. Internal API is POST https://www.pricesmart.com/api/ct/getCategory (not GET-replayable with curl; needs session state). | R34: TRUE | S34: Warehouse-club pack sizes; needs Playwright render at collection time since API is POST + session-cookie gated.
A35: eca | B35: romania | C35: Monitorul Preturilor (Competition Council) | D35: https://monitorulpreturilor.info/Home/Monitor | E35: TIER_2 | F35: medium | G35: Wave 5 | H35: fetcher | I35: Playwright DISCOVERY pass first - find the internal JSON endpoint, then scrape it over plain HTTP | J35: Z_bespoke | K35: Custom (Kendo UI + Firebase) | L35: official_avg | M35: official | N35: RON | O35: 41 | P35: unresolved - needs interactive location-selection flow | Q35: curl 200, 11.8KB Kendo-UI shell (no inline data). Playwright 7s network capture triggered zero XHR to a data endpoint -> page likely gates behind a location/county selector (site references '/Settings/Location') before the grid loads. | R35: TRUE | S35: Official Competition Council feed, 7 participating chains (Mega Image, Lidl, Kaufland, Selgros, Carrefour, Penny, Profi) with a dedicated capped-commercial-margin section (41 products: bread, milk, telemea, yoghurt, flour, eggs, oil, chicken, pork, tomatoes, onions, sugar, potatoes). High value but needs one more probing session to find the grid's data endpoint.
A36: eca | B36: germany | C36: mytime.de | D36: https://www.mytime.de/ | E36: TIER_2 | F36: medium | G36: Wave 5 | H36: spider | I36: Playwright DISCOVERY pass first - find the internal JSON endpoint, then scrape it over plain HTTP | J36: Z_bespoke | K36: Custom | L36: retailer_sku | M36: supermarket | N36: EUR | O36: 40 | P36: not fully isolated | Q36: curl 200, 300KB, some real prices found in raw HTML: '2,49 €', '3,49 €' mixed with '0,00 €' cart placeholders | R36: TRUE | S36: Full-assortment nationwide per CSV; partial price evidence found, category page would confirm depth.
A37: ssa | B37: senegal | C37: DiborMarket | D37: https://lafermededibor.com/ | E37: TIER_2 | F37: medium | G37: Wave 5 | H37: spider | I37: Playwright DISCOVERY pass first - find the internal JSON endpoint, then scrape it over plain HTTP | J37: Z_bespoke | K37: Custom | L37: retailer_sku | M37: supermarket | N37: XOF | O37: 25 | P37: unresolved -- homepage only | Q37: GET / -> 200, 15.8KB HTML, no SPA markers (no id=app/root, no ng-version), but no price class or FCFA pattern matched in the homepage HTML either -- catalogue likely lives on a /shop or category path not probed this pass. | R37: TRUE | S37: Prior research is specific enough to trust directionally (feuille de manioc, madd, gombo, diakhatou aubergine, graded 5/10/25kg onion and potato sacks) -- this is the only source in the shard reaching those local-item leaves, but I could not independently re-verify a live price this pass.
A38: eca | B38: serbia | C38: Maxi | D38: https://www.maxi.rs/ | E38: TIER_2 | F38: medium | G38: Wave 5 | H38: spider | I38: Playwright DISCOVERY pass first - find the internal JSON endpoint, then scrape it over plain HTTP | J38: Z_bespoke | K38: Next.js | L38: retailer_sku | M38: supermarket | N38: RSD | O38: 20 | P38: category tree confirmed, product/price endpoint not isolated | Q38: curl 200, 1.14MB, Next.js + GraphQL detected. Real top-level category tile confirmed in raw HTML: data-testid='category-tile' aria-label='Mlecni proizvodi i jaja' (Dairy products and eggs) linking to /Mlechni-proizvodi-i-jaja/c/02 - category structure confirmed but per-product prices not yet isolated | R38: TRUE | S38: Delhaize-group national leader; also on Wolt/Glovo in 14 cities per CSV. Small partial credit given confirmed dairy category.
A39: sar | B39: sri_lanka | C39: HARTI -- Daily & Weekly Food Commodities Bulletin | D39: http://www.harti.gov.lk/daily-price.php | E39: TIER_2 | F39: medium | G39: Wave 5 | H39: fetcher | I39: Playwright DISCOVERY pass first - find the internal JSON endpoint, then scrape it over plain HTTP | J39: Z_bespoke | K39: PDF bulletin archive (no auth) | L39: official_avg | M39: official_avg | N39: LKR | O39: 10 | P39: assets/pdf/food_price/{daily,weekly}/{eng,sin}/{year}/[month/]{file}.pdf | Q39: GET /daily-price.php -> 200, listing daily PDF bulletins back to 2015 at a predictable path (assets/pdf/food_price/daily/eng/{year}/{month}/daily_{DD-MM-YYYY}.pdf). Sampled 2015-08-03 PDF (200/99KB) via pdftotext: 'Wholesale Prices of Rice & Subsidiary Food Crops', Pettah market, item/range/average/change columns for Nadu/Samba/Kekulu rice grades, Dried Chillies, Onions (Sinnan/Vedalan/imported), Potatoes. Weekly bulletin also exists in English (assets/pdf/food_price/weekly/eng/2026/weekly_10_2026_Eng.pdf, confirmed link present) and Sinhala; sampled Sinhala weekly PDF (2.97MB) shows broader coverage: rice, onions, potatoes, imported dried chillies, vegetables (carrots, cabbage), fish (mackerel). | R39: FALSE | S39: Wholesale (Pettah market) rice + subsidiary-crop feed, PDF-only (needs a table-extraction step, e.g. pdftotext/camelot, not a JSON walk). fnb_leaves_est is the INCREMENTAL contribution over DCS's retail feed -- most of what HARTI covers (rice grades, onions, chilies, potatoes) already overlaps DCS. Kept mainly for the wholesale/retail cross-check it enables, and because the weekly bulletin's vegetable/fish mentions suggest slightly broader coverage than the daily one -- would need a full PDF parse to confirm exact leaf count.
A40: eca | B40: norway | C40: Vinmonopolet | D40: https://www.vinmonopolet.no/ | E40: TIER_2 | F40: medium | G40: Wave 5 | H40: fetcher | I40: Playwright DISCOVERY pass first - find the internal JSON endpoint, then scrape it over plain HTTP | J40: Z_bespoke | K40: Custom | L40: official_avg | M40: official | N40: NOK | O40: 9 | P40: not found (search guess 404'd) | Q40: curl 200, 38.2KB homepage; nav grep confirms real alcohol-category names: 'Alkoholfritt' (non-alcoholic), 'Aromatisert vin' (aromatized wine), 'Brennevin' (spirits), 'Fruktvin' (fruit wine), 'Alle varer' (all products) - a guessed /sok?q= search path 404'd | R40: TRUE | S40: State alcohol monopoly - administered prices per CSV. Category evidence confirms full COICOP 02.1 alcohol range; complete national catalogue once the product/search endpoint is found.
A41: eca | B41: romania | C41: Mega Image | D41: https://www.mega-image.ro/ | E41: TIER_2 | F41: medium | G41: Wave 5 | H41: spider | I41: Playwright DISCOVERY pass first - find the internal JSON endpoint, then scrape it over plain HTTP | J41: Z_bespoke | K41: Next.js | L41: retailer_sku | M41: supermarket | N41: RON | O41: 0 | P41: not found | Q41: curl 200, 1.29MB, Next.js + GraphQL detected; only match on homepage was a '0,00 Lei' basket-total placeholder, no product prices confirmed yet | R41: TRUE | S41: CSV flags CONNECT loyalty price vs standard price as a distinct field worth capturing once the category page is probed.
... A80: eca | B80: norway | C80: Meny | D80: https://meny.no/ | E80: TIER_2 | F80: medium | G80: Wave 5 | H80: spider | I80: Playwright DISCOVERY pass first - find the internal JSON endpoint, then scrape it over plain HTTP | J80: Z_bespoke | K80: Custom | L80: retailer_sku | M80: supermarket | N80: NOK | O80: 0 | P80: not found | Q80: curl 200, 316KB homepage; /varer path returns 200/227KB but no price pattern or F&B category names matched in nav grep (menu/corporate items only, one recipe name 'Pastagrateng med kjottdeig') | R80: TRUE | S80: The /varer route exists (not 404) but reads as a category hub, not a product listing.
A81: eca | B81: croatia | C81: Tommy / Cjenoteka / Eurospin Croatia / Lidl Croatia | D81: https://www.tommy.hr/naruci-i-pokupi ; https://cjenoteka.hr/ ; https://www.eurospin.hr/ ; https://www.lidl.hr/ | E81: TIER_2 | F81: medium | G81: Wave 5 | H81: spider | I81: Playwright DISCOVERY pass first - find the internal JSON endpoint, then scrape it over plain HTTP | J81: Z_bespoke | K81: Next.js/React | L81: retailer_sku | M81: supermarket/aggregator | N81: EUR | O81: 0 | Q81: All 4 returned curl 200 (109KB/671KB/76KB/373KB) with Next.js/React markers present, but a quick grep for price patterns on the homepage/guessed-category found none -- likely needs the correct category URL or Playwright render, not a WAF block. | R81: TRUE | S81: Sampled, not fully verified given time budget -- none of these 403'd, so worth a follow-up probe with a real category URL before writing off. Lidl and Eurospin prices are indirectly recoverable via CroCart in the meantime.
A82: eca | B82: czech_republic | C82: Kosik.cz | D82: https://www.kosik.cz/ | E82: TIER_2 | F82: medium | G82: Wave 5 | H82: spider | I82: Playwright DISCOVERY pass first - find the internal JSON endpoint, then scrape it over plain HTTP | J82: Z_bespoke | K82: Vue SPA | M82: supermarket | N82: CZK | O82: 0 | Q82: GET -> 200 but only 11.2KB, a Vue SPA shell with class='beforeVueInit' and no SSR content. | R82: TRUE | S82: Not a WAF block -- needs a Playwright network-trace to find the internal API, not attempted given time budget.
A83: eca | B83: czech_republic | C83: Albert CZ | D83: https://www.albert.cz/ | E83: TIER_2 | F83: medium | G83: Wave 5 | H83: spider | I83: Playwright DISCOVERY pass first - find the internal JSON endpoint, then scrape it over plain HTTP | J83: Z_bespoke | K83: Next.js | M83: supermarket | N83: CZK | O83: 0 | Q83: GET -> 200, 1.2MB, Next.js markers present, but only placeholder '0,00 Kč' found on homepage. Not blocked (no WAF page). | R83: TRUE | S83: Sampled, inconclusive -- needs a real category URL, not confirmed blocked.
A84: eca | B84: latvia | C84: Rimi Latvia e-veikals | D84: https://www.rimi.lv/e-veikals/en | E84: TIER_2 | F84: medium | G84: Wave 5 | H84: spider | I84: Playwright DISCOVERY pass first - find the internal JSON endpoint, then scrape it over plain HTTP | J84: Z_bespoke | K84: Next/React | L84: retailer_sku | M84: supermarket | N84: EUR | O84: 0 | Q84: GET -> 200, 119KB, Next/React markers present. Guessed category URL /products/f/pieno-produkti-kiausiniai 404'd with 0,00€ placeholders. Not blocked. | R84: TRUE | S84: Per shard, explicit Omnibus 30-day-lowest-price field + separate beverage deposit fee -- high value if the right category URL is found. Not confirmed blocked, just wrong slug guessed.
A85: eca | B85: latvia | C85: Barbora Latvia | D85: https://barbora.lv/ | E85: TIER_2 | F85: medium | G85: Wave 5 | H85: spider | I85: Playwright DISCOVERY pass first - find the internal JSON endpoint, then scrape it over plain HTTP | J85: Z_bespoke | K85: Next/React | L85: retailer_sku | M85: supermarket | N85: EUR | O85: 0 | Q85: GET -> 200, 55KB, Next/React markers present, no direct price on homepage. | R85: TRUE | S85: 8,000+ goods per shard. Coverage withdrawn from Daugavpils/Liepaja/several regions Nov 2025 -- Riga-area only now.
A86: eca | B86: poland | C86: Biedronka (zakupy.biedronka.pl) | D86: https://zakupy.biedronka.pl/ | E86: TIER_2 | F86: medium | G86: Wave 5 | H86: spider | I86: Playwright DISCOVERY pass first - find the internal JSON endpoint, then scrape it over plain HTTP | J86: Z_bespoke | K86: Custom | L86: retailer_sku | M86: supermarket | N86: PLN | O86: 0 | Q86: GET / -> 200, 324KB, only '0,00 zł' placeholder found (empty-cart state). Guessed category /c/nabial -> 410 Gone. Not WAF-blocked. | R86: TRUE | S86: Per shard, per-category item counts are published throughout the tree (Nabiał 140, Słodycze 134, Artykuły spożywcze 577) confirming a rich catalog exists once the right category URL is found. Poland's largest discounter; home delivery currently Warsaw-only per shard note.
A87: eca | B87: portugal | C87: Continente | D87: https://www.continente.pt/ | E87: TIER_2 | F87: medium | G87: Wave 5 | H87: spider | I87: Playwright DISCOVERY pass first - find the internal JSON endpoint, then scrape it over plain HTTP | J87: Z_bespoke | K87: Salesforce Commerce Cloud | L87: retailer_sku | M87: supermarket | N87: EUR | O87: 0 | Q87: GET /mercearia/ -> 200, 2.2MB. Confirmed Salesforce-Commerce-Cloud product-tile classes ('ct-product-tile-badge-value--superprice') present in HTML, but exact price text not isolated within the time budget. | R87: TRUE | S87: Not WAF-blocked, real catalog markup confirmed -- needs one more selector pass to pull the price span. Largest PT chain (Sonae), delivers to all mainland + Madeira + S. Miguel.
A88: eca | B88: portugal | C88: Auchan Portugal / Super Save | D88: https://www.auchan.pt/ ; https://supersave.pt/web/ | E88: TIER_2 | F88: medium | G88: Wave 5 | H88: spider | I88: Playwright DISCOVERY pass first - find the internal JSON endpoint, then scrape it over plain HTTP | J88: Z_bespoke | K88: mixed | L88: retailer_sku | M88: supermarket/aggregator | N88: EUR | O88: 0 | Q88: Auchan.pt GET / -> 200 (635KB); guessed category 404'd, no price found. Supersave.pt/web/ GET -> 200 (1.06MB), Nuxt/Next/Vue/React markers all present but no price pattern matched. | R88: TRUE | S88: Neither confirmed blocked nor confirmed working -- sampled only, would need a real category URL or Playwright render. Super Save is high-value if unlocked: 7-chain daily comparison per kg/L/unit.
A89: eca | B89: spain | C89: Comparaloo.es / losmejoresproductos.es / Alcampo.es / Lidl Spain | D89: https://comparaloo.es/ ; https://losmejoresproductos.es/comparativas/ ; https://www.alcampo.es/ ; https://www.lidl.es/ | E89: TIER_2 | F89: medium | G89: Wave 5 | H89: spider | I89: Playwright DISCOVERY pass first - find the internal JSON endpoint, then scrape it over plain HTTP | J89: Z_bespoke | K89: mixed | L89: retailer_sku | M89: aggregator/supermarket | N89: EUR | O89: 0 | Q89: All 4 GET -> 200 (382KB / 31KB / 688KB / 197KB), none WAF-blocked, but Alcampo showed only '0,00€' placeholders and the other 3 had no price pattern match on the fetched page. | R89: TRUE | S89: Sampled only given time budget -- worth a follow-up with real category/product URLs. Comparaloo has an explicit false-discount detector per shard notes, worth prioritizing if revisited.
A90: eca | B90: sweden | C90: Coop Sweden / ICA (handla.ica.se) | D90: https://www.coop.se/ ; https://handla.ica.se/ | E90: TIER_2 | F90: medium | G90: Wave 5 | H90: spider | I90: Playwright DISCOVERY pass first - find the internal JSON endpoint, then scrape it over plain HTTP | J90: Z_bespoke | K90: React/Next | L90: retailer_sku | M90: supermarket | N90: SEK | O90: 0 | Q90: Both GET -> 200 (126KB / 102KB), React/Next markers present, no direct 'kr'/SEK price pattern matched on the homepage. | R90: TRUE | S90: Not confirmed blocked, just no catalog reachable from a bare homepage fetch. ICA per shard requires store selection first ('Välj butik'), which likely explains the empty homepage.
A91: eca | B91: united_kingdom | C91: Morrisons | D91: https://groceries.morrisons.com/ | E91: TIER_2 | F91: medium | G91: Wave 5 | H91: spider | I91: Playwright DISCOVERY pass first - find the internal JSON endpoint, then scrape it over plain HTTP | J91: Z_bespoke | K91: Enterprise | M91: supermarket | N91: GBP | O91: 0 | Q91: GET / -> 200, 653KB. Guessed category /browse/food-cupboard -> 404 (471KB) but still rendered '£25.00'/'£4.30' widgets -- ambiguous, not clearly product prices vs. page furniture. | R91: TRUE | S91: Not confirmed blocked (only chain in the UK shard that didn't outright 403), but not confirmed working either -- needs the correct category URL.
A92: menaap | B92: egypt | C92: InstaShop Egypt | D92: https://instashop.com/en-eg/ | E92: TIER_2 | F92: high | G92: Wave 5 | H92: spider | I92: Playwright DISCOVERY pass first - find the internal JSON endpoint, then scrape it over plain HTTP | J92: Z_bespoke | K92: Custom (Cloudflare-fronted) | L92: seller_directory | M92: marketplace | N92: EGP | O92: 0 | P92: /eshop/v2/superstore | Q92: curl -> 403 Cloudflare 'Attention Required'. Playwright renders 200 (366KB) past the challenge and captures internal API https://instashop.com/eshop/v2/superstore (597KB JSON) via network trace -- but that same endpoint hit with bare curl (even with countryCode=EG) still 403s Cloudflare, so it needs a browser-cleared session, not just the URL. | R92: TRUE | S92: Marketplace directory of Egyptian partner supermarkets/minimarkets per CSV. Would need Playwright-session-to-curl cookie relay to be worth building; supermarket coverage already well served by Gourmet/HyperOne/Seoudi/Spinneys direct.
A93: menaap | B93: egypt | C93: talabat mart / tKiosk | D93: https://www.talabat.com/egypt/groceries | E93: TIER_2 | F93: medium | G93: Wave 5 | H93: spider | I93: Playwright DISCOVERY pass first - find the internal JSON endpoint, then scrape it over plain HTTP | J93: Z_bespoke | K93: Custom (Next.js) | L93: retailer_sku | M93: dark_store | N93: EGP | O93: 0 | P93: /egypt/restaurant/{branchId}/{slug} (menu items API not yet located) | Q93: Confirmed present in the same vendor list as Talabat Egypt (isDarkstore:true, isTalabatGO:true), with a menuUrl e.g. /egypt/restaurant/725603/tmart-haram-talbiya-2. That menu page returns 200 SSR HTML but __NEXT_DATA__.props.pageProps has no product/price data (only cmsData) -- menu items load via a client-side API call not captured by a 7s Playwright network trace. | R93: TRUE | S93: Own-inventory dark store, platform-set pricing (distinct price-formation process from partner stores per CSV -- must be tagged separately if built). Store-level enumeration is free from the same Talabat vendor-list walk; menu/product-price extraction needs a longer Playwright network trace or interaction (add-to-cart click) to surface the item API.
A94: menaap | B94: tunisia | C94: Magik (Gabès) | D94: https://magik.tn/ | E94: TIER_2 | F94: medium | G94: Wave 5 | H94: spider | I94: Playwright DISCOVERY pass first - find the internal JSON endpoint, then scrape it over plain HTTP | J94: Z_bespoke | K94: Custom | L94: retailer_sku | M94: supermarket | N94: TND | O94: 0 | P94: n/a (client-rendered, no API endpoint found yet) | Q94: curl homepage -> 200, 1.36MB HTML, product links like /produit/avocado-rsab8h and /produit/ailes-de-poulet-wysc2v (chicken wings) visible in raw HTML -- but PDP prices are NOT in SSR HTML (grep for currency patterns only matched CSS false positives, e.g. '1.95rem'). Playwright render of the PDP surfaces real prices in rendered body text ('7.000 TND', '6.500 TND' etc, product='Avocat') but a passive network-response sniff over 5s found no clean JSON product endpoint -- pricing is likely injected via an inline script tag, not a fetchable API. | R94: FALSE | S94: Title says 'Vente en Ligne de Produits Frais' and product slugs confirm fresh produce + fresh/frozen meat -- exactly the coverage gap Otrity/Carrefour TN leave (regional Gabès chain, smaller footprint). Worth a dedicated follow-up Playwright/selector effort to find the price injection point.
A95: menaap | B95: morocco | C95: Carrefour Maroc (Label'Vie) | D95: https://carrefour.ma/ | E95: TIER_2 | F95: medium | G95: Wave 5 | H95: spider | I95: Playwright DISCOVERY pass first - find the internal JSON endpoint, then scrape it over plain HTTP | J95: Z_bespoke | K95: Next.js (custom, confirmed NOT the MAF/Algolia stack per CSV note -- Label'Vie-operated) | L95: retailer_sku | M95: supermarket | N95: MAD | O95: 0 | P95: unknown -- needs Playwright network trace | Q95: www.carrefour.ma does not resolve (no A/CNAME for www); apex carrefour.ma -> 200, 55KB, but is a Next.js app-router SPA shell with zero product/price mentions in SSR HTML (grep for product|prix|MAD = 0 hits). Guessed API paths (/api/catalog_system/pub/products/search, /api/products) all 404 to the identical 55KB shell -- Next.js client-side catch-all, not real 404s. Did not run Playwright network capture (budget); the real API is not discoverable from static HTML alone. | R95: TRUE | S95: Genuinely promising (major national chain, not hard-walled by a WAF -- just client-hydrated). Recommended next step: Playwright network trace on a category page to find the JSON endpoint.
A96: menaap | B96: morocco | C96: Marjane Market via Glovo | D96: https://glovoapp.com/fr/ma/casablanca/stores/marjane | E96: TIER_2 | F96: medium | G96: Wave 5 | H96: spider | I96: Playwright DISCOVERY pass first - find the internal JSON endpoint, then scrape it over plain HTTP | J96: Z_bespoke | K96: Custom (Glovo React SPA) | L96: retailer_sku | M96: delivery_platform | N96: MAD | O96: 0 | P96: unknown -- needs Playwright network trace | Q96: GET -> 200, 913KB (heavy JS bundle), only 2 product/prix/MAD mentions in raw HTML (SPA, client-hydrated). No embedded API base URL string found via grep for __NEXT_DATA__/apiUrl/glovoapp-api patterns. Did not run Playwright network capture within budget. | R96: TRUE | S96: Not hard-walled (200, no WAF signature) -- just needs a real browser network trace, which the brief flags as the single highest-yield move. Recommended follow-up.
A97: sar | B97: india | C97: JioMart | D97: https://www.jiomart.com/ | E97: TIER_2 | F97: high | G97: Wave 5 | H97: spider | I97: Playwright DISCOVERY pass first - find the internal JSON endpoint, then scrape it over plain HTTP | J97: Z_bespoke | K97: Fynd/GoFynd (Reliance white-label) | L97: retailer_sku | M97: supermarket | N97: INR | O97: 0 | P97: api.jiomartjcp.com/service/application/catalog/v1.0/products (session/pincode-gated) | Q97: curl homepage -> HTTP 200, 7MB HTML (Fynd/GoFynd 'jio-pd' white-label platform, application_id=685945f46c8c7aee3f3af605, backing API host api.jiomartjcp.com). Direct hits to /api/service/application/catalog/v1.0/products and api.jiomartjcp.com/service/application/catalog/v1.0/products both 302-redirect to an /ext/vertex/... auth-gated route or return 401 'Invalid authorization token'. Playwright network-sniff of /c/groceries surfaced only theme-preview and content/tags JSON (46-310KB), never a populated product_lists payload -- reduxData.catalog.product_lists stayed empty, consistent with the storefront requiring a pincode/location selection before the catalog API returns rows. | R97: FALSE | S97: Reliance's grocery arm, huge national footprint -- highest-value unresolved lead in India. Needs a Playwright session that sets a pincode first, then a network trace of the resulting catalog calls to find the unauthenticated (or session-cookie-only) product endpoint. Not cracked within this probe's budget.
A98: sar | B98: india | C98: Dept. of Consumer Affairs daily retail price monitoring (fcainfoweb.nic.in) | D98: https://fcainfoweb.nic.in/reports/report_menu_web.aspx | E98: TIER_2 | F98: medium | G98: Wave 5 | H98: fetcher | I98: Playwright DISCOVERY pass first - find the internal JSON endpoint, then scrape it over plain HTTP | J98: Z_bespoke | K98: ASP.NET WebForms (NIC) | L98: official_avg | M98: official_avg | N98: INR | O98: 0 | P98: report_menu_web.aspx (ASPX postback) | Q98: curl -> HTTP 200, 13.1KB HTML. Classic ASP.NET WebForms page (__VIEWSTATE present) -- the price table is rendered via server-side postback after selecting report type/date/commodity, not a plain GET. No JSON API found; would need __VIEWSTATE/__EVENTVALIDATION replay or Playwright form automation. | R98: FALSE | S98: Publicly known to cover ~22 essential commodities daily (rice, wheat/atta, 5 pulses, 5 edible oils, sugar, gur, milk, tea, salt, potato, onion, tomato) across 100+ price-reporting centres -- would add fresh-produce + pulses + oils depth if cracked, but I could not confirm the actual data payload within budget. Do not count leaves for this until the postback flow is verified.
A99: sar | B99: bangladesh | C99: DAM / Ministry of Agriculture market-price directory | D99: https://market.dam.gov.bd/market_daily_price_report and https://moa-services.com/market-directory/market-daily-price-report | E99: TIER_2 | F99: medium | G99: Wave 5 | H99: fetcher | I99: Playwright DISCOVERY pass first - find the internal JSON endpoint, then scrape it over plain HTTP | J99: Z_bespoke | K99: Vue SPA | L99: official_avg | M99: official_avg | N99: BDT | O99: 0 | Q99: Both curl -> HTTP 200 but 0 <td> elements in raw HTML (Vue SPA shells). Playwright passive network-sniff (8s dwell, no interaction) on both URLs captured zero JSON responses -- the site likely requires a date/market dropdown selection before it fires an XHR. Not resolved within budget. | R99: FALSE | S99: dam.gov.bd's homepage links to several distinct report types (comparative market price, daily price report, market directory report, price graphical report, product-wise market price report) via moa-services.com -- if any one of these has an open XHR behind a form submission, this would be the deep fresh-produce/fish/tuber feed the brief flagged as valuable. Needs an interactive Playwright probe (select date + market, then capture the resulting XHR), not attempted here.
A100: sar | B100: bangladesh | C100: Meena Bazar | D100: https://meenabazaronline.com/ and https://www.meenabazar.live/ | E100: TIER_2 | F100: medium | G100: Wave 5 | H100: spider | I100: Playwright DISCOVERY pass first - find the internal JSON endpoint, then scrape it over plain HTTP | J100: Z_bespoke | K100: Angular (meenabazaronline.com) / Next.js (meenabazar.live) | L100: retailer_sku | M100: supermarket | N100: BDT | O100: 0 | Q100: Original guessed domains (meenabazar.com.bd, meenaclick.com.bd) failed to resolve/timed out. WebSearch found the real domains: meenabazaronline.com (Angular SPA shell, HTTP 200/4.4KB) and meenabazar.live (Next.js SPA shell, HTTP 200/10.2KB, no __NEXT_DATA__ or api.meenabazar* string found in the shell HTML). Playwright network-sniff of meenabazar.live returned 0 JSON responses in an 8s dwell -- likely needs a delivery-area/store selection before any catalog call fires. | R100: FALSE | S100: One of Bangladesh's largest chains (8,000-10,000 SKUs per public reporting), Dhaka/Chittagong/Khulna. Worth a follow-up Playwright pass with location/store selection before writing off.
A101: sar | B101: pakistan | C101: Imtiaz | D101: https://shop.imtiaz.com.pk/ (imtiaz.com.pk is the corporate/blog site, not the store) | E101: TIER_2 | F101: high | G101: Wave 5 | H101: spider | I101: Playwright DISCOVERY pass first - find the internal JSON endpoint, then scrape it over plain HTTP | J101: Z_bespoke | K101: Custom SPA (quick-commerce white-label) | L101: retailer_sku | M101: supermarket | N101: PKR | O101: 0 | P101: /api/geofence?restId=55126 (session-gated) | Q101: imtiaz.com.pk -> corporate WordPress/blog, no shop links on homepage, /shop/ resolves to a 2019 blog post. Real storefront located via WebSearch at shop.imtiaz.com.pk -> HTTP 200 but empty SPA shell (30.3KB, no product links, no prices, S3 assets under a 'blinkximtiaz' bucket suggesting a Blinkit-style quick-commerce white-label). Playwright network-sniff surfaced GET /api/geofence?restId=55126 -> HTTP 200, 886KB JSON inside a live session; bare curl replay of the same URL -> HTTP 400. | R101: FALSE | S101: Pakistan's No.1 retail chain per their own marketing; second-most-valuable unresolved Pakistan lead after Metro. The geofence response is large (886KB) which suggests it may carry store/catalog metadata -- worth a full Playwright session bootstrap (set delivery location, then trace the resulting catalog calls) in a follow-up pass.
A102: ssa | B102: ethiopia | C102: AradaMart | D102: https://www.aradamart.net/ | E102: TIER_2 | F102: medium | G102: Wave 5 | H102: spider | I102: Playwright DISCOVERY pass first - find the internal JSON endpoint, then scrape it over plain HTTP | J102: Z_bespoke | K102: Wix | L102: retailer_sku | M102: supermarket | N102: ETB | O102: 0 | P102: unresolved -- needs Wix eCommerce Storefront API discovery (not in platform_fingerprints.md) or Playwright network trace | Q102: GET / -> 200, 2.75MB, but it's a Wix site -- catalog is client-rendered via Wix's own store APIs, not present in raw HTML (only currency='ETB' config strings and SVG icon path data, which is what my first price-pattern grep false-matched on). Confirmed WIX in page markers. | R102: TRUE | S102: Prior research claims deep fresh-produce coverage with bilingual Amharic/English names -- plausible and worth chasing, but I could not verify it live this pass, so it is NOT counted in the country total below. Treat as upside.
A103: ssa | B103: gabon | C103: Chap Chap Gabon | D103: https://chapchapgabon.com/ | E103: TIER_2 | F103: medium | G103: Wave 5 | H103: spider | I103: Playwright DISCOVERY pass first - find the internal JSON endpoint, then scrape it over plain HTTP | J103: Z_bespoke | K103: React (SPA, platform undetermined) | L103: retailer_sku | M103: supermarket | N103: XAF | O103: 0 | P103: unresolved -- needs Playwright network trace | Q103: GET / -> 200, 345KB, but confirmed React in the bundle and no price class / FCFA pattern in raw HTML. An earlier 'sapo' fingerprint hit was a false positive (a base64-looking string containing the substring 'sapo', not the Sapo platform). | R103: TRUE | S103: Live site, real operation (12 cities per prior research) -- worth a Playwright pass, not counted this round.
A104: ssa | B104: malawi | C104: EasyMart Malawi | D104: https://easymartmalawi.com/ | E104: TIER_2 | F104: medium | G104: Wave 5 | H104: spider | I104: Playwright DISCOVERY pass first - find the internal JSON endpoint, then scrape it over plain HTTP | J104: Z_bespoke | K104: React (rebuilt, was Custom/server-rendered) | L104: retailer_sku | M104: supermarket | N104: MWK | O104: 0 | P104: unresolved -- needs Playwright/API sniff against the new build | Q104: GET / -> 200, only 562 bytes -- the site has been rebuilt as a Vite/React SPA shell (empty div id='root') since the prior audit, which had verified server-rendered placeholder-like prices with a x1000 units convention. That evidence is now stale. | R104: TRUE | S104: Platform migration invalidates the prior 'thousands-notation' finding -- treat as an unverified new probe, not a re-confirmation.
A105: ssa | B105: mauritania | C105: Maurikilchi | D105: https://maurikilchi.com/ | E105: TIER_2 | F105: medium | G105: Wave 5 | H105: spider | I105: Playwright DISCOVERY pass first - find the internal JSON endpoint, then scrape it over plain HTTP | J105: Z_bespoke | K105: Laravel + Inertia.js | L105: retailer_sku | M105: supermarket | N105: MRU | O105: 0 | P105: unresolved -- needs Playwright/API sniff (Inertia typically proxies a JSON endpoint per-page-visit) | Q105: GET / -> 200, only 1,024 bytes -- pure Laravel Inertia.js SPA shell (data-page="app" JSON marker, single div#app, no SSR content). | R105: TRUE | S105: Marketplace with a dedicated Supermarche category tree per prior research -- worth a Playwright pass.
A106: ssa | B106: mauritania | C106: Almersoul | D106: https://www.marsarim.com/fr | E106: TIER_2 | F106: medium | G106: Wave 5 | H106: spider | I106: Playwright DISCOVERY pass first - find the internal JSON endpoint, then scrape it over plain HTTP | J106: Z_bespoke | K106: Angular | L106: retailer_sku | M106: supermarket | N106: MRU | O106: 0 | P106: unresolved -- needs Playwright | Q106: GET /fr -> 200, 26KB, but is an Angular SPA (<base href="/">, no SSR content) -- no MRU/product text in raw HTML. | R106: TRUE | S106: Market vertical claimed with Sedad/Bankily/Masrvi mobile-money payments; unconfirmed catalog depth.
A107: ssa | B107: tanzania | C107: Jambo Supermarket | D107: https://www.jambosupermarket.online/ | E107: TIER_2 | F107: medium | G107: Wave 5 | H107: spider | I107: Playwright DISCOVERY pass first - find the internal JSON endpoint, then scrape it over plain HTTP | J107: Z_bespoke | K107: React (SPA) | L107: retailer_sku | M107: supermarket | N107: TZS | O107: 0 | P107: unresolved -- needs Playwright/API sniff | Q107: GET / -> 200, only 477 bytes -- pure Vite/React SPA shell (empty div id='root'). | R107: TRUE | S107: 5 named Dar es Salaam branches with a branch selector per prior research (supports within-city comparison) -- worth a Playwright pass, not counted this round.
A108: ssa | B108: tanzania | C108: duka.direct (Selcom) | D108: https://duka.direct/ | E108: TIER_2 | F108: medium | G108: Wave 5 | H108: spider | I108: Playwright DISCOVERY pass first - find the internal JSON endpoint, then scrape it over plain HTTP | J108: Z_bespoke | K108: Custom | L108: retailer_sku | M108: supermarket | N108: TZS | O108: 0 | P108: unresolved | Q108: GET / -> 200, 155KB SEO/marketing landing page (food delivery + utility payments copy). No SPA shell markers found but also no price class or TSh/TZS pattern in the raw HTML -- catalog likely lives behind app/city-selection flow not reached from the bare domain root. | R108: TRUE | S108: Largest Tanzanian e-commerce platform (Selcom-built) per prior research, with a utility-payment vertical as a bonus for administered-price tracking -- worth a deeper path/Playwright pass later.
A109: ssa | B109: zimbabwe | C109: TM Pick n Pay Zimbabwe | D109: https://tmpnponline.co.zw/ | E109: TIER_2 | F109: medium | G109: Wave 5 | H109: spider | I109: Playwright DISCOVERY pass first - find the internal JSON endpoint, then scrape it over plain HTTP | J109: Z_bespoke | K109: Custom | L109: retailer_sku | M109: supermarket | N109: USD | O109: 0 | P109: unresolved | Q109: GET / -> 200, 54KB. class='products mt-5' confirms a real product-grid container exists, but no $/USD price text matched in the homepage HTML -- likely lazy-loaded or on a category path not probed this pass. | R109: TRUE | S109: Store/region selector + dual USD/ZWG via ZimSwitch per prior research -- major chain, worth a category-page follow-up.
A110: ssa | B110: zimbabwe | C110: TillPoint | D110: https://tillpoint.co.zw/ | E110: TIER_2 | F110: medium | G110: Wave 5 | H110: spider | I110: Playwright DISCOVERY pass first - find the internal JSON endpoint, then scrape it over plain HTTP | J110: Z_bespoke | K110: React (SPA) | L110: retailer_sku | M110: supermarket | N110: USD | O110: 0 | P110: unresolved -- needs Playwright | Q110: GET / -> 200, 52KB, React app markers (id='root'-style shell); no product/price/api JSON text found in raw HTML. | R110: TRUE | S110: Produce, meat boxes, pantry staples claimed per prior research.
A111: ssa | B111: kenya | C111: Quickmart | D111: https://www.quickmart.co.ke/ | E111: TIER_2 | F111: medium | G111: Wave 5 | H111: spider | I111: Playwright DISCOVERY pass first - find the internal JSON endpoint, then scrape it over plain HTTP | J111: Z_bespoke | K111: Custom | L111: retailer_sku | M111: supermarket | N111: KES | O111: 0 | Q111: curl -> HTTP 200 (46.8KB, no product data, no framework fingerprint). Playwright homepage load + 9s wait -> only 3 network responses, all non-product (Google Maps JS). Confirms CSV's own note: catalogue requires a store/location selection step before any product data loads; a single homepage render never reaches it. | R111: TRUE | S111: Widest verified geographic reach in Kenya (19 towns per CSV) -- worth the extra engineering to script the location-select flow, since spatial price dispersion is otherwise unreachable in this shard.
A112: ssa | B112: sudan | C112: Hyper Express | D112: https://hyper.sd/ | E112: TIER_2 | F112: medium | G112: Wave 5 | H112: spider | I112: Playwright DISCOVERY pass first - find the internal JSON endpoint, then scrape it over plain HTTP | J112: Z_bespoke | K112: Custom | L112: retailer_sku | M112: supermarket | N112: SDG | O112: 0 | Q112: curl -> HTTP 200, 286KB SSR HTML. No confirmed product-name + price pair found in the sampled HTML (numeric-looking patterns found were SVG path coordinates, a false positive). Needs a category-page-level probe, not just the homepage. | R112: TRUE | S112: Live multi-vertical platform (hypermarket + restaurants + pharmacies) per CSV; unconfirmed within budget, not a hard block.
A113: ssa | B113: sudan | C113: LILY Delivery | D113: https://www.lilydelivery.com/en | E113: TIER_2 | F113: medium | G113: Wave 5 | H113: spider | I113: Playwright DISCOVERY pass first - find the internal JSON endpoint, then scrape it over plain HTTP | J113: Z_bespoke | K113: Custom | L113: retailer_sku | M113: supermarket | N113: SDG | O113: 0 | Q113: curl -> HTTP 200, 247KB. No SDG price pattern found in homepage HTML. Likely needs the specific /order/supermarket/hypermarket vertical URL from the CSV's second row, not probed further within budget. | R113: TRUE | S113: Unconfirmed within budget, not a hard block.
A114: ssa | B114: sudan | C114: Zaad Delivery | D114: https://zaad.delivery/ | E114: TIER_2 | F114: medium | G114: Wave 5 | H114: spider | I114: Playwright DISCOVERY pass first - find the internal JSON endpoint, then scrape it over plain HTTP | J114: Z_bespoke | K114: Vue.js SPA | L114: retailer_sku | M114: supermarket | N114: SDG | O114: 0 | Q114: curl -> HTTP 200, 192KB, Vue.js fingerprint found. No SDG price pattern found in raw HTML (client-hydrated, as expected for Vue). | R114: TRUE | S114: Not Playwright-verified within budget.
A115: ssa | B115: guinea | C115: Kona Livr | D115: https://www.konalivr.com/ | E115: TIER_2 | F115: medium | G115: Wave 5 | H115: spider | I115: Playwright DISCOVERY pass first - find the internal JSON endpoint, then scrape it over plain HTTP | J115: Z_bespoke | K115: Next.js | L115: retailer_sku | M115: supermarket | N115: GNF | O115: 0 | Q115: curl -> HTTP 200, 112KB Next.js RSC-hydrated HTML. All GNF figures found are delivery-fee thresholds and delivery-time strings ('Frais de livraison offerts des 100 000 GNF', 'livraison 15 000 GNF'), not product prices -- this is a store/restaurant DIRECTORY (name, category, rating, delivery time), not a product catalog at this depth. | R115: TRUE | S115: Per discovery doctrine, treat as a MARKETPLACE lead, not a source: the value here is its partner list (supermarkets/pharmacies/boulangeries in Conakry), each a candidate storefront of its own, reachable only by drilling into per-vendor menu pages.
A116: ssa | B116: guinea | C116: maMakiti | D116: https://mamakiti.com/ | E116: TIER_2 | F116: medium | G116: Wave 5 | H116: spider | I116: Playwright DISCOVERY pass first - find the internal JSON endpoint, then scrape it over plain HTTP | J116: Z_bespoke | K116: React/Next.js SPA (likely) | L116: retailer_sku | M116: supermarket | N116: GNF | O116: 0 | Q116: curl -> HTTP 200, 52KB. Only GNF occurrences are JSON-LD boilerplate (priceRange:'GNF', price:'0') -- an SPA shell with no server-rendered product data. | R116: TRUE | S116: Local market produce/vendor commission model per CSV; needs full network-sniff to find its API.
A117: ssa | B117: guinea | C117: BraPrime | D117: https://www.braprime.com/ | E117: TIER_2 | F117: medium | G117: Wave 5 | H117: spider | I117: Playwright DISCOVERY pass first - find the internal JSON endpoint, then scrape it over plain HTTP | J117: Z_bespoke | K117: React SPA | L117: retailer_sku | M117: supermarket | N117: GNF | O117: 0 | Q117: curl -> HTTP 200, only 2.4KB body -- a Vite/React SPA shell (class='dark', empty root div). | R117: TRUE | S117: Multi-service delivery platform per CSV; not probed further with Playwright within budget.
A118: ssa | B118: congo_dem_rep | C118: Kin Marche | D118: https://kinmarche.com/ | E118: TIER_2 | F118: medium | G118: Wave 5 | H118: spider | I118: Playwright DISCOVERY pass first - find the internal JSON endpoint, then scrape it over plain HTTP | J118: Z_bespoke | K118: Custom | L118: retailer_sku | M118: supermarket | N118: CDF | O118: 0 | Q118: curl -> HTTP 200, 30KB (homepage) and 74KB (/product-categories). No CDF/FC price pattern and no product/category href found in either page -- static shell only exposes nav links (about, contact, stores, product-categories) with no actual category listing content server-rendered. | R118: TRUE | S118: CSV confirms this is a real national chain (Kinshasa/Katanga/Kivu/Kongo Central) with 'Produits frais, Epicerie, Boissons' categories -- the data must exist behind JS/AJAX not reached by a plain curl of the listed pages. Needs Playwright.
A119: ssa | B119: cote_divoire | C119: MegaMarche CI | D119: https://www.megamarche.ci/ | E119: TIER_2 | F119: medium | G119: Wave 5 | H119: spider | I119: Playwright DISCOVERY pass first - find the internal JSON endpoint, then scrape it over plain HTTP | J119: Z_bespoke | K119: Custom | L119: retailer_sku | M119: supermarket | N119: XOF | O119: 0 | Q119: curl -> HTTP 200, 252KB. No FCFA/XOF price pattern, no product/category href found. Playwright render (5s wait + scroll) -> zero JSON/API responses captured. Site appears to require login or store selection before any catalogue content appears. | R119: TRUE | S119: Not a hard block (200 throughout) but unconfirmed within budget.
A120: ssa | B120: cote_divoire | C120: Playce / Carrefour CI | D120: https://playce.ci/ | E120: TIER_2 | F120: medium | G120: Wave 5 | H120: spider | I120: Playwright DISCOVERY pass first - find the internal JSON endpoint, then scrape it over plain HTTP | J120: Z_bespoke | K120: WordPress (store-locator only) | L120: retailer_sku | M120: supermarket | N120: XOF | O120: 0 | Q120: curl -> HTTP 200, 136KB. Playwright network trace found only a WP admin-ajax store-locator call (action=store_search) and Google Maps assets -- no product catalog API observed. | R120: TRUE | S120: CFAO-operated Carrefour franchise per CSV; the page found is a store-locator, not a shop front. Product catalog likely lives elsewhere or behind further navigation not reached within budget.
A121: ssa | B121: rwanda | C121: haha.rw | D121: https://haha.rw/ | E121: TIER_2 | F121: medium | G121: Wave 5 | H121: spider | I121: Playwright DISCOVERY pass first - find the internal JSON endpoint, then scrape it over plain HTTP | J121: Z_bespoke | K121: React SPA (Vite) | L121: retailer_sku | M121: supermarket | N121: RWF | O121: 0 | Q121: curl -> HTTP 200 but only 779 bytes -- a Vite/React SPA shell ('<div id="root"></div>', hashed asset bundle). CSV describes this as 'server-rendered' which is incorrect; it is client-hydrated. | R121: TRUE | S121: CSV's claim of 'RWF prices per kg/piece/bunch, 6 named Kigali markets' must have come from a rendered/API view, not the raw HTML -- needs an API-sniff Playwright pass to find the JSON backend.
A122: ssa | B122: rwanda | C122: Fasita | D122: https://fasita.rw/ | E122: TIER_2 | F122: medium | G122: Wave 5 | H122: spider | I122: Playwright DISCOVERY pass first - find the internal JSON endpoint, then scrape it over plain HTTP | J122: Z_bespoke | K122: Next.js | L122: retailer_sku | M122: supermarket | N122: RWF | O122: 0 | Q122: curl -> HTTP 200, 40.5KB, Next.js app (App Router, RSC preload tags). No RWF price pattern found on the homepage itself. | R122: TRUE | S122: Homepage is a landing/marketing shell; category or product pages not probed within budget.
... A126: ssa | B126: cabo_verde | C126: GO.cv (Correios CV) | D126: https://www.go.cv/ | E126: TIER_2 | F126: medium | G126: Wave 5 | H126: fetcher | I126: Playwright DISCOVERY pass first - find the internal JSON endpoint, then scrape it over plain HTTP | J126: Z_bespoke | K126: Custom | L126: aggregate_proxy | M126: supermarket | N126: CVE | O126: 0 | Q126: curl -> DNS resolves (87.103.13.203) but TLS handshake times out after 20s (connection hangs, not a clean refusal/403). Distinct from a WAF block -- looks like a slow or overloaded origin. | R126: TRUE | S126: National postal multi-vendor marketplace per CSV -- worth a retry with a longer timeout before writing off; the TLS handshake got partway through, suggesting a live-but-slow origin rather than a hard block.

Sheet All_Viable_340
A1: region | B1: slug | C1: source | D1: url | E1: tier | F1: effort | G1: build_wave | H1: scaffolding | I1: build_approach | J1: bucket | K1: platform | L1: analytical_role | M1: channel | N1: currency | O1: fnb_leaves_est | P1: endpoint | Q1: evidence | R1: in_csv | S1: notes | T1: gotcha
A2: ssa | B2: ethiopia | C2: WFP Food Prices (HDX) -- Ethiopia | D2: https://data.humdata.org/dataset/wfp-food-prices-for-ethiopia | E2: TIER_1B | F2: low | G2: Wave 1 | H2: fetcher | I2: Extend _PANELS in src/prices/fetchers/_shared/eap/wfp_food_prices.py - one line per country, no new code. DATE-CHECK each panel first. | J2: A_wfp_ckan | K2: WFP/HDX CKAN | L2: official_avg | M2: official_avg | N2: ETB | O2: 45 | P2: https://data.humdata.org/api/3/action/package_show?id=wfp-food-prices-for-ethiopia | Q2: CKAN resolved -> wfp_food_prices_eth.csv, 62,131 rows. 96 distinct commodities -- richest WFP panel in this shard: full cereal set (wheat/barley/maize/sorghum/teff, each in 2-5 sub-varieties), legumes (beans x6 varieties, chickpeas, lentils, peas x3), dairy (milk, camel milk, butter x2), live animals (bull/camel/cattle/donkey/goat/ox/sheep), produce (avocado/banana/beetroot/cabbage/carrots/garlic/guava/kale/lettuce/mango/onions/oranges/papaya/potatoes/swiss chard/sweet potatoes/tomatoes), coffee, honey, oils, pasta, salt, sesame, sugar. | R2: FALSE | S2: By far the biggest single lever for Ethiopia's F&B coverage -- reaches teff (all 4 sub-varieties), live animals, and multiple dairy/legume forms that no retail source in this shard touches.
A3: lac | B3: guatemala | C3: WFP Food Prices - Guatemala | D3: https://data.humdata.org/dataset/wfp-food-prices-for-guatemala | E3: TIER_1B | F3: low | G3: Wave 1 | H3: fetcher | I3: Extend _PANELS in src/prices/fetchers/_shared/eap/wfp_food_prices.py - one line per country, no new code. DATE-CHECK each panel first. | J3: A_wfp_ckan | K3: CKAN/WFP HDX | L3: official_avg | M3: wholesale/retail (mixed) | N3: GTQ | O3: 45 | P3: CKAN dataset wfp-food-prices-for-guatemala, resource wfp_food_prices_gtm.csv | Q3: GET CSV https://data.humdata.org/dataset/.../wfp_food_prices_gtm.csv -> HTTP 200, 2.29MB, 16,178 rows. Max date confirmed 2026-06-15 (live/recent). Sample: 'Maize (white)' 100 Pounds, Wholesale, La Terminal market, GTQ 67.75 (2026-06-15). Also carrots, onions, tomatoes, beans, coffee, bananas. | R3: FALSE | S3: Wholesale + some retail channel, La Terminal market Guatemala City + others; complements but barely overlaps supermarket SKUs (fresh produce/grains/pulses focus).
A4: menaap | B4: syria | C4: WFP Food Prices - Syria (HDX) | D4: https://data.humdata.org/dataset/aa40b3a8-2bc4-4826-9d82-82189bc5f392 | E4: TIER_1B | F4: low | G4: Wave 1 | H4: fetcher | I4: Extend _PANELS in src/prices/fetchers/_shared/eap/wfp_food_prices.py - one line per country, no new code. DATE-CHECK each panel first. | J4: A_wfp_ckan | K4: WFP/HDX CKAN | L4: official_avg | M4: official_avg | N4: SYP | O4: 44 | P4: CKAN package_show -> S3 CSV | Q4: CKAN package_show -> 200, resolves wfp_food_prices_syr.csv, 275,972 rows - by far the largest panel in the set. 77 distinct commodities across all 8 categories: fruit (apples, bananas), veg (cabbage, carrots, cucumbers x2, eggplant, garlic, parsley, pumpkin, spinach, tomatoes fresh+paste), dairy (cheese x2, labaneh, fresh milk, yogurt), meat (beef minced, chicken legs/plucked, sheep), cereals (bulgur, maize local, wheat, 3 bread variants, 2 pasta variants, rice), pulses (3 bean types, lentils, 2 pea types, chickpeas), oils/fats (oil, ghee), plus sugar/salt/tea/yeast/peanut. | R4: FALSE | S4: Syria's WFP panel is the deepest of the entire shard because of dedicated crisis-monitoring granularity (parallel-market fuel/bread variants tracked separately). One-line _PANELS addition: 'syr': ('Syria', 'wfp-food-prices-for-syrian-arab-republic').
A5: ssa | B5: rwanda | C5: WFP Rwanda (HDX) | D5: https://data.humdata.org/dataset/a4a84c1c-81d1-491b-9fbe-1955ae736508 | E5: TIER_1B | F5: low | G5: Wave 1 | H5: fetcher | I5: Extend _PANELS in src/prices/fetchers/_shared/eap/wfp_food_prices.py - one line per country, no new code. DATE-CHECK each panel first. | J5: A_wfp_ckan | K5: Custom (CKAN/HDX) | L5: official_avg | M5: official_avg | N5: RWF | O5: 42 | P5: https://data.humdata.org/api/3/action/package_show?id=wfp-food-prices-for-rwanda | Q5: CKAN-resolved CSV wfp_food_prices_rwa.csv (200, 19.9MB, richest+largest panel in this shard). 151,961 rows, 65 distinct commodities, max date 2026-06-15. Extremely granular: apples, avocados, guava, mangoes, passion fruit, papaya, oranges, cauliflower, greenhouse cucumbers, zucchini, soybeans, sorghum flour, 4+ rice-origin variants, 5 livestock species (live), 4 meat species. | R5: FALSE | S5: Best WFP panel discovered across the whole shard by both commodity count and row count -- essentially a near-retail-resolution market-price census. With every retail candidate in this shard unconfirmed, this feed alone is Rwanda's current F&B backbone.
A6: lac | B6: el_salvador | C6: WFP Food Prices - El Salvador | D6: https://data.humdata.org/dataset/wfp-food-prices-for-el-salvador | E6: TIER_1B | F6: low | G6: Wave 1 | H6: fetcher | I6: Extend _PANELS in src/prices/fetchers/_shared/eap/wfp_food_prices.py - one line per country, no new code. DATE-CHECK each panel first. | J6: A_wfp_ckan | K6: CKAN/WFP HDX | L6: official_avg | M6: wholesale/retail (mixed) | N6: USD | O6: 40 | P6: CKAN dataset wfp-food-prices-for-el-salvador, resource wfp_food_prices_slv.csv | Q6: GET CSV -> HTTP 200, 7,561 rows, max date confirmed 2026-06-15 (live). Sample: 'Maize (white)' 46 KG Wholesale San Salvador USD 26.49 (2026-06-15); also 'Maize (white)' Libra Retail USD 0.34. | R6: FALSE | S6: Both wholesale and retail channel rows present; national-average style market coverage.
A7: lac | B7: nicaragua | C7: WFP Food Prices - Nicaragua | D7: https://data.humdata.org/dataset/wfp-food-prices-for-nicaragua | E7: TIER_1B | F7: low | G7: Wave 1 | H7: fetcher | I7: Extend _PANELS in src/prices/fetchers/_shared/eap/wfp_food_prices.py - one line per country, no new code. DATE-CHECK each panel first. | J7: A_wfp_ckan | K7: CKAN/WFP HDX | L7: official_avg | M7: retail | N7: USD | O7: 35 | P7: CKAN dataset wfp-food-prices-for-nicaragua, resource wfp_food_prices_nic.csv | Q7: GET CSV -> HTTP 200, max date confirmed 2026-05-15 (live). Sample: 'Plantains' Pound, Retail, National Average, USD 0.44 (2026-05-15); also squashes, tomatoes. | R7: FALSE | S7: Retail national-average channel, fresh produce focus.
A8: menaap | B8: west_bank_and_gaza | C8: WFP Food Prices - State of Palestine (HDX) | D8: https://data.humdata.org/dataset/7d06b059-5831-4101-aa68-6d9123ad65b7 | E8: TIER_1B | F8: low | G8: Wave 1 | H8: fetcher | I8: Extend _PANELS in src/prices/fetchers/_shared/eap/wfp_food_prices.py - one line per country, no new code. DATE-CHECK each panel first. | J8: A_wfp_ckan | K8: WFP/HDX CKAN | L8: official_avg | M8: official_avg | N8: ILS | O8: 33 | P8: CKAN package_show -> S3 CSV | Q8: CKAN package_show?id=wfp-food-prices-for-state-of-palestine -> 200, resolves wfp_food_prices_pse.csv, 26,815 rows. 41 commodities: fruit (apples, bananas, oranges), veg (cauliflower, cucumbers, eggplant, onions, tomatoes greenhouse), dairy (goat cheese, labaneh, milk pasteurized + powder, yogurt), meat (beef, chicken, goat), 3 rice varieties, 2 oil types (maize + olive), semolina, bottled water. | R8: FALSE | S8: Repo slug is 'west_bank_and_gaza' (iso3 PSE per countries.yaml) - HDX dataset slug is 'wfp-food-prices-for-state-of-palestine'. One-line _PANELS addition: 'pse': ('State of Palestine', 'wfp-food-prices-for-state-of-palestine').
A9: ssa | B9: malawi | C9: WFP Food Prices (HDX) -- Malawi | D9: https://data.humdata.org/dataset/wfp-food-prices-for-malawi | E9: TIER_1B | F9: low | G9: Wave 1 | H9: fetcher | I9: Extend _PANELS in src/prices/fetchers/_shared/eap/wfp_food_prices.py - one line per country, no new code. DATE-CHECK each panel first. | J9: A_wfp_ckan | K9: WFP/HDX CKAN | L9: official_avg | M9: official_avg | N9: MWK | O9: 30 | P9: https://data.humdata.org/api/3/action/package_show?id=wfp-food-prices-for-malawi | Q9: CKAN resolved -> wfp_food_prices_mwi.csv, 82,819 rows. 63 distinct commodities -- notably rich in Malawi-specific leafy greens (Amaranthus, Blackjack leaves, Cowpea leaves, Mustard leaves, Pumpkin leaves, Rape leaves) and dried small fish (bonya, kapenta, matemba, usipa, utaka), plus cereals/legumes/tubers/oil/sugar. | R9: FALSE | S9: Second-richest WFP panel in the shard. The leafy-greens and dried-fish depth here is not replicated by any retailer in this pass -- structurally complementary, not overlapping.
A10: menaap | B10: jordan | C10: WFP Food Prices - Jordan (HDX) | D10: https://data.humdata.org/dataset/fba510fd-eccf-4b34-b5f6-cc531900270b | E10: TIER_1B | F10: low | G10: Wave 1 | H10: fetcher | I10: Extend _PANELS in src/prices/fetchers/_shared/eap/wfp_food_prices.py - one line per country, no new code. DATE-CHECK each panel first. | J10: A_wfp_ckan | K10: WFP/HDX CKAN | L10: official_avg | M10: official_avg | N10: JOD | O10: 29 | P10: CKAN package_show -> S3 CSV | Q10: CKAN package_show -> 200, resolves wfp_food_prices_jor.csv, 47,943 rows. 36 commodities across all 8 categories including both olive oil AND vegetable oil as separate lines, apples/bananas/oranges (fruit), cucumbers/garlic/onions/spinach/tomatoes (veg), beef/chicken/lamb (meat), two cheese types + two milk types (dairy) - the richest, most balanced panel of the whole shard. | R10: FALSE | S10: One-line _PANELS addition: 'jor': ('Jordan', 'wfp-food-prices-for-jordan').
A11: ssa | B11: kenya | C11: WFP Kenya (HDX) | D11: https://data.humdata.org/dataset/e0d3fba6-f9a2-45d7-b949-140c455197ff | E11: TIER_1B | F11: low | G11: Wave 1 | H11: fetcher | I11: Extend _PANELS in src/prices/fetchers/_shared/eap/wfp_food_prices.py - one line per country, no new code. DATE-CHECK each panel first. | J11: A_wfp_ckan | K11: Custom (CKAN/HDX, same pattern as existing src/prices/fetchers/_shared/eap/wfp_food_prices.py) | L11: official_avg | M11: official_avg | N11: KES | O11: 28 | P11: https://data.humdata.org/api/3/action/package_show?id=wfp-food-prices-for-kenya | Q11: CKAN package_show resolved CSV at wfp_food_prices_ken.csv (200, 3.6MB). 27,837 rows, 51 distinct commodities, max date 2026-07-15 (current). Retail+wholesale mixed pricetype. Sample: Maize (white) KES 1480/90kg wholesale Mombasa. | R11: FALSE | S11: Direct extension of the existing shared EAP WFP fetcher module -- just add ken to the _PANELS dict. 51 commodities incl. camel meat/milk (not covered by any retailer) is the standout addition.
A12: ssa | B12: central_african_republic | C12: WFP Central African Republic (HDX) | D12: https://data.humdata.org/dataset/e9f27b34-f511-498c-a7f8-fe8d2321f7ba | E12: TIER_1B | F12: low | G12: Wave 1 | H12: fetcher | I12: Extend _PANELS in src/prices/fetchers/_shared/eap/wfp_food_prices.py - one line per country, no new code. DATE-CHECK each panel first. | J12: A_wfp_ckan | K12: Custom (CKAN/HDX) | L12: official_avg | M12: official_avg | N12: XAF | O12: 28 | P12: https://data.humdata.org/api/3/action/package_show?id=wfp-food-prices-for-central-african-republic | Q12: CKAN-resolved CSV wfp_food_prices_caf.csv (200, 3.6MB). 30,356 rows, 39 distinct commodities (tied with Rwanda for richest panel in this shard), max date 2026-06-15. Commodities incl. Meat (antelope smoked, gazelle smoked -- bushmeat), Fish (catfish/frozen/sardine canned/smoked), Sesame, Groundnuts (shelled/unshelled), Charcoal. | R12: FALSE | S12: With no live retail candidate, this is effectively the ONLY viable F&B price source for CAR in this shard. The bushmeat commodities (antelope, gazelle) are a rare hit on the 'Other meat' leaf (01.1.2.2.9) that almost no supermarket source in the wider repo reaches.
A13: menaap | B13: iraq | C13: WFP Food Prices - Iraq (HDX) | D13: https://data.humdata.org/dataset/7d8955eb-37d2-4087-80e9-cae1aaa242f5 | E13: TIER_1B | F13: low | G13: Wave 1 | H13: fetcher | I13: Extend _PANELS in src/prices/fetchers/_shared/eap/wfp_food_prices.py - one line per country, no new code. DATE-CHECK each panel first. | J13: A_wfp_ckan | K13: WFP/HDX CKAN | L13: official_avg | M13: official_avg | N13: IQD | O13: 26 | P13: CKAN package_show -> S3 CSV | Q13: CKAN package_show -> 200, resolves wfp_food_prices_irq.csv, 56,712 rows. 49 commodities - largest non-Syria commodity list, includes dates, eggplant, cheese (local), yogurt, three rice varieties (regular/Indian/basmati), three wheat-flour sourcing variants (Turkey/local/generic). | R13: FALSE | S13: One-line _PANELS addition: 'irq': ('Iraq', 'wfp-food-prices-for-iraq').
... A118: menaap | B118: libya | C118: Al Mustawda (big.ly) | D118: https://big.ly/food | E118: TIER_1A | F118: low | G118: Wave 2 | H118: spider | I118: Generic OpenCart spider | J118: G_opencart | K118: OpenCart | L118: retailer_sku | M118: supermarket | N118: LYD | O118: 20 | P118: /food (OpenCart category route, SSR) | Q118: curl GET https://big.ly/food -> 200, 208KB HTML. OpenCart platform (theme 'renoxa'). Dedicated /food category (h2 title 'طعام'). Product cards parse cleanly: 'باذنجان' (Eggplant) 6.00 د.ل, 'بازلاء خضراء' (Green peas) 6.00 د.ل, 'بصل أحمر جاف' (Dry red onion) 3.50 د.ل. | R118: TRUE | S118: Sample was the fresh-produce subcategory only; '20,000+ completed orders' per CSV note suggests a larger catalog behind /food's 'subcategories' menu than what I paginated. Re-probe to enumerate all food subcategories before scaffolding.
A119: sar | B119: sri_lanka | C119: Carkeells | D119: https://carkeells.lk/en-gb/catalog/grocery | E119: TIER_1A | F119: low | G119: Wave 2 | H119: spider | I119: Generic OpenCart spider | J119: G_opencart | K119: OpenCart | L119: retailer_sku | M119: pharmacy | N119: LKR | O119: 15 | Q119: curl 200/21-64KB, plain OpenCart SSR HTML, `opencart` string present in body. GET /en-gb/catalog/grocery/food-products -> 200/64KB with real prices: Rs.525.00, Rs.375.00, Rs.595.00, Rs.160.00 etc (excluding a Rs.0.00 placeholder row). Confirmed as shard's own AI_NOTES suggested: a small grocery/beverages tail (2 subcategories) bolted onto a cosmetics/health/haircare-dominant OpenCart store. | R119: TRUE | S119: Real but tiny (~55 SKUs total across grocery+beverages per shard notes). Low priority -- everything it carries is already covered more deeply by Glomark/OnlineKade/SPAR2U.
A120: lac | B120: jamaica | C120: CoolMarket Groceries | D120: https://www.coolmarket.com/groceries.html | E120: TIER_1A | F120: low | G120: Wave 2 | H120: spider | I120: Generic Magento/GraphQL spider (incl. the mcprod.<domain> pattern) | J120: H_magento | K120: Magento | L120: retailer_sku | M120: supermarket | N120: JMD | O120: 170 | P120: SSR HTML Magento listing/PDP (data-price-amount attrs) | Q120: curl 200/4.04MB (Magento). data-price-amount attributes throughout: 'NESTLÉ Kit Kat 4 Bar Milk Chocolate 45g' JMD 204.00. 591 product-item-link matches on this single paginated listing page, consistent with CSV's '1,386 grocery items' claim. | R120: TRUE | S120: CSV called this the best Jamaica source; confirmed — deep grocery catalog with clean Magento price markup.
A121: menaap | B121: egypt | C121: Spinneys Egypt | D121: https://spinneys-egypt.com/ | E121: TIER_1B | F121: low | G121: Wave 2 | H121: spider | I121: Generic Magento/GraphQL spider (incl. the mcprod.<domain> pattern) | J121: H_magento | K121: Nuxt + Magento 2 (mcprod.<domain> backend pattern) | L121: retailer_sku | M121: supermarket | N121: EGP | O121: 165 | P121: https://mcprod.spinneys-egypt.com/graphql (Magento GraphQL, POST, no auth) | Q121: curl homepage -> 200, Nuxt fingerprint, config.apiURL 'https://spinneys-egypt.com/graphql' (direct proxy 400s on POST body, use mcprod subdomain instead). Direct curl POST to https://mcprod.spinneys-egypt.com/graphql (search:'rice') -> 200 clean JSON: 'El Shorouk Rice - 5 Kg' EGP 163.95, 'Dayma Rice - 1K' EGP 45.25. | R121: TRUE | S121: Upper-mid chain, third confirmed 'mcprod.<retailer-domain>/graphql' Magento site in Egypt (with Hyper One, Seoudi) -- strong signal of a shared storefront vendor to check for more Egyptian retailers on this stack. Categories incl. Fruits&Vegetables(916), Meat&Poultry(135), Seafood&Fish(137), Cheese/Dairy/Eggs(1844), Bakery&Bread(460), Frozen(998).
A122: menaap | B122: tunisia | C122: Carrefour Tunisia | D122: https://www.carrefour.tn/ | E122: TIER_1B | F122: low | G122: Wave 2 | H122: spider | I122: Generic Magento/GraphQL spider (incl. the mcprod.<domain> pattern) | J122: H_magento | K122: Magento 2 | L122: retailer_sku | M122: supermarket | N122: TND | O122: 165 | P122: /graphql (Magento GraphQL, POST, no auth) | Q122: curl homepage -> 200 but tiny 8.8KB SPA shell (data-media-backend=back.carrefour.tn). Playwright network trace found same-origin GraphQL traffic at /graphql. Direct curl POST to https://www.carrefour.tn/graphql (search:'riz') -> 200 clean JSON, NO Cloudflare/Akamai block: 'Riz Djerbien' TND 19.20, 'Riz Basmati' TND 8.49. categoryList query confirms full hypermarket taxonomy. | R122: FALSE | S122: Found via local operator search, not CSV. Distinct backend/operator from Carrefour Egypt's MAF/Akamai stack -- not WAF-hardened at all. Categories: Le marché(1082, likely fresh produce/meat/fish), Épicerie Salée(1292), Épicerie Sucrée(1654), Crèmerie et Produits Laitiers(671), Surgelés(312), Boissons(335). Strongest single Tunisia source found.
A123: menaap | B123: egypt | C123: Seoudi Market | D123: https://seoudisupermarket.com/ | E123: TIER_1B | F123: low | G123: Wave 2 | H123: spider | I123: Generic Magento/GraphQL spider (incl. the mcprod.<domain> pattern) | J123: H_magento | K123: Nuxt + Magento 2 (mcprod.<domain> backend pattern) | L123: retailer_sku | M123: supermarket | N123: EGP | O123: 160 | P123: https://mcprod.seoudisupermarket.com/graphql (Magento GraphQL, POST, no auth) | Q123: curl homepage -> 200, Magento+Nuxt fingerprint. Page source contains apiURL 'https://mcprod.seoudisupermarket.com/graphql'. Direct curl POST (search:'rice') -> 200 clean JSON: 'Al Doha Beyti Rice, Easy Rice Edition - 320g' EGP 25.75, 'Rehana Rice - 1kg' EGP 40.45. | R123: TRUE | S123: Established Cairo chain. Categories incl. Fruits&Vegetables(616), Meat/Poultry/Fishery(216), Dairy/Eggs/Cheese(1385), Cold Cuts&Deli(240), Bakery(471), Frozen(1146), Hot Drinks(1093). Same vendor pattern as Hyper One -- likely a shared Egyptian Magento/Nuxt storefront agency worth checking for other Egyptian retailers.
A124: menaap | B124: egypt | C124: Hyper One | D124: https://www.hyperone.com.eg/ | E124: TIER_1B | F124: low | G124: Wave 2 | H124: spider | I124: Generic Magento/GraphQL spider (incl. the mcprod.<domain> pattern) | J124: H_magento | K124: Nuxt + Magento 2 (mcprod.<domain> backend pattern) | L124: retailer_sku | M124: supermarket | N124: EGP | O124: 155 | P124: https://mcprod.hyperone.com.eg/graphql (Magento GraphQL, POST, no auth) | Q124: Bare domain hyperone.com.eg does not resolve; www. subdomain -> 200, Nuxt SPA. window.__NUXT__.config exposes apiUrl 'https://mcprod.hyperone.com.eg/graphql'. Direct curl POST to that endpoint (search:'rice') -> 200 clean JSON: 'Top Value Luxury Egyptian Rice - 1K' EGP 26.95, 'Meeza Egyptian Rice -1K' EGP 25.95. (The site's own www.hyperone.com.eg/graphql proxy path 400s on malformed body -- use the mcprod subdomain directly.) | R124: TRUE | S124: Large Egyptian-owned hypermarket, welfare-relevant per CSV. Categories incl. Fruits&Vegetables(172), Butchery&Poultry(59), Seafood(28), Dairy/Eggs/Cheese(521), Bakery(125), Herbs&Spices(291), Pickles(37).
A125: menaap | B125: egypt | C125: Gourmet Egypt | D125: https://gourmetegypt.com/ | E125: TIER_1B | F125: low | G125: Wave 2 | H125: spider | I125: Generic Magento/GraphQL spider (incl. the mcprod.<domain> pattern) | J125: H_magento | K125: Magento 2 | L125: retailer_sku | M125: supermarket | N125: EGP | O125: 150 | P125: /graphql (Magento GraphQL, POST, no auth) | Q125: curl homepage -> 200, Magento fingerprint. REST /rest/V1/products -> 401 (needs token, expected default). GraphQL POST /graphql (search:'rice') -> 200, clean JSON: 'Kohinoor Basmati Rice' EGP 195, 'Tilda Basmati Rice' EGP 180. categoryList query confirms full-line taxonomy. | R125: TRUE | S125: Premium/imported grocer. Categories: Meat/Poultry/Seafood(380), Bakery(317), Dairy&Eggs(637), Fruits&Vegetables(362), Frozen(568), Food Cupboard(1453), Beverages(871), Desserts(296), Chips&Snacks(469), Chocolate&Sweets(796).
A126: ssa | B126: kenya | C126: Chandarana Foodplus | D126: https://foodplus.co.ke/ | E126: TIER_1B | F126: low | G126: Wave 2 | H126: spider | I126: Generic Magento/GraphQL spider (incl. the mcprod.<domain> pattern) | J126: H_magento | K126: Magento | L126: retailer_sku | M126: supermarket | N126: KES | O126: 150 | P126: /rest/V1/products, /rest/V1/categories | Q126: The CSV's domain (chandaranafoodplus.com) is NXDOMAIN. Real domain foodplus.co.ke resolves and is Magento (not WooCommerce as CSV's platform column claims). GET /rest/V1/categories -> 200, no auth, full taxonomy incl. Fresh Fruits(146)/Fresh Vegetables(291)/Milk Butter Eggs(157)/Yoghurt(306)/Cheese(244)/Fresh Meat(102)/Deli(90), 18,205 products total. GET /rest/V1/products?searchCriteria[pageSize]=3 -> 200, 8KB JSON, sample 'C/CARE SCRUBBING BRUSH HANDLE A14' KES 165. | R126: TRUE | S126: Premium/expatriate chain per CSV; deepest single-source taxonomy verified in this shard. Domain correction is the key finding -- CSV's chandaranafoodplus.com does not resolve at all.
A127: lac | B127: panama | C127: Riba Smith | D127: https://www.ribasmith.com/ | E127: TIER_1B | F127: low | G127: Wave 2 | H127: spider | I127: Generic Magento/GraphQL spider (incl. the mcprod.<domain> pattern) | J127: H_magento | K127: Magento 2 | L127: retailer_sku | M127: supermarket | N127: USD | O127: 150 | P127: /graphql | Q127: POST /graphql {products(search:"arroz",pageSize:5){...}} -> HTTP 200 JSON. Sample: 'ARROZ PELIN ARROZ ESPECIAL 20 LBS' USD 16.48. | R127: FALSE | S127: Full-line premium PA chain; GraphQL open, no auth required for product search.
A128: lac | B128: dominican_republic | C128: Supermercados Nacional | D128: https://www.supermercadosnacional.com/ | E128: TIER_1B | F128: low | G128: Wave 2 | H128: spider | I128: Generic Magento/GraphQL spider (incl. the mcprod.<domain> pattern) | J128: H_magento | K128: Magento 2 | L128: retailer_sku | M128: supermarket | N128: DOP | O128: 150 | P128: /graphql | Q128: POST /graphql {products(search:"arroz",pageSize:5){...}} -> HTTP 200 JSON. Sample: 'Arroz Selecto Líder 10 Lb' DOP 327.95. | R128: FALSE | S128: Full-line DR chain, GraphQL open.
A129: lac | B129: curacao | C129: Van den Tweel Supermarket | D129: https://shopvdtcuracao.com/ | E129: TIER_1B | F129: low | G129: Wave 2 | H129: spider | I129: Generic Magento/GraphQL spider (incl. the mcprod.<domain> pattern) | J129: H_magento | K129: Magento 2 | L129: retailer_sku | M129: supermarket | N129: ANG | O129: 140 | P129: /graphql | Q129: POST /graphql {products(search:"melk",pageSize:5){...}} -> HTTP 200 JSON. Sample: 'AH Volle melk' ANG 3.29; also 'AH Magere melk' ANG 2.89, 'AH Halfvolle melk' ANG 2.89. | R129: FALSE | S129: Full-line CW chain (dairy confirmed), Albert Heijn-sourced private label suggests Dutch supply chain.
A130: lac | B130: british_virgin_islands | C130: RiteWay Food Markets | D130: https://www.riteway.vg/ | E130: TIER_1A | F130: low | G130: Wave 2 | H130: spider | I130: Generic Magento/GraphQL spider (incl. the mcprod.<domain> pattern) | J130: H_magento | K130: Magento 2 (custom 'Roadtown' theme) | L130: retailer_sku | M130: supermarket | N130: USD | O130: 130 | P130: /shop-groceries.html (SSR category listing) | Q130: GET /shop-groceries.html -> HTTP 200, 1.9MB SSR HTML with real Magento product-item cards. Sample product names: 'Fresh Ground Beef', 'Pork Tenderloin', 'Extra Sharp Cheddar Bar', 'Bakerly Brioche Hot Dog Buns'. Prices in same page: $4.99, $8.99, $39.99, $24.99, $7.99 (data-price-amount attrs). GraphQL endpoint (/graphql) returns HTTP 404 via the Varnish edge — GraphQL module likely disabled — but SSR category pages carry full name+price so Tier 1A applies instead. | R130: FALSE | S130: 60-year BVI chain, 9 stores, dedicated online-ordering platform ('RiteWay Online') with next-day delivery.
A131: lac | B131: jamaica | C131: Virtual Mart Jamaica | D131: https://www.virtualmartja.com/ | E131: TIER_1A | F131: low | G131: Wave 2 | H131: spider | I131: Generic Magento/GraphQL spider (incl. the mcprod.<domain> pattern) | J131: H_magento | K131: Magento | L131: retailer_sku | M131: supermarket | N131: JMD | O131: 100 | P131: SSR HTML Magento listing/PDP (data-price-amount attrs) | Q131: curl 200/225KB (Magento). data-price-amount price blocks confirmed, e.g. J$2,471.29 special-price product (id 106209). CSV notes groceries plus hardware/business-supplies categories. | R131: TRUE | S131: Mixed grocery + hardware/household catalog; F&B is a subset of a broader general-merchandise store.
... A136: eca | B136: italy | C136: Conad | D136: https://spesaonline.conad.it/ | E136: TIER_1A | F136: low | G136: Wave 3 | H136: spider | I136: One bespoke spider or fetcher per source | J136: Z_bespoke | K136: Custom (Sapo-family) | L136: retailer_sku | M136: supermarket | N136: EUR | O136: 170 | P136: /p/<slug>--<id> | Q136: GET / -> 200, 475KB, Sapo/Next hybrid. 15 unique real /p/<slug>--<id> product links on the homepage alone, spanning mozzarella, organic eggs, free-range eggs, water, chicken breast, carrots, toilet paper. EUR prices in SSR HTML (6,55 €, 2,49€, 5,24 €, 1,99€ ...). | R136: TRUE | S136: Largest Italian chain by share per CSV. Homepage alone already spans dairy, eggs, fresh meat, fresh produce, beverages, non-food -- strong full-line signal.
A137: eap | B137: malaysia | C137: KPDNHEP PriceCatcher (data.gov.my) | D137: https://storage.data.gov.my/pricecatcher/ | E137: TIER_1B | F137: low | G137: Wave 3 | H137: fetcher | I137: One bespoke spider or fetcher per source | J137: Z_bespoke | K137: Custom (static gov open-data bucket, no auth, no rate limit hit) | L137: official_avg | N137: MYR | O137: 160 | P137: /pricecatcher/pricecatcher_YYYY-MM.csv + /pricecatcher/lookup_item.csv (+ presumably lookup_premise.csv) | Q137: GET https://storage.data.gov.my/pricecatcher/pricecatcher_2026-08.csv -> 200, 8.9MB CSV, 345,029 rows (date,premise_code,item_code,price) for August 2026 alone; monthly files exist back to program start (pricecatcher_YYYY-MM.csv, also daily YYYY-MM-DD variants and a *_preview.parquet). Companion GET .../lookup_item.csv -> 200, 758-row item master (item_code,item,unit,item_group,item_category). Sample: item_code=1 'AYAM BERSIH - STANDARD' unit=1kg; premise_code=2, 2026-08-01, price=MYR 11.00. | R137: FALSE | S137: KPDNHEP's official daily price-monitoring program across 500+ registered premises nationwide (wet markets, supermarkets, minimarkets, hypermarkets), 758 SKUs total. Item-group breakdown: AYAM(10, chicken), DAGING(32, meat), BAHAN LAUT(38, fresh seafood), IKAN DARAT(4, freshwater fish), IKAN DALAM TIN(11, canned fish), HASIL LAUT KERING(4, dried seafood), SAYUR-SAYURAN(40, vegetables) + BAWANG(11, onions) + UBI KENTANG(3, potato), BUAH-BUAHAN(17, fruit), BERAS(19, rice), TEPUNG(8, flour), MEE/BIHUN/KUEY TEOW(28+3+2, noodles), MINYAK DAN LEMAK(39, oils/fats), TELUR(11, eggs), SUSU BAYI(20)+KRIMER DAN SUSU TEPUNG(23, dairy/milk powder), KACANG(7, nuts/pulses), REMPAH RATUS berbungkus+tidak(30+18, spices/condiments), KICAP DAN SOS(20, sauces), GULA(4, sugar), MINUMAN(47)+TERSEDIA MINUM(25, beverages) -- roughly 600 of the 758 items are food/beverage; the remainder (toiletries, stationery, diapers) rides the same monitoring program and is excluded downstream by the food gate. True whole-catalog walker: bulk monthly file, no pagination, no auth. Malaysia currently has zero official_avg/wholesale manifest in the repo -- this closes that gap outright and is the single strongest source found this session.
A138: eca | B138: malta | C138: PaviPama | D138: https://www.pavipama.com.mt/ | E138: TIER_1B | F138: low | G138: Wave 3 | H138: spider | I138: One bespoke spider or fetcher per source | J138: Z_bespoke | K138: Custom | L138: retailer_sku | M138: supermarket | N138: EUR | O138: 160 | P138: /api/cli/ecommerce/products/featured?p=0&store= (also /api/cli/categories) | Q138: curl 200 (after -L to /app/), Playwright network sniff found open API https://pavipama.com.mt/api/cli/ecommerce/products/featured?p=0&store= -> plain curl with Origin/Referer headers returns HTTP 200, 32.8KB JSON, 20 products/page. Sample: 'ACQUA FRIZZANTE 500ML' price 0.25 EUR, brand CONAD. /api/cli/categories returns 23 top-level categories: CONFECTIONERY, FRUIT & VEG, DELICATESSEN, FISH, BUTCHER, FROZEN, CHILLED, BABY, PERSONAL CARE, PASTA SHOP, FOODS, CELLAR, BAKERY, BEVERAGES, PETSHOP, CLEANING, HEALTH, etc. | R138: TRUE | S138: CSV URL (pavishopping.com) was DEAD (NXDOMAIN). Correct current domain found via WebSearch: pavipama.com.mt. Genuinely full-line: fruit&veg, fish, butcher, frozen, chilled, bakery, beverages, cellar, pasta shop confirmed as real top-level categories.
A139: eca | B139: armenia | C139: Parma | D139: https://parma.am/en/ | E139: TIER_1A | F139: low | G139: Wave 3 | H139: spider | I139: One bespoke spider or fetcher per source | J139: Z_bespoke | K139: Custom (Next.js) | L139: retailer_sku | M139: supermarket | N139: AMD | O139: 160 | P139: /en/product/shop?slug=<category>, /en/product/category?slug=<id> | Q139: GET /en/product/shop?slug=only-in-parma -> 200, 539KB HTML. Full category tree (baby-food, alcoholic-beverages, bakery, beef, basturma-sudjuk, battery...). Server-rendered dram prices in raw HTML: e.g. 233 է, 10387 է, 8514 է. | R139: TRUE | S139: Full grocery taxonomy incl. baby food, alcohol, bakery, fresh/cured meat (basturma). No login/geo wall hit.
A140: sar | B140: sri_lanka | C140: Glomark | D140: https://glomark.lk/ | E140: TIER_1A | F140: low | G140: Wave 3 | H140: spider | I140: One bespoke spider or fetcher per source | J140: Z_bespoke | K140: Custom PHP (ZENEDGE-fronted) | L140: retailer_sku | M140: supermarket | N140: LKR | O140: 160 | Q140: curl 200/1.14MB SSR HTML on /shop-now. 102 distinct subcategory URLs (/<path>/c/<id> and /<path>/<sub>/sc/<id>) spanning bakery(bread,buns,cake,cookies,savoury,sweet), beverages(coffee,tea,water,juices,malt,soft-drinks,sport/energy), chilled(cheese,cream,curd,desserts,pasteurized-milk,ready-to-cook,spreads,yogurt), fresh(fish: fresh-water+sea; fruits: imported+local; meat: beef,lamb,mutton,pork,poultry,ready-to-cook,value-added; vegetable: exotic,low-country,up-country), frozen(ready-to-cook,ready-to-eat,processed fish/meat/veg-fruit), grocery, household, pharmaceuticals. PDP confirmed: 'Banno Basmati Biriyani Rice 500G' Rs.250 (h1 + price both present, 767KB page). | R140: FALSE | S140: Best single find of this shard -- 'Sri Lanka's first global market', a genuine full-line supermarket (fresh meat by cut, two fish types, imported+local fruit, three vegetable tiers) served entirely over plain SSR HTML with no WAF encountered. Should be the first onboarding priority for Sri Lanka.
A141: lac | B141: bolivia | C141: Hipermaxi | D141: https://www.hipermaxi.com/ | E141: TIER_1A | F141: low | G141: Wave 3 | H141: spider | I141: One bespoke spider or fetcher per source | J141: Z_bespoke | K141: Next.js/Custom | L141: retailer_sku | M141: supermarket | N141: BOB | O141: 160 | P141: SSR HTML (no API needed) | Q141: curl 200/791KB, Next.js SSR. Prices server-rendered directly in HTML with schema-labelled blocks: 'Carne Molida de Segunda' (ground beef) Bs 40.50; 'Coca Cola Original 3 L' Bs 17.10. Full meat + beverage + grocery categories visible. | R141: TRUE | S141: Largest Bolivian supermarket chain per CSV; strongest Bolivia source, prices render server-side with no API needed.
A142: eca | B142: romania | C142: Freshful by eMAG | D142: https://www.freshful.ro/ | E142: TIER_1A | F142: low | G142: Wave 3 | H142: spider | I142: One bespoke spider or fetcher per source | J142: Z_bespoke | K142: Next.js | L142: retailer_sku | M142: supermarket | N142: RON | O142: 150 | P142: SSR HTML, no API needed | Q142: curl 200, 566KB SSR HTML (__NEXT_DATA__), real prices in raw HTML: '12,99 lei', '20,00 Lei', '56,99 Lei', '47,98 Lei', '23,03 Lei' | R142: TRUE | S142: Matches the brief's own worked example. Fresh produce with named local-producer attribution per CSV notes.
A143: eca | B143: kazakhstan | C143: Galmart | D143: https://galmart.kz/ | E143: TIER_1A | F143: low | G143: Wave 3 | H143: spider | I143: One bespoke spider or fetcher per source | J143: Z_bespoke | K143: Custom | L143: retailer_sku | M143: supermarket | N143: KZT | O143: 150 | P143: SSR HTML | Q143: curl 200, 142KB, real prices in raw HTML: '2 650₸', '2 850₸', '1 456₸', '1 835₸', '2 310₸', '2 100₸' | R143: TRUE | S143: Premium Astana chain with deep dairy taxonomy per CSV (mare/camel/goat milk as separate categories).
A144: eca | B144: slovenia | C144: Mercator Online | D144: https://mercatoronline.si/ | E144: TIER_1A | F144: low | G144: Wave 3 | H144: spider | I144: One bespoke spider or fetcher per source | J144: Z_bespoke | K144: Custom | L144: retailer_sku | M144: supermarket | N144: EUR | O144: 150 | P144: SSR HTML | Q144: curl 200, 767KB, real prices in raw HTML: '150,00 EUR', '60,00 EUR', '3,99€' | R144: TRUE | S144: 18,000+ products, delivery to 99% of Slovenian addresses per CSV; PC30 (30-day-lowest, omnibus) field noted but not verified in this pass.
A145: eca | B145: estonia | C145: Prisma Estonia | D145: https://www.prismamarket.ee/ | E145: TIER_1A | F145: low | G145: Wave 3 | H145: spider | I145: One bespoke spider or fetcher per source | J145: Z_bespoke | K145: Next.js | L145: retailer_sku | M145: supermarket | N145: EUR | O145: 150 | P145: SSR HTML / __NEXT_DATA__ JSON blob | Q145: curl 200, 367KB, Next.js SSR (__NEXT_DATA__ valid JSON with props.pageProps), real prices in raw HTML: '1,85 €', '12,33 €', '3,28 €' | R145: TRUE | S145: -
A146: eca | B146: armenia | C146: Supermarket.am | D146: https://supermarket.am/en/ | E146: TIER_1A | F146: low | G146: Wave 3 | H146: spider | I146: One bespoke spider or fetcher per source | J146: Z_bespoke | K146: Custom | L146: retailer_sku | M146: supermarket | N146: AMD | O146: 150 | P146: /en/products/_<id>/ | Q146: GET /en/products/_723530/ -> 200, 399KB. PDP h1 'Pasta Zara No. 50 500g', span.priceValue = '710 dr'. Category tree via /en/products/_<id>/ product links visible on homepage. | R146: TRUE | S146: Weight-based items sliced to order per CSV note; PDP price rendered server-side.
A147: eca | B147: bulgaria | C147: T Market Online | D147: https://tmarketonline.bg/ | E147: TIER_1A | F147: low | G147: Wave 3 | H147: spider | I147: One bespoke spider or fetcher per source | J147: Z_bespoke | K147: Custom | L147: retailer_sku | M147: supermarket | N147: BGN/EUR | O147: 150 | P147: SSR product pages | Q147: GET /product/avokado-izrael -> h1 'Avokado, br.' (avocado), price '1,39 lv' / '0,71 EUR'. Real /product/<slug> and /category/<slug> links throughout homepage. | R147: TRUE | S147: Maxima-group chain; CSV flags unusually good fresh + LOCAL Bulgarian lines (rose tomatoes, Madzharov cheese, banitsa sheets).
A148: eca | B148: finland | C148: Prisma | D148: https://www.prisma.fi/ | E148: TIER_1A | F148: low | G148: Wave 3 | H148: spider | I148: One bespoke spider or fetcher per source | J148: Z_bespoke | K148: Custom (Next.js) | L148: retailer_sku | M148: supermarket | N148: EUR | O148: 150 | P148: SSR + __NEXT_DATA__ | Q148: GET / -> 200, 1.04MB, __NEXT_DATA__ present, real EUR prices rendered server-side (e.g. '5 439,15 €' owner-price banner item). Same S-Group family as s-kaupat.fi. Grocery category page not separately fetched this round. | R148: TRUE | S148: Homepage sample was a big-ticket appliance, not F&B -- grocery category page needs a follow-up fetch to confirm F&B depth directly, but platform/SSR confirmed working.
A149: eca | B149: iceland | C149: Kronan | D149: https://www.kronan.is/ | E149: TIER_1B | F149: low | G149: Wave 3 | H149: spider | I149: One bespoke spider or fetcher per source | J149: Z_bespoke | K149: Custom | L149: retailer_sku | M149: supermarket | N149: ISK | O149: 150 | P149: SSR embedded JSON at /vara/<slug> | Q149: GET / -> 200, 479KB. Embedded product JSON in SSR HTML: {"slug":"100273243-isey-skyr-solmyrkvi",...,"categoryTag":"05-05-01-skyr",...,"discountedPrice":330,"priceInfo":"170 gr. - 1.941 kr. / kg"} (Isey skyr yoghurt, 330 kr). Also saw Red Bull, Floridana juice, /vara/<id-slug> product links throughout. | R149: TRUE | S149: Internal category codes (e.g. 05-05-01-skyr) look pre-classified -- useful mapping hint. ISK has no minor units so price values are literal kr.
A150: eca | B150: croatia | C150: Plodine | D150: https://www.plodine.hr/ | E150: TIER_1A | F150: low | G150: Wave 3 | H150: spider | I150: One bespoke spider or fetcher per source | J150: Z_bespoke | K150: Next.js | L150: retailer_sku | M150: supermarket | N150: EUR | O150: 150 | P150: SSR homepage/category HTML | Q150: GET -> 200, 86KB SSR (Next.js). Sample: h2 'Svježi black Angus steak' near 9,49€; also 4,49€, 12,99€ visible. | R150: TRUE | S150: National chain, carried by all 4 Croatian aggregators for cross-validation.
A151: eca | B151: croatia | C151: Kaufland Croatia | D151: https://www.kaufland.hr/ | E151: TIER_1A | F151: low | G151: Wave 3 | H151: spider | I151: One bespoke spider or fetcher per source | J151: Z_bespoke | K151: Vue/Next hybrid | L151: retailer_sku | M151: supermarket | N151: EUR | O151: 150 | P151: SSR homepage/category HTML | Q151: GET -> 200, 208KB SSR (Vue+Next). Direct price '1,44€' repeated in homepage HTML. Also found a published 'Popis maloprodajnih cijena' (retail price list) page at /akcije-novosti/popis-mpc.html (200, 114KB) but it is an explanatory HTML page, not a raw CSV/XML download. | R151: TRUE | S151: Overturns shard's D-tier 'SUSPECT' prediction -- plain curl works cleanly, no WAF encountered.
A152: eca | B152: moldova | C152: Linella.md | D152: https://linella.md/ | E152: TIER_1A | F152: low | G152: Wave 3 | H152: spider | I152: One bespoke spider or fetcher per source | J152: Z_bespoke | K152: Custom | L152: retailer_sku | M152: supermarket | N152: MDL | O152: 150 | P152: SSR category HTML (/ro/catalog) | Q152: GET -> 200, 864KB SSR. class='price-products-catalog-content__main 10.59 9.49' style list/discount pairs directly in listing HTML. | R152: TRUE | S152: 206 stores, 14,500+ products per shard; list+promo price pairs and per-0.5kg fresh pricing.
... A164: eca | B164: spain | C164: Ulabox | D164: https://www.ulabox.com/ | E164: TIER_1B | F164: low | G164: Wave 3 | H164: spider | I164: One bespoke spider or fetcher per source | J164: Z_bespoke | K164: Next.js | L164: retailer_sku | M164: supermarket | N164: EUR | O164: 140 | P164: page-embedded JSON (Next.js hydration) | Q164: GET -> 200, 347KB. Embedded JSON 'price':9.95 and 'price':12.45 in page source. | R164: TRUE | S164: Bespoke storefront, prices present in initial page payload.
A165: sar | B165: maldives | C165: WHIM | D165: https://whim.com.mv/ | E165: TIER_1A | F165: low | G165: Wave 3 | H165: spider | I165: One bespoke spider or fetcher per source | J165: Z_bespoke | K165: Custom (not yet fingerprinted beyond SSR HTML) | L165: retailer_sku | M165: supermarket | N165: MVR | O165: 140 | Q165: GET /shop -> 200, 192KB SSR HTML. ~55 category links found: dairy/eggs/milk (butter, cheese, milk, yogurt), drinks (chocolate-malted, coffee, cordials, juices, non-alcoholic, soft drinks, tea incl. flower/herbal, water), fresh-fruits-vegetables, frozen (food, meat, seafood, vegetables, ice-cream), chilled-ham-sausage, maldivian-smoked-dried-fish-related-products, pantry (baking, breads incl. flatbread/wraps, breakfast/cereals, canned foods/fruits, coconut products, condiments incl. Maldivian condiments and pickles/chutney, dried fruit, herbs/legumes/spices, jam/spreads/honey, noodles, oils/vinegar, pasta, rice/multigrains/quinoa, sauces, snacks, sugar/syrups), vegan, baby food. | R165: FALSE | S165: This is the already-onboarded 'whim_mv' spider (manifest lists it as channel: supermarket on Odoo, PDPs at /shop/<slug>-<id>) -- re-verified category breadth here since it anchors the whole Maldives estimate. Genuinely the closest thing to a full-line supermarket found for Maldives: strong pantry/dairy/drinks/frozen breadth including a Maldivian-specific dried/smoked fish line, but NO fresh meat and NO fresh fish category (only frozen meat/seafood + chilled ham/sausage) -- matches the island-import-dependent profile the brief predicted.
A166: ssa | B166: zimbabwe | C166: SPAR Zimbabwe | D166: https://www.spar.co.zw/products | E166: TIER_1A | F166: low | G166: Wave 3 | H166: spider | I166: One bespoke spider or fetcher per source | J166: Z_bespoke | K166: Custom (ASP.NET WebForms + AngularJS) | L166: retailer_sku | M166: supermarket | N166: USD | O166: 140 | P166: SSR HTML listing at /products (paginated/searchable via query string, not yet mapped) | Q166: GET /products -> 200, 134KB. Real ASP.NET+AngularJS-enhanced SSR product listing: 'MAZOE ORANGE CRUSH ORIGINAL 2L' -> USD$4.00, 'RAHA COOKING OIL 2L' visible with product-links markup, canonical /products/{id}/{slug} PDP URLs. | R166: TRUE | S166: USD staples (maize meal, cooking oil, sugar) confirmed live and dollarised per prior research; full SPAR chain.
A167: eca | B167: romania | C167: MegaMarket.ro | D167: https://www.megamarket.ro/ | E167: TIER_1A | F167: low | G167: Wave 3 | H167: spider | I167: One bespoke spider or fetcher per source | J167: Z_bespoke | K167: Custom | L167: retailer_sku | M167: supermarket | N167: RON | O167: 130 | P167: SSR HTML | Q167: curl 200, 148KB, real prices in raw HTML: '8,09 lei', '0,81 lei', '13,49 lei', '33,94 lei', '3,57 lei' | R167: TRUE | S167: CSV notes per-category item counts (conserve 278, paste 53) as a completeness check.
A168: eca | B168: austria | C168: MPreis | D168: https://www.mpreis.at/ | E168: TIER_1A | F168: low | G168: Wave 3 | H168: spider | I168: One bespoke spider or fetcher per source | J168: Z_bespoke | K168: Custom + Algolia | L168: retailer_sku | M168: supermarket | N168: EUR | O168: 130 | P168: SSR HTML (Algolia search key not yet extracted) | Q168: curl 200, 640KB, Algolia detected, real prices in raw HTML: '0,78 €', '1,57 €', '1,56 €', '3,99 €', '5,99 €', '12,09 €' | R168: FALSE | S168: Net-new discovery (not in CSV shard) - Austria's 3 CSV rows all failed probing, this fills the gap. Tyrol-based regional chain, ~150 stores nationwide-adjacent.
A169: eca | B169: iceland | C169: Heimkaup | D169: https://www.heimkaup.is/ | E169: TIER_1B | F169: low | G169: Wave 3 | H169: spider | I169: One bespoke spider or fetcher per source | J169: Z_bespoke | K169: Custom | L169: retailer_sku | M169: supermarket | N169: ISK | O169: 130 | P169: SSR embedded JSON at /p/<slug>-<id> | Q169: GET / -> 200, 379KB. 49 unique /p/<slug>-<id> product links (beer, soft drinks, wine, ice cream). Embedded JSON for Pepsi Max 12x330ml: "price":129900,"commodityGroup":{"name":"GROCERY"}. | R169: TRUE | S169: MINOR-UNIT TRAP: price field is in hundredths (129900 -> 1,299.00 kr for a 12-pack), not literal ISK like Kronan. Verify against rendered page before trusting raw field.
A170: eca | B170: kosovo | C170: Maxi E-Shop | D170: https://maxiks.shop/ | E170: TIER_1A | F170: low | G170: Wave 3 | H170: spider | I170: One bespoke spider or fetcher per source | J170: Z_bespoke | K170: Custom | L170: retailer_sku | M170: supermarket | N170: EUR | O170: 130 | P170: /product/<slug> | Q170: GET / -> 200, 390KB. Real product card: h3.product-title 'Faculet e lagur Fresh x 52cope' (wet wipes), h4.product-price '1.79€'. Full supermarket taxonomy visible in nav (Ushqimore=grocery, Bulmet=dairy, Pije=drinks, Fruta & Perime=fruit&veg, Pjekurina=bakery). | R170: TRUE | S170: 18 Prishtina outlets per CSV; EUR is Kosovo's domestic currency so this passes the currency-authenticity check cleanly.
A171: eca | B171: latvia | C171: Elvi.lv | D171: https://www.elvi.lv/ | E171: TIER_1A | F171: low | G171: Wave 3 | H171: spider | I171: One bespoke spider or fetcher per source | J171: Z_bespoke | K171: Custom | L171: retailer_sku | M171: supermarket | N171: EUR | O171: 130 | P171: SSR homepage/category HTML | Q171: GET -> 200, 73KB SSR. Direct prices 0.89€ / 2.58€ / 2.86€ in homepage HTML. | R171: TRUE | S171: National chain, bespoke storefront, prices render server-side.
A172: eca | B172: latvia | C172: Top! Veikali (toppartika.lv) | D172: https://www.toppartika.lv/ | E172: TIER_1A | F172: low | G172: Wave 3 | H172: spider | I172: One bespoke spider or fetcher per source | J172: Z_bespoke | K172: Custom | L172: retailer_sku | M172: supermarket | N172: EUR | O172: 130 | P172: SSR homepage/category HTML | Q172: GET -> 200, 4.08MB SSR. Direct prices 1.47€ / 1.59€ / 1.98€ in homepage HTML. | R172: TRUE | S172: Very large homepage payload (4MB) -- likely already lists most/all categories server-side.
A173: eca | B173: moldova | C173: Mega Alina | D173: https://www.megaalina.md/ | E173: TIER_1A | F173: low | G173: Wave 3 | H173: spider | I173: One bespoke spider or fetcher per source | J173: Z_bespoke | K173: Custom | L173: retailer_sku | M173: supermarket | N173: MDL | O173: 130 | P173: SSR category HTML (/ro/catalog/...) | Q173: GET -> 200, 673KB SSR. Direct catalog prices '5.99 MDL' / '4.99 MDL' repeated in listing HTML. | R173: TRUE | S173: Strike-through discount pairs across food, dairy, juice, household.
A174: eca | B174: spain | C174: Cartio | D174: https://cartio.es/landing/ | E174: TIER_1A | F174: low | G174: Wave 3 | H174: spider | I174: One bespoke spider or fetcher per source | J174: Z_bespoke | K174: Custom | L174: retailer_sku | M174: aggregator | N174: EUR | O174: 130 | P174: SSR landing HTML | Q174: GET -> 200, 120KB SSR. Direct prices '6,99€' / '0,31€' / '1,95€' in HTML. | R174: TRUE | S174: Basket-level comparison across Mercadona/Carrefour/Lidl/Alcampo; shard notes an account requirement but the landing page itself rendered prices without one.
A175: ssa | B175: benin | C175: NolMarket | D175: https://nolmarket.com/ | E175: TIER_1B | F175: low | G175: Wave 3 | H175: spider | I175: One bespoke spider or fetcher per source | J175: Z_bespoke | K175: Custom (Laravel + React) | L175: retailer_sku | M175: supermarket | N175: XOF | O175: 130 | P175: /api/products (paginate ?page=N) | Q175: React SPA (CRA, div#root) with a fully open Laravel JSON API. GET https://nolmarket.com/api/products -> 200, paginated (24/page, 121 total_pages, 2,887 total products), no auth needed. Sample: 'Patee au boeuf PRIX MINI' 700 FCFA (Animalerie). Sampled pages 1,5,10,20,40,60,80,100,120 -> categories span Animalerie, Boissons (Biere, Champagnes, Cidre, Jus de fruits, Spiritueux, Vins), Epicerie (Conserves-plats cuisines, Petit Dejeuner, Produits de base), Produits Frais (Fromages-Charcuterie-Beurre, Fruits secs et frais, Pains-Viennoiseries, Viandes-Poissons-Crustasses-Oeufs, Yaourt/Creme fraiche), Produits Locaux (Amuse gueule, Boissons locales, Epices/Huile locale, Graine/Legume sec, Poudre/Farine/Bouillie, Produits cosmetiques, The/Cafe/Miel/Confiture). | R175: TRUE | S175: Best single retail source found across all 8 countries this pass -- genuinely full-line (fresh + meat/fish/eggs + dairy + bakery + local staples) with a dedicated 'Produits Locaux' section that carries exactly the local-grain/flour/oil forms that block chain supermarkets do not.
A176: eca | B176: romania | C176: VivoMarket.ro | D176: https://www.vivomarket.ro/ | E176: TIER_1A | F176: low | G176: Wave 3 | H176: spider | I176: One bespoke spider or fetcher per source | J176: Z_bespoke | K176: Custom | L176: retailer_sku | M176: supermarket | N176: RON | O176: 120 | P176: SSR HTML | Q176: curl 200, 1.9MB, real prices in raw HTML: '51,82 Lei', '28,90 Lei', '21,60 Lei', '26,21 Lei', '13,18 Lei' | R176: TRUE | S176: Carries both retail and HoReCa lines per CSV; tag channel separately.
A177: eca | B177: kazakhstan | C177: GroceryKZ | D177: https://grocerykz.com/ | E177: TIER_1A | F177: low | G177: Wave 3 | H177: spider | I177: One bespoke spider or fetcher per source | J177: Z_bespoke | K177: Custom | L177: retailer_sku | M177: supermarket | N177: KZT | O177: 120 | P177: SSR HTML | Q177: curl 200, 164KB, real prices in raw HTML: '3 750 KZT', '4 650 KZT', '2 450 KZT', '2 250 KZT', '16 900 KZT' | R177: TRUE | S177: English interface per CSV, per-piece pricing with stock flags.
... A198: ssa | B198: sudan | C198: HyperSale | D198: https://www.hypersale.sd/ | E198: TIER_1A | F198: low | G198: Wave 3 | H198: spider | I198: One bespoke spider or fetcher per source | J198: Z_bespoke | K198: Custom (Laravel) | L198: retailer_sku | M198: supermarket | N198: SDG | O198: 45 | P198: /category/hypersale-super-market | Q198: GET /category/hypersale-super-market -> HTTP 200, 430KB SSR HTML with real product links + prices. Samples: 'Al Hamwi Coffee Classic Cardamom 180gm' 24.000 SDG, 'Frozina Pomme Frite Potatoes 25gm' 23.000 SDG, 'Karim Coconut Milk 400ml' 7.500 SDG, 'Lotus Biscoff Original 250gm' price present, 'Frozen Strawberry 1kg' present. | R198: TRUE | S198: GOTCHA: prices render as '24.000SDG' -- verify whether '.' is a thousands separator (SDG 24,000) or a decimal point before scaffolding; eyeball against a known SDG price level. Dedicated grocery vertical confirmed distinct from the general marketplace (electronics/fashion/beauty also on this domain).
A199: ssa | B199: guinea | C199: Beryz | D199: https://www.beryz.com/fr/alimentation | E199: TIER_1A | F199: low | G199: Wave 3 | H199: spider | I199: One bespoke spider or fetcher per source | J199: Z_bespoke | K199: Custom | L199: retailer_sku | M199: supermarket | N199: GNF | O199: 40 | Q199: curl -> HTTP 200, 104.5KB SSR HTML. Confirmed product card: 'Huile de palme rouge' -- 'Fatou Camara -- Conakry' -- '8 000 GNF/litre', tagged category 'Huiles'. | R199: TRUE | S199: Confirms CSV's 'STRONG' rating and dual retail/wholesale pricing claim structurally (though the sampled card shows only one price point). Per-vendor + per-region (Conakry/Labe/Kindia/Boke) tagging is unusually valuable for spatial analysis.
A200: sar | B200: nepal | C200: Kalimati Fruits and Vegetable Market Development Board (wholesale) | D200: https://kalimatimarket.gov.np/price | E200: TIER_1B | F200: low | G200: Wave 3 | H200: fetcher | I200: One bespoke spider or fetcher per source | J200: Z_bespoke | K200: Custom (Laravel, DataTables.js UI but server renders HTML rows on POST) | L200: wholesale reference | M200: official_avg | N200: NPR | O200: 35 | P200: /price (GET for token, POST with datePricing param) | Q200: GET /price (grab CSRF token '_token' + session cookie from hidden form field) then POST same URL with form fields _token, datePricing=YYYY-MM-DD (X-Requested-With: XMLHttpRequest header not even required) -> 200, 30821 bytes HTML fragment, 98 commodity rows/day. Sample: 'गोलभेडा ठूलो(नेपाली)' (Tomato, large, local) के.जी. रू ४०.००-५०.०० (avg रू ४५). No auth beyond the CSRF handshake. | R200: FALSE | S200: Whole-catalog walker: 98 commodities/day (many varieties per crop e.g. 3 tomato types, 4 potato types) covering nearly all fresh vegetables + fruits traded through Nepal's largest wholesale market. min/max/avg per unit. Walk daily by iterating datePricing for history. This is the single highest-value new find in the shard.
A201: ssa | B201: angola | C201: Kiwaba Online | D201: https://www.kiwaba.online/ | E201: TIER_1B | F201: low | G201: Wave 3 | H201: spider | I201: One bespoke spider or fetcher per source | J201: Z_bespoke | K201: Custom (React/Vite + Supabase) | L201: retailer_sku | M201: supermarket | N201: AOA | O201: 30 | P201: https://{project-ref}.supabase.co/rest/v1/products (apikey header required, key lives in the site's JS bundle) | Q201: React SPA (Vite, div#root) backed by open Supabase REST API. Anon JWT key found embedded in /assets/index-D4PaSevu.js. GET https://aljtwptkvhazymmtiqmx.supabase.co/rest/v1/products?select=id,name,price,unit,category_id&active=eq.true&limit=1500 -H 'apikey: <anon-jwt>' -> 200, 302 active products. Sample: 'LABIO DE VACA cax 15kg' (cow lip, wholesale case) Kz 48,500.00. Categories: Carnes, Peixe & Marisco, Hortícolas, Cereais & Grãos, Bebidas, Fubas e farinhas, Lacticínios (plus non-food: Saúde e beleza, Medicamentos, Detergentes, Roupa). | R201: TRUE | S201: Mid-size mixed grocery+pharmacy catalog (302 active items). Confirms CSV's 'STRONG' verdict. Food categories are real but not deep per-category (single digits to low tens of SKUs each).
